Workbook

Sheet 持仓总览
B2: 华夏全球科技先锋 · 单笔交易账本
B3: 005698 / QDII A人民币 模板更新：2026-09-28 支持利润优先与本金优先两种记账模式
B5: 估值净值日期 | C5: =IF(AND(AND(ISNUMBER(C37),C37>0,C37=INT(C37),ISNUMBER(F37),F37>0),OR(NOT(AND(ISNUMBER(C19),C19>0,ISNUMBER(逐笔交易!AB506),逐笔交易!AB506>0)),C37>=C19)),C37,IF(AND(ISNUMBER(C19),C19>0,ISNUMBER(逐笔交易!AB506),逐笔交易!AB506>0),C19,"")) -> 46288 | E5: 估值单位净值 | F5: =IF(AND(AND(ISNUMBER(C37),C37>0,C37=INT(C37),ISNUMBER(F37),F37>0),OR(NOT(AND(ISNUMBER(C19),C19>0,ISNUMBER(逐笔交易!AB506),逐笔交易!AB506>0)),C37>=C19)),F37,IF(AND(ISNUMBER(C19),C19>0,ISNUMBER(逐笔交易!AB506),逐笔交易!AB506>0),逐笔交易!AB506,"")) -> 2.8398 | H5: 金额核对容差（元）
B6: 录入提示 | C6: 自动取日期较新的净值；公布净值在下方更新。 | H6: 0.1
B7: 卖出分配模式 | C7: 利润优先 | E7: 切换模式后，重算全部已确认卖出记录。
B8: =IF(逐笔交易!AA506="错误","存在录入问题，请先修正逐笔交易 I 列提示",IF(COUNTIFS(逐笔交易!I7:I506,"已计入")=0,"尚未录入可计入交易",IF(NOT(ISNUMBER(C5)),"估值日期未填写或格式无效，请检查 C5",IF(OR(C5<=0,C5<>INT(C5)),"估值日期无效，请检查 C5",IF(NOT(ISNUMBER(F5)),"估值单位净值未填写或不是数字，请检查 F5",IF(F5<=0,"估值单位净值须大于 0，请检查 F5",IF(C5<逐笔交易!Z506,"估值日期 "&TEXT(C5,"yyyy-mm-dd")&" 早于最近交易 "&TEXT(逐笔交易!Z506,"yyyy-mm-dd")&"；请核对交易日期，或更新同日净值。",IF(H19>0,"历史交易已入账；含原表估算，请核对成交单","已按录入交易更新")))))))) -> 历史交易已入账；含原表估算，请核对成交单
B10: 当前持仓 | E10: 累计收支
B11: 当前持有金额（元） | C11: =IF(AND(AND(逐笔交易!AA506="正常",COUNTIFS(逐笔交易!I7:I506,"已计入")>0),ISNUMBER(C5),ISNUMBER(F5),F5>0,C5>=逐笔交易!Z506),ROUND(逐笔交易!K506*F5,2),"") -> 97360.92 | E11: 累计投入及转入成本 | F11: =IF(AND(逐笔交易!AA506="正常",COUNTIFS(逐笔交易!I7:I506,"已计入")>0),逐笔交易!U506,"") -> 82516.01
B12: 剩余本金（元） | C12: =IF(AND(逐笔交易!AA506="正常",COUNTIFS(逐笔交易!I7:I506,"已计入")>0),逐笔交易!Q506,"") -> 82516.01 | E12: 累计收回金额（元） | F12: =IF(AND(逐笔交易!AA506="正常",COUNTIFS(逐笔交易!I7:I506,"已计入")>0),逐笔交易!V506,"") -> 0
B13: 持有盈亏（元） | C13: =IF(ISNUMBER(C11),ROUND(C11-C12,2),"") -> 14844.91 | E13: 累计提取利润（元） | F13: =IF(AND(逐笔交易!AA506="正常",COUNTIFS(逐笔交易!I7:I506,"已计入")>0),逐笔交易!W506,"") -> 0
B14: 持有盈亏比例 | C14: =IF(AND(ISNUMBER(C13),C12>0),C13/C12,"") -> 0.17990339 | E14: 累计结清亏损（元） | F14: =IF(AND(逐笔交易!AA506="正常",COUNTIFS(逐笔交易!I7:I506,"已计入")>0),逐笔交易!X506,"") -> 0
B15: 当前持有份额 | C15: =IF(AND(逐笔交易!AA506="正常",COUNTIFS(逐笔交易!I7:I506,"已计入")>0),逐笔交易!K506,"") -> 34284.43 | E15: 累计总盈亏（元） | F15: =IF(ISNUMBER(C11),ROUND(C11+F12-F11,2),"") -> 14844.91
B16: 本金状态 | C16: =IF(ISNUMBER(C15),IF(C15=0,"已清仓",IF(C12=0,"本金已收回","仍有本金")),"") -> 仍有本金 | E16: 累计收益率（非年化） | F16: =IF(AND(ISNUMBER(F15),F11>0),F15/F11,"") -> 0.17990339
B18: 已计入笔数 | C18: =COUNTIFS(逐笔交易!I7:I506,"已计入") -> 110 | E18: 待确认／待修正 | F18: =COUNTIFS(逐笔交易!G7:G506,"待确认")+COUNTIFS(逐笔交易!G7:G506,"待修正") -> 0 | H18: 含历史估算（笔）
B19: 最新成交净值日 | C19: =IF(AND(逐笔交易!AA506="正常",COUNTIFS(逐笔交易!I7:I506,"已计入")>0),逐笔交易!Z506,"") -> 46247 | E19: 收益恒等式核对 | F19: =IF(ISNUMBER(F15),IF(ABS(F15-(C13+F13-F14))<0.02,"一致","需检查"),"") -> 一致 | H19: =COUNTIFS(逐笔交易!G7:G506,"历史估算") -> 110
B21: 填写与计算口径
B22: 1. 新增买卖从第 117 行起，仅手填 A:D、F 五项黄色格；按实际成交净值日期升序填写。
B23: 2. 自动金额：买入／定投 = 份额 × 净值 + 手续费；卖出 = 份额 × 净值 − 手续费，保留到分。
B24: 3. 五项采用成交确认单数据，费用为 0 也需填写。确认份额不要再根据金额自行反推。
B25: 4. 五项录入支持买入、定投、卖出、红利再投。现金分红和转换转入需实际金额，不支持五项反推。
B26: 5. 新增记录填完五项且通过 I 列检查即计入，状态与说明自动填写；只录真实成交，不录撤单。
B27: 6. 利润优先：可提利润 = MAX(交易前市值 − 交易前本金 − 赎回费, 0)。到账先提利润，再收本金。
B28: 7. 全部赎回后，未收回的本金记为结清亏损；剩余份额与本金归零，之后买入重新累计本金。
B29: 8. 持有盈亏 = 当前市值 − 剩余本金。盈亏比例 = 持有盈亏 ÷ 剩余本金；本金为 0 时留空。
B30: 9. 累计总盈亏 = 市值 + 累计收回 − 累计投入及转入成本。累计收益率以该成本合计为分母，非年化。
B31: 10. 本金优先：卖出净到账先冲减剩余本金，超出本金才计为提取利润。现金分红仍按利润优先。
B32: 11. 同花顺界面供参考，未确认其内部收益算法。逐笔右侧显示每笔成交后的整个账户状态。
... B36: 历史 110 笔及转入成本按原表保留；已删除用户确认的 9 月 28 日试填交易，最后真实操作仍为 8 月 13 日。
B37: 公布净值日期 | C37: 46288 | E37: 公布单位净值 | F37: 2.8398
B38: 净值来源：华夏基金 https://fund.chinaamc.com/fund/005698/index.shtml（核验 2026-09-28，后续净值需更新）
B39: 公布净值栏需手动更新，不自动联网。历史数据含估算；新增金额反推可能有分位尾差，以成交单为准。

Sheet 逐笔交易
A2: 逐笔交易录入 | J2: 交易后账户明细（公式自动计算）
A3: 新增买卖仅填写黄色五项：净值日期、交易类型、成交净值、确认份额、手续费（无费用填 0）。 | J3: ="当前模式："&持仓总览!C7&"。卖出按所选模式分配；全部赎回时确认未收回本金的亏损。" -> 当前模式：利润优先。卖出按所选模式分配；全部赎回时确认未收回本金的亏损。
A4: 从第 117 行录入已成交记录，填完自动计入。历史 110 笔保留原数据；估值日期另在总览更新。
A6: 净值日期 | B6: 交易类型 | C6: 成交净值 | D6: 确认份额 | E6: 金额／历史转入成本 | F6: 手续费（元） | G6: 状态 | H6: 说明 | I6: 录入检查 | J6: 份额变动 | K6: 交易后份额 | L6: 交易前市值 | M6: 可提取利润 | N6: 本笔提取利润 | O6: 本笔收回本金 | P6: 清仓确认亏损 | Q6: 交易后本金 | R6: 交易后市值 | S6: 交易后盈亏 | T6: 交易后收益率 | U6: 累计投入及转入成本 | V6: 累计收回金额 | W6: 累计提取利润 | X6: 累计结清亏损 | Y6: 累计总盈亏 | Z6: 最近成交净值日 | AA6: 计算链状态 | AB6: 最近成交净值
A7: 45870 | B7: 买入 | C7: 1.937 | D7: 4123.9 | E7: 8000 | F7: 12 | G7: 历史估算 | H7: 原下单 2025-08-01T10:13:48 份额、费用及净值日沿用旧表估算 | I7: =IF(COUNTA(A7:H7)=0,"",IF(OR(OR(OR(G7="撤单",G7="交易失败",G7="交易关闭"),G7="交易失败",G7="交易关闭"),G7="交易失败",G7="交易关闭"),"已排除",IF(G7="待确认","待确认",IF(NOT(OR(G7="已确认",G7="历史估算")),"请选择确认状态",IF(NOT(ISNUMBER(A7)),"缺少有效净值日期",IF(OR(A7<=0,A7<>INT(A7)),"净值日期无效",IF(NOT(OR(OR(B7="买入",B7="定投",B7="转换转入"),B7="卖出",B7="现金分红",B7="红利再投")),"请选择交易类型",IF(NOT(ISNUMBER(C7)),"缺少成交净值",IF(C7<=0,"成交净值须大于零",IF(NOT(ISNUMBER(D7)),"缺少确认份额（分红填0）",IF(NOT(ISNUMBER(E7)),"缺少确认金额（再投填0）",IF(NOT(ISNUMBER(F7)),"缺少手续费（无费用填0）",IF(OR(D7<0,E7<0,F7<0),"份额金额费用不能为负",IF("正常"="错误","前行待修正",IF(A7<0,"日期需按成交顺序递增",IF(AND(B7="现金分红",OR(D7<>0,E7<=0,F7<>0)),"分红填份额0、费用0、正金额",IF(AND(B7="红利再投",OR(D7<=0,E7<>0,F7<>0)),"再投填正份额、金额0、费用0",IF(AND(OR(B7="现金分红",B7="红利再投"),0<=0),"分红或再投前须有持仓",IF(AND(OR(OR(B7="买入",B7="定投",B7="转换转入"),B7="卖出"),OR(D7<=0,E7<=0)),"买卖须填正份额、正金额",IF(AND(B7="卖出",D7>0+0.000001),"卖出份额超过持仓",IF(AND(OR(B7="买入",B7="定投",B7="转换转入"),F7>=E7),"申购费不能达到总支出",IF(NOT(ISNUMBER(持仓总览!$H$6)),"请填写金额核对容差",IF(持仓总览!$H$6<0,"金额核对容差不能为负",IF(NOT(OR(持仓总览!$C$7="利润优先",持仓总览!$C$7="本金优先")),"请选择卖出分配模式",IF(AND(OR(B7="买入",B7="定投",B7="转换转入"),ABS(E7-F7-C7*D7)>持仓总览!$H$6),"买入金额与份额净值不符",IF(AND(B7="卖出",ABS(E7+F7-C7*D7)>持仓总览!$H$6),"到账加费用与赎回市值不符","已计入")))))))))))))))))))))))))) -> 已计入 | J7: =IF(AA7="正常",IF(I7="已计入",IF(OR(OR(B7="买入",B7="定投",B7="转换转入"),B7="红利再投"),D7,IF(B7="卖出",-D7,0)),0),"") -> 4123.9 | K7: =IF(AA7="正常",ROUND(0+J7,6),"") -> 4123.9 | L7: =IF(I7="已计入",ROUND(0*C7,2),"") -> 0 | M7: =IF(I7="已计入",IF(B7="卖出",MAX(0,L7-0-F7),IF(B7="现金分红",MAX(0,L7+E7-0),0)),"") -> 0 | N7: =IF(I7="已计入",IF(AND(B7="卖出",持仓总览!$C$7="本金优先"),MAX(0,E7-0),IF(OR(B7="卖出",B7="现金分红"),MIN(E7,M7),0)),"") -> 0 | O7: =IF(I7="已计入",IF(OR(B7="卖出",B7="现金分红"),MIN(0,MAX(0,E7-N7)),0),"") -> 0 | P7: =IF(I7="已计入",IF(AND(B7="卖出",K7=0),MAX(0,0-O7),0),"") -> 0 | Q7: =IF(AA7="正常",IF(I7="已计入",ROUND(0+IF(OR(B7="买入",B7="定投",B7="转换转入"),E7,0)-O7-P7,2),0),"") -> 8000 | R7: =IF(I7="已计入",ROUND(K7*C7,2),"") -> 7987.99 | S7: =IF(I7="已计入",ROUND(R7-Q7,2),"") -> -12.01 | T7: =IF(I7="已计入",IF(Q7=0,"",S7/Q7),"") -> -0.00150125 | U7: =IF(AA7="正常",0+IF(AND(I7="已计入",OR(B7="买入",B7="定投",B7="转换转入")),E7,0),"") -> 8000 | V7: =IF(AA7="正常",0+IF(AND(I7="已计入",OR(B7="卖出",B7="现金分红")),E7,0),"") -> 0 | W7: =IF(AA7="正常",0+IF(I7="已计入",N7,0),"") -> 0 | X7: =IF(AA7="正常",0+IF(I7="已计入",P7,0),"") -> 0 | Y7: =IF(I7="已计入",ROUND(R7+V7-U7,2),"") -> -12.01 | Z7: =IF(AA7="正常",IF(I7="已计入",A7,0),"") -> 45870 | AA7: =IF(OR("正常"="错误",AND(I7<>"",I7<>"已排除",I7<>"待确认",I7<>"已计入")),"错误","正常") -> 正常 | AB7: =IF(AA7="正常",IF(I7="已计入",C7,0),"") -> 1.937
A8: 45870 | B8: 买入 | C8: 1.937 | D8: 5154.88 | E8: 10000 | F8: 15 | G8: 历史估算 | H8: 原下单 2025-08-01T14:53:00 份额、费用及净值日沿用旧表估算 | I8: =IF(COUNTA(A8:H8)=0,"",IF(OR(OR(OR(G8="撤单",G8="交易失败",G8="交易关闭"),G8="交易失败",G8="交易关闭"),G8="交易失败",G8="交易关闭"),"已排除",IF(G8="待确认","待确认",IF(NOT(OR(G8="已确认",G8="历史估算")),"请选择确认状态",IF(NOT(ISNUMBER(A8)),"缺少有效净值日期",IF(OR(A8<=0,A8<>INT(A8)),"净值日期无效",IF(NOT(OR(OR(B8="买入",B8="定投",B8="转换转入"),B8="卖出",B8="现金分红",B8="红利再投")),"请选择交易类型",IF(NOT(ISNUMBER(C8)),"缺少成交净值",IF(C8<=0,"成交净值须大于零",IF(NOT(ISNUMBER(D8)),"缺少确认份额（分红填0）",IF(NOT(ISNUMBER(E8)),"缺少确认金额（再投填0）",IF(NOT(ISNUMBER(F8)),"缺少手续费（无费用填0）",IF(OR(D8<0,E8<0,F8<0),"份额金额费用不能为负",IF(AA7="错误","前行待修正",IF(A8<Z7,"日期需按成交顺序递增",IF(AND(B8="现金分红",OR(D8<>0,E8<=0,F8<>0)),"分红填份额0、费用0、正金额",IF(AND(B8="红利再投",OR(D8<=0,E8<>0,F8<>0)),"再投填正份额、金额0、费用0",IF(AND(OR(B8="现金分红",B8="红利再投"),K7<=0),"分红或再投前须有持仓",IF(AND(OR(OR(B8="买入",B8="定投",B8="转换转入"),B8="卖出"),OR(D8<=0,E8<=0)),"买卖须填正份额、正金额",IF(AND(B8="卖出",D8>K7+0.000001),"卖出份额超过持仓",IF(AND(OR(B8="买入",B8="定投",B8="转换转入"),F8>=E8),"申购费不能达到总支出",IF(NOT(ISNUMBER(持仓总览!$H$6)),"请填写金额核对容差",IF(持仓总览!$H$6<0,"金额核对容差不能为负",IF(NOT(OR(持仓总览!$C$7="利润优先",持仓总览!$C$7="本金优先")),"请选择卖出分配模式",IF(AND(OR(B8="买入",B8="定投",B8="转换转入"),ABS(E8-F8-C8*D8)>持仓总览!$H$6),"买入金额与份额净值不符",IF(AND(B8="卖出",ABS(E8+F8-C8*D8)>持仓总览!$H$6),"到账加费用与赎回市值不符","已计入")))))))))))))))))))))))))) -> 已计入 | J8: =IF(AA8="正常",IF(I8="已计入",IF(OR(OR(B8="买入",B8="定投",B8="转换转入"),B8="红利再投"),D8,IF(B8="卖出",-D8,0)),0),"") -> 5154.88 | K8: =IF(AA8="正常",ROUND(K7+J8,6),"") -> 9278.78 | L8: =IF(I8="已计入",ROUND(K7*C8,2),"") -> 7987.99 | M8: =IF(I8="已计入",IF(B8="卖出",MAX(0,L8-Q7-F8),IF(B8="现金分红",MAX(0,L8+E8-Q7),0)),"") -> 0 | N8: =IF(I8="已计入",IF(AND(B8="卖出",持仓总览!$C$7="本金优先"),MAX(0,E8-Q7),IF(OR(B8="卖出",B8="现金分红"),MIN(E8,M8),0)),"") -> 0 | O8: =IF(I8="已计入",IF(OR(B8="卖出",B8="现金分红"),MIN(Q7,MAX(0,E8-N8)),0),"") -> 0 | P8: =IF(I8="已计入",IF(AND(B8="卖出",K8=0),MAX(0,Q7-O8),0),"") -> 0 | Q8: =IF(AA8="正常",IF(I8="已计入",ROUND(Q7+IF(OR(B8="买入",B8="定投",B8="转换转入"),E8,0)-O8-P8,2),Q7),"") -> 18000 | R8: =IF(I8="已计入",ROUND(K8*C8,2),"") -> 17973 | S8: =IF(I8="已计入",ROUND(R8-Q8,2),"") -> -27 | T8: =IF(I8="已计入",IF(Q8=0,"",S8/Q8),"") -> -0.0015 | U8: =IF(AA8="正常",U7+IF(AND(I8="已计入",OR(B8="买入",B8="定投",B8="转换转入")),E8,0),"") -> 18000 | V8: =IF(AA8="正常",V7+IF(AND(I8="已计入",OR(B8="卖出",B8="现金分红")),E8,0),"") -> 0 | W8: =IF(AA8="正常",W7+IF(I8="已计入",N8,0),"") -> 0 | X8: =IF(AA8="正常",X7+IF(I8="已计入",P8,0),"") -> 0 | Y8: =IF(I8="已计入",ROUND(R8+V8-U8,2),"") -> -27 | Z8: =IF(AA8="正常",IF(I8="已计入",A8,Z7),"") -> 45870 | AA8: =IF(OR(AA7="错误",AND(I8<>"",I8<>"已排除",I8<>"待确认",I8<>"已计入")),"错误","正常") -> 正常 | AB8: =IF(AA8="正常",IF(I8="已计入",C8,AB7),"") -> 1.937
A9: 45873 | B9: 买入 | C9: 1.9949 | D9: 1001.05 | E9: 2000 | F9: 3 | G9: 历史估算 | H9: 原下单 2025-08-04T08:27:29 份额、费用及净值日沿用旧表估算 | I9: =IF(COUNTA(A9:H9)=0,"",IF(OR(OR(OR(G9="撤单",G9="交易失败",G9="交易关闭"),G9="交易失败",G9="交易关闭"),G9="交易失败",G9="交易关闭"),"已排除",IF(G9="待确认","待确认",IF(NOT(OR(G9="已确认",G9="历史估算")),"请选择确认状态",IF(NOT(ISNUMBER(A9)),"缺少有效净值日期",IF(OR(A9<=0,A9<>INT(A9)),"净值日期无效",IF(NOT(OR(OR(B9="买入",B9="定投",B9="转换转入"),B9="卖出",B9="现金分红",B9="红利再投")),"请选择交易类型",IF(NOT(ISNUMBER(C9)),"缺少成交净值",IF(C9<=0,"成交净值须大于零",IF(NOT(ISNUMBER(D9)),"缺少确认份额（分红填0）",IF(NOT(ISNUMBER(E9)),"缺少确认金额（再投填0）",IF(NOT(ISNUMBER(F9)),"缺少手续费（无费用填0）",IF(OR(D9<0,E9<0,F9<0),"份额金额费用不能为负",IF(AA8="错误","前行待修正",IF(A9<Z8,"日期需按成交顺序递增",IF(AND(B9="现金分红",OR(D9<>0,E9<=0,F9<>0)),"分红填份额0、费用0、正金额",IF(AND(B9="红利再投",OR(D9<=0,E9<>0,F9<>0)),"再投填正份额、金额0、费用0",IF(AND(OR(B9="现金分红",B9="红利再投"),K8<=0),"分红或再投前须有持仓",IF(AND(OR(OR(B9="买入",B9="定投",B9="转换转入"),B9="卖出"),OR(D9<=0,E9<=0)),"买卖须填正份额、正金额",IF(AND(B9="卖出",D9>K8+0.000001),"卖出份额超过持仓",IF(AND(OR(B9="买入",B9="定投",B9="转换转入"),F9>=E9),"申购费不能达到总支出",IF(NOT(ISNUMBER(持仓总览!$H$6)),"请填写金额核对容差",IF(持仓总览!$H$6<0,"金额核对容差不能为负",IF(NOT(OR(持仓总览!$C$7="利润优先",持仓总览!$C$7="本金优先")),"请选择卖出分配模式",IF(AND(OR(B9="买入",B9="定投",B9="转换转入"),ABS(E9-F9-C9*D9)>持仓总览!$H$6),"买入金额与份额净值不符",IF(AND(B9="卖出",ABS(E9+F9-C9*D9)>持仓总览!$H$6),"到账加费用与赎回市值不符","已计入")))))))))))))))))))))))))) -> 已计入 | J9: =IF(AA9="正常",IF(I9="已计入",IF(OR(OR(B9="买入",B9="定投",B9="转换转入"),B9="红利再投"),D9,IF(B9="卖出",-D9,0)),0),"") -> 1001.05 | K9: =IF(AA9="正常",ROUND(K8+J9,6),"") -> 10279.83 | L9: =IF(I9="已计入",ROUND(K8*C9,2),"") -> 18510.24 | M9: =IF(I9="已计入",IF(B9="卖出",MAX(0,L9-Q8-F9),IF(B9="现金分红",MAX(0,L9+E9-Q8),0)),"") -> 0 | N9: =IF(I9="已计入",IF(AND(B9="卖出",持仓总览!$C$7="本金优先"),MAX(0,E9-Q8),IF(OR(B9="卖出",B9="现金分红"),MIN(E9,M9),0)),"") -> 0 | O9: =IF(I9="已计入",IF(OR(B9="卖出",B9="现金分红"),MIN(Q8,MAX(0,E9-N9)),0),"") -> 0 | P9: =IF(I9="已计入",IF(AND(B9="卖出",K9=0),MAX(0,Q8-O9),0),"") -> 0 | Q9: =IF(AA9="正常",IF(I9="已计入",ROUND(Q8+IF(OR(B9="买入",B9="定投",B9="转换转入"),E9,0)-O9-P9,2),Q8),"") -> 20000 | R9: =IF(I9="已计入",ROUND(K9*C9,2),"") -> 20507.23 | S9: =IF(I9="已计入",ROUND(R9-Q9,2),"") -> 507.23 | T9: =IF(I9="已计入",IF(Q9=0,"",S9/Q9),"") -> 0.0253615 | U9: =IF(AA9="正常",U8+IF(AND(I9="已计入",OR(B9="买入",B9="定投",B9="转换转入")),E9,0),"") -> 20000 | V9: =IF(AA9="正常",V8+IF(AND(I9="已计入",OR(B9="卖出",B9="现金分红")),E9,0),"") -> 0 | W9: =IF(AA9="正常",W8+IF(I9="已计入",N9,0),"") -> 0 | X9: =IF(AA9="正常",X8+IF(I9="已计入",P9,0),"") -> 0 | Y9: =IF(I9="已计入",ROUND(R9+V9-U9,2),"") -> 507.23 | Z9: =IF(AA9="正常",IF(I9="已计入",A9,Z8),"") -> 45873 | AA9: =IF(OR(AA8="错误",AND(I9<>"",I9<>"已排除",I9<>"待确认",I9<>"已计入")),"错误","正常") -> 正常 | AB9: =IF(AA9="正常",IF(I9="已计入",C9,AB8),"") -> 1.9949
A10: 45875 | B10: 买入 | C10: 2.0113 | D10: 24.82 | E10: 50 | F10: 0.08 | G10: 历史估算 | H10: 原下单 2025-08-06T09:08:01 份额、费用及净值日沿用旧表估算 | I10: =IF(COUNTA(A10:H10)=0,"",IF(OR(OR(OR(G10="撤单",G10="交易失败",G10="交易关闭"),G10="交易失败",G10="交易关闭"),G10="交易失败",G10="交易关闭"),"已排除",IF(G10="待确认","待确认",IF(NOT(OR(G10="已确认",G10="历史估算")),"请选择确认状态",IF(NOT(ISNUMBER(A10)),"缺少有效净值日期",IF(OR(A10<=0,A10<>INT(A10)),"净值日期无效",IF(NOT(OR(OR(B10="买入",B10="定投",B10="转换转入"),B10="卖出",B10="现金分红",B10="红利再投")),"请选择交易类型",IF(NOT(ISNUMBER(C10)),"缺少成交净值",IF(C10<=0,"成交净值须大于零",IF(NOT(ISNUMBER(D10)),"缺少确认份额（分红填0）",IF(NOT(ISNUMBER(E10)),"缺少确认金额（再投填0）",IF(NOT(ISNUMBER(F10)),"缺少手续费（无费用填0）",IF(OR(D10<0,E10<0,F10<0),"份额金额费用不能为负",IF(AA9="错误","前行待修正",IF(A10<Z9,"日期需按成交顺序递增",IF(AND(B10="现金分红",OR(D10<>0,E10<=0,F10<>0)),"分红填份额0、费用0、正金额",IF(AND(B10="红利再投",OR(D10<=0,E10<>0,F10<>0)),"再投填正份额、金额0、费用0",IF(AND(OR(B10="现金分红",B10="红利再投"),K9<=0),"分红或再投前须有持仓",IF(AND(OR(OR(B10="买入",B10="定投",B10="转换转入"),B10="卖出"),OR(D10<=0,E10<=0)),"买卖须填正份额、正金额",IF(AND(B10="卖出",D10>K9+0.000001),"卖出份额超过持仓",IF(AND(OR(B10="买入",B10="定投",B10="转换转入"),F10>=E10),"申购费不能达到总支出",IF(NOT(ISNUMBER(持仓总览!$H$6)),"请填写金额核对容差",IF(持仓总览!$H$6<0,"金额核对容差不能为负",IF(NOT(OR(持仓总览!$C$7="利润优先",持仓总览!$C$7="本金优先")),"请选择卖出分配模式",IF(AND(OR(B10="买入",B10="定投",B10="转换转入"),ABS(E10-F10-C10*D10)>持仓总览!$H$6),"买入金额与份额净值不符",IF(AND(B10="卖出",ABS(E10+F10-C10*D10)>持仓总览!$H$6),"到账加费用与赎回市值不符","已计入")))))))))))))))))))))))))) -> 已计入 | J10: =IF(AA10="正常",IF(I10="已计入",IF(OR(OR(B10="买入",B10="定投",B10="转换转入"),B10="红利再投"),D10,IF(B10="卖出",-D10,0)),0),"") -> 24.82 | K10: =IF(AA10="正常",ROUND(K9+J10,6),"") -> 10304.65 | L10: =IF(I10="已计入",ROUND(K9*C10,2),"") -> 20675.82 | M10: =IF(I10="已计入",IF(B10="卖出",MAX(0,L10-Q9-F10),IF(B10="现金分红",MAX(0,L10+E10-Q9),0)),"") -> 0 | N10: =IF(I10="已计入",IF(AND(B10="卖出",持仓总览!$C$7="本金优先"),MAX(0,E10-Q9),IF(OR(B10="卖出",B10="现金分红"),MIN(E10,M10),0)),"") -> 0 | O10: =IF(I10="已计入",IF(OR(B10="卖出",B10="现金分红"),MIN(Q9,MAX(0,E10-N10)),0),"") -> 0 | P10: =IF(I10="已计入",IF(AND(B10="卖出",K10=0),MAX(0,Q9-O10),0),"") -> 0 | Q10: =IF(AA10="正常",IF(I10="已计入",ROUND(Q9+IF(OR(B10="买入",B10="定投",B10="转换转入"),E10,0)-O10-P10,2),Q9),"") -> 20050 | R10: =IF(I10="已计入",ROUND(K10*C10,2),"") -> 20725.74 | S10: =IF(I10="已计入",ROUND(R10-Q10,2),"") -> 675.74 | T10: =IF(I10="已计入",IF(Q10=0,"",S10/Q10),"") -> 0.033702743 | U10: =IF(AA10="正常",U9+IF(AND(I10="已计入",OR(B10="买入",B10="定投",B10="转换转入")),E10,0),"") -> 20050 | V10: =IF(AA10="正常",V9+IF(AND(I10="已计入",OR(B10="卖出",B10="现金分红")),E10,0),"") -> 0 | W10: =IF(AA10="正常",W9+IF(I10="已计入",N10,0),"") -> 0 | X10: =IF(AA10="正常",X9+IF(I10="已计入",P10,0),"") -> 0 | Y10: =IF(I10="已计入",ROUND(R10+V10-U10,2),"") -> 675.74 | Z10: =IF(AA10="正常",IF(I10="已计入",A10,Z9),"") -> 45875 | AA10: =IF(OR(AA9="错误",AND(I10<>"",I10<>"已排除",I10<>"待确认",I10<>"已计入")),"错误","正常") -> 正常 | AB10: =IF(AA10="正常",IF(I10="已计入",C10,AB9),"") -> 2.0113
A11: 45875 | B11: 转换转入 | C11: 2.0113 | D11: 5317.96 | E11: 10696.01 | F11: 0 | G11: 历史估算 | H11: 原下单 2025-08-06T14:32:28 份额、费用及净值日沿用旧表估算 | I11: =IF(COUNTA(A11:H11)=0,"",IF(OR(OR(OR(G11="撤单",G11="交易失败",G11="交易关闭"),G11="交易失败",G11="交易关闭"),G11="交易失败",G11="交易关闭"),"已排除",IF(G11="待确认","待确认",IF(NOT(OR(G11="已确认",G11="历史估算")),"请选择确认状态",IF(NOT(ISNUMBER(A11)),"缺少有效净值日期",IF(OR(A11<=0,A11<>INT(A11)),"净值日期无效",IF(NOT(OR(OR(B11="买入",B11="定投",B11="转换转入"),B11="卖出",B11="现金分红",B11="红利再投")),"请选择交易类型",IF(NOT(ISNUMBER(C11)),"缺少成交净值",IF(C11<=0,"成交净值须大于零",IF(NOT(ISNUMBER(D11)),"缺少确认份额（分红填0）",IF(NOT(ISNUMBER(E11)),"缺少确认金额（再投填0）",IF(NOT(ISNUMBER(F11)),"缺少手续费（无费用填0）",IF(OR(D11<0,E11<0,F11<0),"份额金额费用不能为负",IF(AA10="错误","前行待修正",IF(A11<Z10,"日期需按成交顺序递增",IF(AND(B11="现金分红",OR(D11<>0,E11<=0,F11<>0)),"分红填份额0、费用0、正金额",IF(AND(B11="红利再投",OR(D11<=0,E11<>0,F11<>0)),"再投填正份额、金额0、费用0",IF(AND(OR(B11="现金分红",B11="红利再投"),K10<=0),"分红或再投前须有持仓",IF(AND(OR(OR(B11="买入",B11="定投",B11="转换转入"),B11="卖出"),OR(D11<=0,E11<=0)),"买卖须填正份额、正金额",IF(AND(B11="卖出",D11>K10+0.000001),"卖出份额超过持仓",IF(AND(OR(B11="买入",B11="定投",B11="转换转入"),F11>=E11),"申购费不能达到总支出",IF(NOT(ISNUMBER(持仓总览!$H$6)),"请填写金额核对容差",IF(持仓总览!$H$6<0,"金额核对容差不能为负",IF(NOT(OR(持仓总览!$C$7="利润优先",持仓总览!$C$7="本金优先")),"请选择卖出分配模式",IF(AND(OR(B11="买入",B11="定投",B11="转换转入"),ABS(E11-F11-C11*D11)>持仓总览!$H$6),"买入金额与份额净值不符",IF(AND(B11="卖出",ABS(E11+F11-C11*D11)>持仓总览!$H$6),"到账加费用与赎回市值不符","已计入")))))))))))))))))))))))))) -> 已计入 | J11: =IF(AA11="正常",IF(I11="已计入",IF(OR(OR(B11="买入",B11="定投",B11="转换转入"),B11="红利再投"),D11,IF(B11="卖出",-D11,0)),0),"") -> 5317.96 | K11: =IF(AA11="正常",ROUND(K10+J11,6),"") -> 15622.61 | L11: =IF(I11="已计入",ROUND(K10*C11,2),"") -> 20725.74 | M11: =IF(I11="已计入",IF(B11="卖出",MAX(0,L11-Q10-F11),IF(B11="现金分红",MAX(0,L11+E11-Q10),0)),"") -> 0 | N11: =IF(I11="已计入",IF(AND(B11="卖出",持仓总览!$C$7="本金优先"),MAX(0,E11-Q10),IF(OR(B11="卖出",B11="现金分红"),MIN(E11,M11),0)),"") -> 0 | O11: =IF(I11="已计入",IF(OR(B11="卖出",B11="现金分红"),MIN(Q10,MAX(0,E11-N11)),0),"") -> 0 | P11: =IF(I11="已计入",IF(AND(B11="卖出",K11=0),MAX(0,Q10-O11),0),"") -> 0 | Q11: =IF(AA11="正常",IF(I11="已计入",ROUND(Q10+IF(OR(B11="买入",B11="定投",B11="转换转入"),E11,0)-O11-P11,2),Q10),"") -> 30746.01 | R11: =IF(I11="已计入",ROUND(K11*C11,2),"") -> 31421.76 | S11: =IF(I11="已计入",ROUND(R11-Q11,2),"") -> 675.75 | T11: =IF(I11="已计入",IF(Q11=0,"",S11/Q11),"") -> 0.021978462 | U11: =IF(AA11="正常",U10+IF(AND(I11="已计入",OR(B11="买入",B11="定投",B11="转换转入")),E11,0),"") -> 30746.01 | V11: =IF(AA11="正常",V10+IF(AND(I11="已计入",OR(B11="卖出",B11="现金分红")),E11,0),"") -> 0 | W11: =IF(AA11="正常",W10+IF(I11="已计入",N11,0),"") -> 0 | X11: =IF(AA11="正常",X10+IF(I11="已计入",P11,0),"") -> 0 | Y11: =IF(I11="已计入",ROUND(R11+V11-U11,2),"") -> 675.75 | Z11: =IF(AA11="正常",IF(I11="已计入",A11,Z10),"") -> 45875 | AA11: =IF(OR(AA10="错误",AND(I11<>"",I11<>"已排除",I11<>"待确认",I11<>"已计入")),"错误","正常") -> 正常 | AB11: =IF(AA11="正常",IF(I11="已计入",C11,AB10),"") -> 2.0113
A12: 45919 | B12: 买入 | C12: 2.1377 | D12: 467.09 | E12: 1000 | F12: 1.5 | G12: 历史估算 | H12: 原下单 2025-09-19T08:01:23 份额、费用及净值日沿用旧表估算 | I12: =IF(COUNTA(A12:H12)=0,"",IF(OR(OR(OR(G12="撤单",G12="交易失败",G12="交易关闭"),G12="交易失败",G12="交易关闭"),G12="交易失败",G12="交易关闭"),"已排除",IF(G12="待确认","待确认",IF(NOT(OR(G12="已确认",G12="历史估算")),"请选择确认状态",IF(NOT(ISNUMBER(A12)),"缺少有效净值日期",IF(OR(A12<=0,A12<>INT(A12)),"净值日期无效",IF(NOT(OR(OR(B12="买入",B12="定投",B12="转换转入"),B12="卖出",B12="现金分红",B12="红利再投")),"请选择交易类型",IF(NOT(ISNUMBER(C12)),"缺少成交净值",IF(C12<=0,"成交净值须大于零",IF(NOT(ISNUMBER(D12)),"缺少确认份额（分红填0）",IF(NOT(ISNUMBER(E12)),"缺少确认金额（再投填0）",IF(NOT(ISNUMBER(F12)),"缺少手续费（无费用填0）",IF(OR(D12<0,E12<0,F12<0),"份额金额费用不能为负",IF(AA11="错误","前行待修正",IF(A12<Z11,"日期需按成交顺序递增",IF(AND(B12="现金分红",OR(D12<>0,E12<=0,F12<>0)),"分红填份额0、费用0、正金额",IF(AND(B12="红利再投",OR(D12<=0,E12<>0,F12<>0)),"再投填正份额、金额0、费用0",IF(AND(OR(B12="现金分红",B12="红利再投"),K11<=0),"分红或再投前须有持仓",IF(AND(OR(OR(B12="买入",B12="定投",B12="转换转入"),B12="卖出"),OR(D12<=0,E12<=0)),"买卖须填正份额、正金额",IF(AND(B12="卖出",D12>K11+0.000001),"卖出份额超过持仓",IF(AND(OR(B12="买入",B12="定投",B12="转换转入"),F12>=E12),"申购费不能达到总支出",IF(NOT(ISNUMBER(持仓总览!$H$6)),"请填写金额核对容差",IF(持仓总览!$H$6<0,"金额核对容差不能为负",IF(NOT(OR(持仓总览!$C$7="利润优先",持仓总览!$C$7="本金优先")),"请选择卖出分配模式",IF(AND(OR(B12="买入",B12="定投",B12="转换转入"),ABS(E12-F12-C12*D12)>持仓总览!$H$6),"买入金额与份额净值不符",IF(AND(B12="卖出",ABS(E12+F12-C12*D12)>持仓总览!$H$6),"到账加费用与赎回市值不符","已计入")))))))))))))))))))))))))) -> 已计入 | J12: =IF(AA12="正常",IF(I12="已计入",IF(OR(OR(B12="买入",B12="定投",B12="转换转入"),B12="红利再投"),D12,IF(B12="卖出",-D12,0)),0),"") -> 467.09 | K12: =IF(AA12="正常",ROUND(K11+J12,6),"") -> 16089.7 | L12: =IF(I12="已计入",ROUND(K11*C12,2),"") -> 33396.45 | M12: =IF(I12="已计入",IF(B12="卖出",MAX(0,L12-Q11-F12),IF(B12="现金分红",MAX(0,L12+E12-Q11),0)),"") -> 0 | N12: =IF(I12="已计入",IF(AND(B12="卖出",持仓总览!$C$7="本金优先"),MAX(0,E12-Q11),IF(OR(B12="卖出",B12="现金分红"),MIN(E12,M12),0)),"") -> 0 | O12: =IF(I12="已计入",IF(OR(B12="卖出",B12="现金分红"),MIN(Q11,MAX(0,E12-N12)),0),"") -> 0 | P12: =IF(I12="已计入",IF(AND(B12="卖出",K12=0),MAX(0,Q11-O12),0),"") -> 0 | Q12: =IF(AA12="正常",IF(I12="已计入",ROUND(Q11+IF(OR(B12="买入",B12="定投",B12="转换转入"),E12,0)-O12-P12,2),Q11),"") -> 31746.01 | R12: =IF(I12="已计入",ROUND(K12*C12,2),"") -> 34394.95 | S12: =IF(I12="已计入",ROUND(R12-Q12,2),"") -> 2648.94 | T12: =IF(I12="已计入",IF(Q12=0,"",S12/Q12),"") -> 0.083441667 | U12: =IF(AA12="正常",U11+IF(AND(I12="已计入",OR(B12="买入",B12="定投",B12="转换转入")),E12,0),"") -> 31746.01 | V12: =IF(AA12="正常",V11+IF(AND(I12="已计入",OR(B12="卖出",B12="现金分红")),E12,0),"") -> 0 | W12: =IF(AA12="正常",W11+IF(I12="已计入",N12,0),"") -> 0 | X12: =IF(AA12="正常",X11+IF(I12="已计入",P12,0),"") -> 0 | Y12: =IF(I12="已计入",ROUND(R12+V12-U12,2),"") -> 2648.94 | Z12: =IF(AA12="正常",IF(I12="已计入",A12,Z11),"") -> 45919 | AA12: =IF(OR(AA11="错误",AND(I12<>"",I12<>"已排除",I12<>"待确认",I12<>"已计入")),"错误","正常") -> 正常 | AB12: =IF(AA12="正常",IF(I12="已计入",C12,AB11),"") -> 2.1377
A13: 45940 | B13: 买入 | C13: 2.0671 | D13: 483.04 | E13: 1000 | F13: 1.5 | G13: 历史估算 | H13: 原下单 2025-10-10T14:15:47 份额、费用及净值日沿用旧表估算 | I13: =IF(COUNTA(A13:H13)=0,"",IF(OR(OR(OR(G13="撤单",G13="交易失败",G13="交易关闭"),G13="交易失败",G13="交易关闭"),G13="交易失败",G13="交易关闭"),"已排除",IF(G13="待确认","待确认",IF(NOT(OR(G13="已确认",G13="历史估算")),"请选择确认状态",IF(NOT(ISNUMBER(A13)),"缺少有效净值日期",IF(OR(A13<=0,A13<>INT(A13)),"净值日期无效",IF(NOT(OR(OR(B13="买入",B13="定投",B13="转换转入"),B13="卖出",B13="现金分红",B13="红利再投")),"请选择交易类型",IF(NOT(ISNUMBER(C13)),"缺少成交净值",IF(C13<=0,"成交净值须大于零",IF(NOT(ISNUMBER(D13)),"缺少确认份额（分红填0）",IF(NOT(ISNUMBER(E13)),"缺少确认金额（再投填0）",IF(NOT(ISNUMBER(F13)),"缺少手续费（无费用填0）",IF(OR(D13<0,E13<0,F13<0),"份额金额费用不能为负",IF(AA12="错误","前行待修正",IF(A13<Z12,"日期需按成交顺序递增",IF(AND(B13="现金分红",OR(D13<>0,E13<=0,F13<>0)),"分红填份额0、费用0、正金额",IF(AND(B13="红利再投",OR(D13<=0,E13<>0,F13<>0)),"再投填正份额、金额0、费用0",IF(AND(OR(B13="现金分红",B13="红利再投"),K12<=0),"分红或再投前须有持仓",IF(AND(OR(OR(B13="买入",B13="定投",B13="转换转入"),B13="卖出"),OR(D13<=0,E13<=0)),"买卖须填正份额、正金额",IF(AND(B13="卖出",D13>K12+0.000001),"卖出份额超过持仓",IF(AND(OR(B13="买入",B13="定投",B13="转换转入"),F13>=E13),"申购费不能达到总支出",IF(NOT(ISNUMBER(持仓总览!$H$6)),"请填写金额核对容差",IF(持仓总览!$H$6<0,"金额核对容差不能为负",IF(NOT(OR(持仓总览!$C$7="利润优先",持仓总览!$C$7="本金优先")),"请选择卖出分配模式",IF(AND(OR(B13="买入",B13="定投",B13="转换转入"),ABS(E13-F13-C13*D13)>持仓总览!$H$6),"买入金额与份额净值不符",IF(AND(B13="卖出",ABS(E13+F13-C13*D13)>持仓总览!$H$6),"到账加费用与赎回市值不符","已计入")))))))))))))))))))))))))) -> 已计入 | J13: =IF(AA13="正常",IF(I13="已计入",IF(OR(OR(B13="买入",B13="定投",B13="转换转入"),B13="红利再投"),D13,IF(B13="卖出",-D13,0)),0),"") -> 483.04 | K13: =IF(AA13="正常",ROUND(K12+J13,6),"") -> 16572.74 | L13: =IF(I13="已计入",ROUND(K12*C13,2),"") -> 33259.02 | M13: =IF(I13="已计入",IF(B13="卖出",MAX(0,L13-Q12-F13),IF(B13="现金分红",MAX(0,L13+E13-Q12),0)),"") -> 0 | N13: =IF(I13="已计入",IF(AND(B13="卖出",持仓总览!$C$7="本金优先"),MAX(0,E13-Q12),IF(OR(B13="卖出",B13="现金分红"),MIN(E13,M13),0)),"") -> 0 | O13: =IF(I13="已计入",IF(OR(B13="卖出",B13="现金分红"),MIN(Q12,MAX(0,E13-N13)),0),"") -> 0 | P13: =IF(I13="已计入",IF(AND(B13="卖出",K13=0),MAX(0,Q12-O13),0),"") -> 0 | Q13: =IF(AA13="正常",IF(I13="已计入",ROUND(Q12+IF(OR(B13="买入",B13="定投",B13="转换转入"),E13,0)-O13-P13,2),Q12),"") -> 32746.01 | R13: =IF(I13="已计入",ROUND(K13*C13,2),"") -> 34257.51 | S13: =IF(I13="已计入",ROUND(R13-Q13,2),"") -> 1511.5 | T13: =IF(I13="已计入",IF(Q13=0,"",S13/Q13),"") -> 0.046158295 | U13: =IF(AA13="正常",U12+IF(AND(I13="已计入",OR(B13="买入",B13="定投",B13="转换转入")),E13,0),"") -> 32746.01 | V13: =IF(AA13="正常",V12+IF(AND(I13="已计入",OR(B13="卖出",B13="现金分红")),E13,0),"") -> 0 | W13: =IF(AA13="正常",W12+IF(I13="已计入",N13,0),"") -> 0 | X13: =IF(AA13="正常",X12+IF(I13="已计入",P13,0),"") -> 0 | Y13: =IF(I13="已计入",ROUND(R13+V13-U13,2),"") -> 1511.5 | Z13: =IF(AA13="正常",IF(I13="已计入",A13,Z12),"") -> 45940 | AA13: =IF(OR(AA12="错误",AND(I13<>"",I13<>"已排除",I13<>"待确认",I13<>"已计入")),"错误","正常") -> 正常 | AB13: =IF(AA13="正常",IF(I13="已计入",C13,AB12),"") -> 2.0671
A14: 45964 | B14: 定投 | C14: 2.2572 | D14: 132.71 | E14: 300 | F14: 0.45 | G14: 历史估算 | H14: 原下单 2025-11-03T10:13:33 份额、费用及净值日沿用旧表估算 | I14: =IF(COUNTA(A14:H14)=0,"",IF(OR(OR(OR(G14="撤单",G14="交易失败",G14="交易关闭"),G14="交易失败",G14="交易关闭"),G14="交易失败",G14="交易关闭"),"已排除",IF(G14="待确认","待确认",IF(NOT(OR(G14="已确认",G14="历史估算")),"请选择确认状态",IF(NOT(ISNUMBER(A14)),"缺少有效净值日期",IF(OR(A14<=0,A14<>INT(A14)),"净值日期无效",IF(NOT(OR(OR(B14="买入",B14="定投",B14="转换转入"),B14="卖出",B14="现金分红",B14="红利再投")),"请选择交易类型",IF(NOT(ISNUMBER(C14)),"缺少成交净值",IF(C14<=0,"成交净值须大于零",IF(NOT(ISNUMBER(D14)),"缺少确认份额（分红填0）",IF(NOT(ISNUMBER(E14)),"缺少确认金额（再投填0）",IF(NOT(ISNUMBER(F14)),"缺少手续费（无费用填0）",IF(OR(D14<0,E14<0,F14<0),"份额金额费用不能为负",IF(AA13="错误","前行待修正",IF(A14<Z13,"日期需按成交顺序递增",IF(AND(B14="现金分红",OR(D14<>0,E14<=0,F14<>0)),"分红填份额0、费用0、正金额",IF(AND(B14="红利再投",OR(D14<=0,E14<>0,F14<>0)),"再投填正份额、金额0、费用0",IF(AND(OR(B14="现金分红",B14="红利再投"),K13<=0),"分红或再投前须有持仓",IF(AND(OR(OR(B14="买入",B14="定投",B14="转换转入"),B14="卖出"),OR(D14<=0,E14<=0)),"买卖须填正份额、正金额",IF(AND(B14="卖出",D14>K13+0.000001),"卖出份额超过持仓",IF(AND(OR(B14="买入",B14="定投",B14="转换转入"),F14>=E14),"申购费不能达到总支出",IF(NOT(ISNUMBER(持仓总览!$H$6)),"请填写金额核对容差",IF(持仓总览!$H$6<0,"金额核对容差不能为负",IF(NOT(OR(持仓总览!$C$7="利润优先",持仓总览!$C$7="本金优先")),"请选择卖出分配模式",IF(AND(OR(B14="买入",B14="定投",B14="转换转入"),ABS(E14-F14-C14*D14)>持仓总览!$H$6),"买入金额与份额净值不符",IF(AND(B14="卖出",ABS(E14+F14-C14*D14)>持仓总览!$H$6),"到账加费用与赎回市值不符","已计入")))))))))))))))))))))))))) -> 已计入 | J14: =IF(AA14="正常",IF(I14="已计入",IF(OR(OR(B14="买入",B14="定投",B14="转换转入"),B14="红利再投"),D14,IF(B14="卖出",-D14,0)),0),"") -> 132.71 | K14: =IF(AA14="正常",ROUND(K13+J14,6),"") -> 16705.45 | L14: =IF(I14="已计入",ROUND(K13*C14,2),"") -> 37407.99 | M14: =IF(I14="已计入",IF(B14="卖出",MAX(0,L14-Q13-F14),IF(B14="现金分红",MAX(0,L14+E14-Q13),0)),"") -> 0 | N14: =IF(I14="已计入",IF(AND(B14="卖出",持仓总览!$C$7="本金优先"),MAX(0,E14-Q13),IF(OR(B14="卖出",B14="现金分红"),MIN(E14,M14),0)),"") -> 0 | O14: =IF(I14="已计入",IF(OR(B14="卖出",B14="现金分红"),MIN(Q13,MAX(0,E14-N14)),0),"") -> 0 | P14: =IF(I14="已计入",IF(AND(B14="卖出",K14=0),MAX(0,Q13-O14),0),"") -> 0 | Q14: =IF(AA14="正常",IF(I14="已计入",ROUND(Q13+IF(OR(B14="买入",B14="定投",B14="转换转入"),E14,0)-O14-P14,2),Q13),"") -> 33046.01 | R14: =IF(I14="已计入",ROUND(K14*C14,2),"") -> 37707.54 | S14: =IF(I14="已计入",ROUND(R14-Q14,2),"") -> 4661.53 | T14: =IF(I14="已计入",IF(Q14=0,"",S14/Q14),"") -> 0.14106181 | U14: =IF(AA14="正常",U13+IF(AND(I14="已计入",OR(B14="买入",B14="定投",B14="转换转入")),E14,0),"") -> 33046.01 | V14: =IF(AA14="正常",V13+IF(AND(I14="已计入",OR(B14="卖出",B14="现金分红")),E14,0),"") -> 0 | W14: =IF(AA14="正常",W13+IF(I14="已计入",N14,0),"") -> 0 | X14: =IF(AA14="正常",X13+IF(I14="已计入",P14,0),"") -> 0 | Y14: =IF(I14="已计入",ROUND(R14+V14-U14,2),"") -> 4661.53 | Z14: =IF(AA14="正常",IF(I14="已计入",A14,Z13),"") -> 45964 | AA14: =IF(OR(AA13="错误",AND(I14<>"",I14<>"已排除",I14<>"待确认",I14<>"已计入")),"错误","正常") -> 正常 | AB14: =IF(AA14="正常",IF(I14="已计入",C14,AB13),"") -> 2.2572
A15: 45965 | B15: 买入 | C15: 2.1901 | D15: 136.77 | E15: 300 | F15: 0.45 | G15: 历史估算 | H15: 原下单 2025-11-04T11:06:31 份额、费用及净值日沿用旧表估算 | I15: =IF(COUNTA(A15:H15)=0,"",IF(OR(OR(OR(G15="撤单",G15="交易失败",G15="交易关闭"),G15="交易失败",G15="交易关闭"),G15="交易失败",G15="交易关闭"),"已排除",IF(G15="待确认","待确认",IF(NOT(OR(G15="已确认",G15="历史估算")),"请选择确认状态",IF(NOT(ISNUMBER(A15)),"缺少有效净值日期",IF(OR(A15<=0,A15<>INT(A15)),"净值日期无效",IF(NOT(OR(OR(B15="买入",B15="定投",B15="转换转入"),B15="卖出",B15="现金分红",B15="红利再投")),"请选择交易类型",IF(NOT(ISNUMBER(C15)),"缺少成交净值",IF(C15<=0,"成交净值须大于零",IF(NOT(ISNUMBER(D15)),"缺少确认份额（分红填0）",IF(NOT(ISNUMBER(E15)),"缺少确认金额（再投填0）",IF(NOT(ISNUMBER(F15)),"缺少手续费（无费用填0）",IF(OR(D15<0,E15<0,F15<0),"份额金额费用不能为负",IF(AA14="错误","前行待修正",IF(A15<Z14,"日期需按成交顺序递增",IF(AND(B15="现金分红",OR(D15<>0,E15<=0,F15<>0)),"分红填份额0、费用0、正金额",IF(AND(B15="红利再投",OR(D15<=0,E15<>0,F15<>0)),"再投填正份额、金额0、费用0",IF(AND(OR(B15="现金分红",B15="红利再投"),K14<=0),"分红或再投前须有持仓",IF(AND(OR(OR(B15="买入",B15="定投",B15="转换转入"),B15="卖出"),OR(D15<=0,E15<=0)),"买卖须填正份额、正金额",IF(AND(B15="卖出",D15>K14+0.000001),"卖出份额超过持仓",IF(AND(OR(B15="买入",B15="定投",B15="转换转入"),F15>=E15),"申购费不能达到总支出",IF(NOT(ISNUMBER(持仓总览!$H$6)),"请填写金额核对容差",IF(持仓总览!$H$6<0,"金额核对容差不能为负",IF(NOT(OR(持仓总览!$C$7="利润优先",持仓总览!$C$7="本金优先")),"请选择卖出分配模式",IF(AND(OR(B15="买入",B15="定投",B15="转换转入"),ABS(E15-F15-C15*D15)>持仓总览!$H$6),"买入金额与份额净值不符",IF(AND(B15="卖出",ABS(E15+F15-C15*D15)>持仓总览!$H$6),"到账加费用与赎回市值不符","已计入")))))))))))))))))))))))))) -> 已计入 | J15: =IF(AA15="正常",IF(I15="已计入",IF(OR(OR(B15="买入",B15="定投",B15="转换转入"),B15="红利再投"),D15,IF(B15="卖出",-D15,0)),0),"") -> 136.77 | K15: =IF(AA15="正常",ROUND(K14+J15,6),"") -> 16842.22 | L15: =IF(I15="已计入",ROUND(K14*C15,2),"") -> 36586.61 | M15: =IF(I15="已计入",IF(B15="卖出",MAX(0,L15-Q14-F15),IF(B15="现金分红",MAX(0,L15+E15-Q14),0)),"") -> 0 | N15: =IF(I15="已计入",IF(AND(B15="卖出",持仓总览!$C$7="本金优先"),MAX(0,E15-Q14),IF(OR(B15="卖出",B15="现金分红"),MIN(E15,M15),0)),"") -> 0 | O15: =IF(I15="已计入",IF(OR(B15="卖出",B15="现金分红"),MIN(Q14,MAX(0,E15-N15)),0),"") -> 0 | P15: =IF(I15="已计入",IF(AND(B15="卖出",K15=0),MAX(0,Q14-O15),0),"") -> 0 | Q15: =IF(AA15="正常",IF(I15="已计入",ROUND(Q14+IF(OR(B15="买入",B15="定投",B15="转换转入"),E15,0)-O15-P15,2),Q14),"") -> 33346.01 | R15: =IF(I15="已计入",ROUND(K15*C15,2),"") -> 36886.15 | S15: =IF(I15="已计入",ROUND(R15-Q15,2),"") -> 3540.14 | T15: =IF(I15="已计入",IF(Q15=0,"",S15/Q15),"") -> 0.10616383 | U15: =IF(AA15="正常",U14+IF(AND(I15="已计入",OR(B15="买入",B15="定投",B15="转换转入")),E15,0),"") -> 33346.01 | V15: =IF(AA15="正常",V14+IF(AND(I15="已计入",OR(B15="卖出",B15="现金分红")),E15,0),"") -> 0 | W15: =IF(AA15="正常",W14+IF(I15="已计入",N15,0),"") -> 0 | X15: =IF(AA15="正常",X14+IF(I15="已计入",P15,0),"") -> 0 | Y15: =IF(I15="已计入",ROUND(R15+V15-U15,2),"") -> 3540.14 | Z15: =IF(AA15="正常",IF(I15="已计入",A15,Z14),"") -> 45965 | AA15: =IF(OR(AA14="错误",AND(I15<>"",I15<>"已排除",I15<>"待确认",I15<>"已计入")),"错误","正常") -> 正常 | AB15: =IF(AA15="正常",IF(I15="已计入",C15,AB14),"") -> 2.1901
A16: 45966 | B16: 定投 | C16: 2.2152 | D16: 135.22 | E16: 300 | F16: 0.45 | G16: 历史估算 | H16: 原下单 2025-11-05T10:05:15 份额、费用及净值日沿用旧表估算 | I16: =IF(COUNTA(A16:H16)=0,"",IF(OR(OR(OR(G16="撤单",G16="交易失败",G16="交易关闭"),G16="交易失败",G16="交易关闭"),G16="交易失败",G16="交易关闭"),"已排除",IF(G16="待确认","待确认",IF(NOT(OR(G16="已确认",G16="历史估算")),"请选择确认状态",IF(NOT(ISNUMBER(A16)),"缺少有效净值日期",IF(OR(A16<=0,A16<>INT(A16)),"净值日期无效",IF(NOT(OR(OR(B16="买入",B16="定投",B16="转换转入"),B16="卖出",B16="现金分红",B16="红利再投")),"请选择交易类型",IF(NOT(ISNUMBER(C16)),"缺少成交净值",IF(C16<=0,"成交净值须大于零",IF(NOT(ISNUMBER(D16)),"缺少确认份额（分红填0）",IF(NOT(ISNUMBER(E16)),"缺少确认金额（再投填0）",IF(NOT(ISNUMBER(F16)),"缺少手续费（无费用填0）",IF(OR(D16<0,E16<0,F16<0),"份额金额费用不能为负",IF(AA15="错误","前行待修正",IF(A16<Z15,"日期需按成交顺序递增",IF(AND(B16="现金分红",OR(D16<>0,E16<=0,F16<>0)),"分红填份额0、费用0、正金额",IF(AND(B16="红利再投",OR(D16<=0,E16<>0,F16<>0)),"再投填正份额、金额0、费用0",IF(AND(OR(B16="现金分红",B16="红利再投"),K15<=0),"分红或再投前须有持仓",IF(AND(OR(OR(B16="买入",B16="定投",B16="转换转入"),B16="卖出"),OR(D16<=0,E16<=0)),"买卖须填正份额、正金额",IF(AND(B16="卖出",D16>K15+0.000001),"卖出份额超过持仓",IF(AND(OR(B16="买入",B16="定投",B16="转换转入"),F16>=E16),"申购费不能达到总支出",IF(NOT(ISNUMBER(持仓总览!$H$6)),"请填写金额核对容差",IF(持仓总览!$H$6<0,"金额核对容差不能为负",IF(NOT(OR(持仓总览!$C$7="利润优先",持仓总览!$C$7="本金优先")),"请选择卖出分配模式",IF(AND(OR(B16="买入",B16="定投",B16="转换转入"),ABS(E16-F16-C16*D16)>持仓总览!$H$6),"买入金额与份额净值不符",IF(AND(B16="卖出",ABS(E16+F16-C16*D16)>持仓总览!$H$6),"到账加费用与赎回市值不符","已计入")))))))))))))))))))))))))) -> 已计入 | J16: =IF(AA16="正常",IF(I16="已计入",IF(OR(OR(B16="买入",B16="定投",B16="转换转入"),B16="红利再投"),D16,IF(B16="卖出",-D16,0)),0),"") -> 135.22 | K16: =IF(AA16="正常",ROUND(K15+J16,6),"") -> 16977.44 | L16: =IF(I16="已计入",ROUND(K15*C16,2),"") -> 37308.89 | M16: =IF(I16="已计入",IF(B16="卖出",MAX(0,L16-Q15-F16),IF(B16="现金分红",MAX(0,L16+E16-Q15),0)),"") -> 0 | N16: =IF(I16="已计入",IF(AND(B16="卖出",持仓总览!$C$7="本金优先"),MAX(0,E16-Q15),IF(OR(B16="卖出",B16="现金分红"),MIN(E16,M16),0)),"") -> 0 | O16: =IF(I16="已计入",IF(OR(B16="卖出",B16="现金分红"),MIN(Q15,MAX(0,E16-N16)),0),"") -> 0 | P16: =IF(I16="已计入",IF(AND(B16="卖出",K16=0),MAX(0,Q15-O16),0),"") -> 0 | Q16: =IF(AA16="正常",IF(I16="已计入",ROUND(Q15+IF(OR(B16="买入",B16="定投",B16="转换转入"),E16,0)-O16-P16,2),Q15),"") -> 33646.01 | R16: =IF(I16="已计入",ROUND(K16*C16,2),"") -> 37608.43 | S16: =IF(I16="已计入",ROUND(R16-Q16,2),"") -> 3962.42 | T16: =IF(I16="已计入",IF(Q16=0,"",S16/Q16),"") -> 0.1177679 | U16: =IF(AA16="正常",U15+IF(AND(I16="已计入",OR(B16="买入",B16="定投",B16="转换转入")),E16,0),"") -> 33646.01 | V16: =IF(AA16="正常",V15+IF(AND(I16="已计入",OR(B16="卖出",B16="现金分红")),E16,0),"") -> 0 | W16: =IF(AA16="正常",W15+IF(I16="已计入",N16,0),"") -> 0 | X16: =IF(AA16="正常",X15+IF(I16="已计入",P16,0),"") -> 0 | Y16: =IF(I16="已计入",ROUND(R16+V16-U16,2),"") -> 3962.42 | Z16: =IF(AA16="正常",IF(I16="已计入",A16,Z15),"") -> 45966 | AA16: =IF(OR(AA15="错误",AND(I16<>"",I16<>"已排除",I16<>"待确认",I16<>"已计入")),"错误","正常") -> 正常 | AB16: =IF(AA16="正常",IF(I16="已计入",C16,AB15),"") -> 2.2152
A17: 46003 | B17: 定投 | C17: 2.1506 | D17: 46.43 | E17: 100 | F17: 0.15 | G17: 历史估算 | H17: 原下单 2025-12-12T10:16:18 份额、费用及净值日沿用旧表估算 | I17: =IF(COUNTA(A17:H17)=0,"",IF(OR(OR(OR(G17="撤单",G17="交易失败",G17="交易关闭"),G17="交易失败",G17="交易关闭"),G17="交易失败",G17="交易关闭"),"已排除",IF(G17="待确认","待确认",IF(NOT(OR(G17="已确认",G17="历史估算")),"请选择确认状态",IF(NOT(ISNUMBER(A17)),"缺少有效净值日期",IF(OR(A17<=0,A17<>INT(A17)),"净值日期无效",IF(NOT(OR(OR(B17="买入",B17="定投",B17="转换转入"),B17="卖出",B17="现金分红",B17="红利再投")),"请选择交易类型",IF(NOT(ISNUMBER(C17)),"缺少成交净值",IF(C17<=0,"成交净值须大于零",IF(NOT(ISNUMBER(D17)),"缺少确认份额（分红填0）",IF(NOT(ISNUMBER(E17)),"缺少确认金额（再投填0）",IF(NOT(ISNUMBER(F17)),"缺少手续费（无费用填0）",IF(OR(D17<0,E17<0,F17<0),"份额金额费用不能为负",IF(AA16="错误","前行待修正",IF(A17<Z16,"日期需按成交顺序递增",IF(AND(B17="现金分红",OR(D17<>0,E17<=0,F17<>0)),"分红填份额0、费用0、正金额",IF(AND(B17="红利再投",OR(D17<=0,E17<>0,F17<>0)),"再投填正份额、金额0、费用0",IF(AND(OR(B17="现金分红",B17="红利再投"),K16<=0),"分红或再投前须有持仓",IF(AND(OR(OR(B17="买入",B17="定投",B17="转换转入"),B17="卖出"),OR(D17<=0,E17<=0)),"买卖须填正份额、正金额",IF(AND(B17="卖出",D17>K16+0.000001),"卖出份额超过持仓",IF(AND(OR(B17="买入",B17="定投",B17="转换转入"),F17>=E17),"申购费不能达到总支出",IF(NOT(ISNUMBER(持仓总览!$H$6)),"请填写金额核对容差",IF(持仓总览!$H$6<0,"金额核对容差不能为负",IF(NOT(OR(持仓总览!$C$7="利润优先",持仓总览!$C$7="本金优先")),"请选择卖出分配模式",IF(AND(OR(B17="买入",B17="定投",B17="转换转入"),ABS(E17-F17-C17*D17)>持仓总览!$H$6),"买入金额与份额净值不符",IF(AND(B17="卖出",ABS(E17+F17-C17*D17)>持仓总览!$H$6),"到账加费用与赎回市值不符","已计入")))))))))))))))))))))))))) -> 已计入 | J17: =IF(AA17="正常",IF(I17="已计入",IF(OR(OR(B17="买入",B17="定投",B17="转换转入"),B17="红利再投"),D17,IF(B17="卖出",-D17,0)),0),"") -> 46.43 | K17: =IF(AA17="正常",ROUND(K16+J17,6),"") -> 17023.87 | L17: =IF(I17="已计入",ROUND(K16*C17,2),"") -> 36511.68 | M17: =IF(I17="已计入",IF(B17="卖出",MAX(0,L17-Q16-F17),IF(B17="现金分红",MAX(0,L17+E17-Q16),0)),"") -> 0 | N17: =IF(I17="已计入",IF(AND(B17="卖出",持仓总览!$C$7="本金优先"),MAX(0,E17-Q16),IF(OR(B17="卖出",B17="现金分红"),MIN(E17,M17),0)),"") -> 0 | O17: =IF(I17="已计入",IF(OR(B17="卖出",B17="现金分红"),MIN(Q16,MAX(0,E17-N17)),0),"") -> 0 | P17: =IF(I17="已计入",IF(AND(B17="卖出",K17=0),MAX(0,Q16-O17),0),"") -> 0 | Q17: =IF(AA17="正常",IF(I17="已计入",ROUND(Q16+IF(OR(B17="买入",B17="定投",B17="转换转入"),E17,0)-O17-P17,2),Q16),"") -> 33746.01 | R17: =IF(I17="已计入",ROUND(K17*C17,2),"") -> 36611.53 | S17: =IF(I17="已计入",ROUND(R17-Q17,2),"") -> 2865.52 | T17: =IF(I17="已计入",IF(Q17=0,"",S17/Q17),"") -> 0.084914335 | U17: =IF(AA17="正常",U16+IF(AND(I17="已计入",OR(B17="买入",B17="定投",B17="转换转入")),E17,0),"") -> 33746.01 | V17: =IF(AA17="正常",V16+IF(AND(I17="已计入",OR(B17="卖出",B17="现金分红")),E17,0),"") -> 0 | W17: =IF(AA17="正常",W16+IF(I17="已计入",N17,0),"") -> 0 | X17: =IF(AA17="正常",X16+IF(I17="已计入",P17,0),"") -> 0 | Y17: =IF(I17="已计入",ROUND(R17+V17-U17,2),"") -> 2865.52 | Z17: =IF(AA17="正常",IF(I17="已计入",A17,Z16),"") -> 46003 | AA17: =IF(OR(AA16="错误",AND(I17<>"",I17<>"已排除",I17<>"待确认",I17<>"已计入")),"错误","正常") -> 正常 | AB17: =IF(AA17="正常",IF(I17="已计入",C17,AB16),"") -> 2.1506
A18: 46006 | B18: 定投 | C18: 2.1177 | D18: 94.3 | E18: 200 | F18: 0.3 | G18: 历史估算 | H18: 原下单 2025-12-15T10:22:03 份额、费用及净值日沿用旧表估算 | I18: =IF(COUNTA(A18:H18)=0,"",IF(OR(OR(OR(G18="撤单",G18="交易失败",G18="交易关闭"),G18="交易失败",G18="交易关闭"),G18="交易失败",G18="交易关闭"),"已排除",IF(G18="待确认","待确认",IF(NOT(OR(G18="已确认",G18="历史估算")),"请选择确认状态",IF(NOT(ISNUMBER(A18)),"缺少有效净值日期",IF(OR(A18<=0,A18<>INT(A18)),"净值日期无效",IF(NOT(OR(OR(B18="买入",B18="定投",B18="转换转入"),B18="卖出",B18="现金分红",B18="红利再投")),"请选择交易类型",IF(NOT(ISNUMBER(C18)),"缺少成交净值",IF(C18<=0,"成交净值须大于零",IF(NOT(ISNUMBER(D18)),"缺少确认份额（分红填0）",IF(NOT(ISNUMBER(E18)),"缺少确认金额（再投填0）",IF(NOT(ISNUMBER(F18)),"缺少手续费（无费用填0）",IF(OR(D18<0,E18<0,F18<0),"份额金额费用不能为负",IF(AA17="错误","前行待修正",IF(A18<Z17,"日期需按成交顺序递增",IF(AND(B18="现金分红",OR(D18<>0,E18<=0,F18<>0)),"分红填份额0、费用0、正金额",IF(AND(B18="红利再投",OR(D18<=0,E18<>0,F18<>0)),"再投填正份额、金额0、费用0",IF(AND(OR(B18="现金分红",B18="红利再投"),K17<=0),"分红或再投前须有持仓",IF(AND(OR(OR(B18="买入",B18="定投",B18="转换转入"),B18="卖出"),OR(D18<=0,E18<=0)),"买卖须填正份额、正金额",IF(AND(B18="卖出",D18>K17+0.000001),"卖出份额超过持仓",IF(AND(OR(B18="买入",B18="定投",B18="转换转入"),F18>=E18),"申购费不能达到总支出",IF(NOT(ISNUMBER(持仓总览!$H$6)),"请填写金额核对容差",IF(持仓总览!$H$6<0,"金额核对容差不能为负",IF(NOT(OR(持仓总览!$C$7="利润优先",持仓总览!$C$7="本金优先")),"请选择卖出分配模式",IF(AND(OR(B18="买入",B18="定投",B18="转换转入"),ABS(E18-F18-C18*D18)>持仓总览!$H$6),"买入金额与份额净值不符",IF(AND(B18="卖出",ABS(E18+F18-C18*D18)>持仓总览!$H$6),"到账加费用与赎回市值不符","已计入")))))))))))))))))))))))))) -> 已计入 | J18: =IF(AA18="正常",IF(I18="已计入",IF(OR(OR(B18="买入",B18="定投",B18="转换转入"),B18="红利再投"),D18,IF(B18="卖出",-D18,0)),0),"") -> 94.3 | K18: =IF(AA18="正常",ROUND(K17+J18,6),"") -> 17118.17 | L18: =IF(I18="已计入",ROUND(K17*C18,2),"") -> 36051.45 | M18: =IF(I18="已计入",IF(B18="卖出",MAX(0,L18-Q17-F18),IF(B18="现金分红",MAX(0,L18+E18-Q17),0)),"") -> 0 | N18: =IF(I18="已计入",IF(AND(B18="卖出",持仓总览!$C$7="本金优先"),MAX(0,E18-Q17),IF(OR(B18="卖出",B18="现金分红"),MIN(E18,M18),0)),"") -> 0 | O18: =IF(I18="已计入",IF(OR(B18="卖出",B18="现金分红"),MIN(Q17,MAX(0,E18-N18)),0),"") -> 0 | P18: =IF(I18="已计入",IF(AND(B18="卖出",K18=0),MAX(0,Q17-O18),0),"") -> 0 | Q18: =IF(AA18="正常",IF(I18="已计入",ROUND(Q17+IF(OR(B18="买入",B18="定投",B18="转换转入"),E18,0)-O18-P18,2),Q17),"") -> 33946.01 | R18: =IF(I18="已计入",ROUND(K18*C18,2),"") -> 36251.15 | S18: =IF(I18="已计入",ROUND(R18-Q18,2),"") -> 2305.14 | T18: =IF(I18="已计入",IF(Q18=0,"",S18/Q18),"") -> 0.067906066 | U18: =IF(AA18="正常",U17+IF(AND(I18="已计入",OR(B18="买入",B18="定投",B18="转换转入")),E18,0),"") -> 33946.01 | V18: =IF(AA18="正常",V17+IF(AND(I18="已计入",OR(B18="卖出",B18="现金分红")),E18,0),"") -> 0 | W18: =IF(AA18="正常",W17+IF(I18="已计入",N18,0),"") -> 0 | X18: =IF(AA18="正常",X17+IF(I18="已计入",P18,0),"") -> 0 | Y18: =IF(I18="已计入",ROUND(R18+V18-U18,2),"") -> 2305.14 | Z18: =IF(AA18="正常",IF(I18="已计入",A18,Z17),"") -> 46006 | AA18: =IF(OR(AA17="错误",AND(I18<>"",I18<>"已排除",I18<>"待确认",I18<>"已计入")),"错误","正常") -> 正常 | AB18: =IF(AA18="正常",IF(I18="已计入",C18,AB17),"") -> 2.1177
A19: 46007 | B19: 定投 | C19: 2.1043 | D19: 94.9 | E19: 200 | F19: 0.3 | G19: 历史估算 | H19: 原下单 2025-12-16T10:16:25 份额、费用及净值日沿用旧表估算 | I19: =IF(COUNTA(A19:H19)=0,"",IF(OR(OR(OR(G19="撤单",G19="交易失败",G19="交易关闭"),G19="交易失败",G19="交易关闭"),G19="交易失败",G19="交易关闭"),"已排除",IF(G19="待确认","待确认",IF(NOT(OR(G19="已确认",G19="历史估算")),"请选择确认状态",IF(NOT(ISNUMBER(A19)),"缺少有效净值日期",IF(OR(A19<=0,A19<>INT(A19)),"净值日期无效",IF(NOT(OR(OR(B19="买入",B19="定投",B19="转换转入"),B19="卖出",B19="现金分红",B19="红利再投")),"请选择交易类型",IF(NOT(ISNUMBER(C19)),"缺少成交净值",IF(C19<=0,"成交净值须大于零",IF(NOT(ISNUMBER(D19)),"缺少确认份额（分红填0）",IF(NOT(ISNUMBER(E19)),"缺少确认金额（再投填0）",IF(NOT(ISNUMBER(F19)),"缺少手续费（无费用填0）",IF(OR(D19<0,E19<0,F19<0),"份额金额费用不能为负",IF(AA18="错误","前行待修正",IF(A19<Z18,"日期需按成交顺序递增",IF(AND(B19="现金分红",OR(D19<>0,E19<=0,F19<>0)),"分红填份额0、费用0、正金额",IF(AND(B19="红利再投",OR(D19<=0,E19<>0,F19<>0)),"再投填正份额、金额0、费用0",IF(AND(OR(B19="现金分红",B19="红利再投"),K18<=0),"分红或再投前须有持仓",IF(AND(OR(OR(B19="买入",B19="定投",B19="转换转入"),B19="卖出"),OR(D19<=0,E19<=0)),"买卖须填正份额、正金额",IF(AND(B19="卖出",D19>K18+0.000001),"卖出份额超过持仓",IF(AND(OR(B19="买入",B19="定投",B19="转换转入"),F19>=E19),"申购费不能达到总支出",IF(NOT(ISNUMBER(持仓总览!$H$6)),"请填写金额核对容差",IF(持仓总览!$H$6<0,"金额核对容差不能为负",IF(NOT(OR(持仓总览!$C$7="利润优先",持仓总览!$C$7="本金优先")),"请选择卖出分配模式",IF(AND(OR(B19="买入",B19="定投",B19="转换转入"),ABS(E19-F19-C19*D19)>持仓总览!$H$6),"买入金额与份额净值不符",IF(AND(B19="卖出",ABS(E19+F19-C19*D19)>持仓总览!$H$6),"到账加费用与赎回市值不符","已计入")))))))))))))))))))))))))) -> 已计入 | J19: =IF(AA19="正常",IF(I19="已计入",IF(OR(OR(B19="买入",B19="定投",B19="转换转入"),B19="红利再投"),D19,IF(B19="卖出",-D19,0)),0),"") -> 94.9 | K19: =IF(AA19="正常",ROUND(K18+J19,6),"") -> 17213.07 | L19: =IF(I19="已计入",ROUND(K18*C19,2),"") -> 36021.77 | M19: =IF(I19="已计入",IF(B19="卖出",MAX(0,L19-Q18-F19),IF(B19="现金分红",MAX(0,L19+E19-Q18),0)),"") -> 0 | N19: =IF(I19="已计入",IF(AND(B19="卖出",持仓总览!$C$7="本金优先"),MAX(0,E19-Q18),IF(OR(B19="卖出",B19="现金分红"),MIN(E19,M19),0)),"") -> 0 | O19: =IF(I19="已计入",IF(OR(B19="卖出",B19="现金分红"),MIN(Q18,MAX(0,E19-N19)),0),"") -> 0 | P19: =IF(I19="已计入",IF(AND(B19="卖出",K19=0),MAX(0,Q18-O19),0),"") -> 0 | Q19: =IF(AA19="正常",IF(I19="已计入",ROUND(Q18+IF(OR(B19="买入",B19="定投",B19="转换转入"),E19,0)-O19-P19,2),Q18),"") -> 34146.01 | R19: =IF(I19="已计入",ROUND(K19*C19,2),"") -> 36221.46 | S19: =IF(I19="已计入",ROUND(R19-Q19,2),"") -> 2075.45 | T19: =IF(I19="已计入",IF(Q19=0,"",S19/Q19),"") -> 0.060781626 | U19: =IF(AA19="正常",U18+IF(AND(I19="已计入",OR(B19="买入",B19="定投",B19="转换转入")),E19,0),"") -> 34146.01 | V19: =IF(AA19="正常",V18+IF(AND(I19="已计入",OR(B19="卖出",B19="现金分红")),E19,0),"") -> 0 | W19: =IF(AA19="正常",W18+IF(I19="已计入",N19,0),"") -> 0 | X19: =IF(AA19="正常",X18+IF(I19="已计入",P19,0),"") -> 0 | Y19: =IF(I19="已计入",ROUND(R19+V19-U19,2),"") -> 2075.45 | Z19: =IF(AA19="正常",IF(I19="已计入",A19,Z18),"") -> 46007 | AA19: =IF(OR(AA18="错误",AND(I19<>"",I19<>"已排除",I19<>"待确认",I19<>"已计入")),"错误","正常") -> 正常 | AB19: =IF(AA19="正常",IF(I19="已计入",C19,AB18),"") -> 2.1043
... A74: 46157 | B74: 定投 | C74: 3.3486 | D74: 29.82 | E74: 100 | F74: 0.15 | G74: 历史估算 | H74: 原下单 2026-05-15T10:53:51 份额、费用及净值日沿用旧表估算 | I74: =IF(COUNTA(A74:H74)=0,"",IF(OR(OR(OR(G74="撤单",G74="交易失败",G74="交易关闭"),G74="交易失败",G74="交易关闭"),G74="交易失败",G74="交易关闭"),"已排除",IF(G74="待确认","待确认",IF(NOT(OR(G74="已确认",G74="历史估算")),"请选择确认状态",IF(NOT(ISNUMBER(A74)),"缺少有效净值日期",IF(OR(A74<=0,A74<>INT(A74)),"净值日期无效",IF(NOT(OR(OR(B74="买入",B74="定投",B74="转换转入"),B74="卖出",B74="现金分红",B74="红利再投")),"请选择交易类型",IF(NOT(ISNUMBER(C74)),"缺少成交净值",IF(C74<=0,"成交净值须大于零",IF(NOT(ISNUMBER(D74)),"缺少确认份额（分红填0）",IF(NOT(ISNUMBER(E74)),"缺少确认金额（再投填0）",IF(NOT(ISNUMBER(F74)),"缺少手续费（无费用填0）",IF(OR(D74<0,E74<0,F74<0),"份额金额费用不能为负",IF(AA73="错误","前行待修正",IF(A74<Z73,"日期需按成交顺序递增",IF(AND(B74="现金分红",OR(D74<>0,E74<=0,F74<>0)),"分红填份额0、费用0、正金额",IF(AND(B74="红利再投",OR(D74<=0,E74<>0,F74<>0)),"再投填正份额、金额0、费用0",IF(AND(OR(B74="现金分红",B74="红利再投"),K73<=0),"分红或再投前须有持仓",IF(AND(OR(OR(B74="买入",B74="定投",B74="转换转入"),B74="卖出"),OR(D74<=0,E74<=0)),"买卖须填正份额、正金额",IF(AND(B74="卖出",D74>K73+0.000001),"卖出份额超过持仓",IF(AND(OR(B74="买入",B74="定投",B74="转换转入"),F74>=E74),"申购费不能达到总支出",IF(NOT(ISNUMBER(持仓总览!$H$6)),"请填写金额核对容差",IF(持仓总览!$H$6<0,"金额核对容差不能为负",IF(NOT(OR(持仓总览!$C$7="利润优先",持仓总览!$C$7="本金优先")),"请选择卖出分配模式",IF(AND(OR(B74="买入",B74="定投",B74="转换转入"),ABS(E74-F74-C74*D74)>持仓总览!$H$6),"买入金额与份额净值不符",IF(AND(B74="卖出",ABS(E74+F74-C74*D74)>持仓总览!$H$6),"到账加费用与赎回市值不符","已计入")))))))))))))))))))))))))) -> 已计入 | J74: =IF(AA74="正常",IF(I74="已计入",IF(OR(OR(B74="买入",B74="定投",B74="转换转入"),B74="红利再投"),D74,IF(B74="卖出",-D74,0)),0),"") -> 29.82 | K74: =IF(AA74="正常",ROUND(K73+J74,6),"") -> 18942.58 | L74: =IF(I74="已计入",ROUND(K73*C74,2),"") -> 63331.27 | M74: =IF(I74="已计入",IF(B74="卖出",MAX(0,L74-Q73-F74),IF(B74="现金分红",MAX(0,L74+E74-Q73),0)),"") -> 0 | N74: =IF(I74="已计入",IF(AND(B74="卖出",持仓总览!$C$7="本金优先"),MAX(0,E74-Q73),IF(OR(B74="卖出",B74="现金分红"),MIN(E74,M74),0)),"") -> 0 | O74: =IF(I74="已计入",IF(OR(B74="卖出",B74="现金分红"),MIN(Q73,MAX(0,E74-N74)),0),"") -> 0 | P74: =IF(I74="已计入",IF(AND(B74="卖出",K74=0),MAX(0,Q73-O74),0),"") -> 0 | Q74: =IF(AA74="正常",IF(I74="已计入",ROUND(Q73+IF(OR(B74="买入",B74="定投",B74="转换转入"),E74,0)-O74-P74,2),Q73),"") -> 38746.01 | R74: =IF(I74="已计入",ROUND(K74*C74,2),"") -> 63431.12 | S74: =IF(I74="已计入",ROUND(R74-Q74,2),"") -> 24685.11 | T74: =IF(I74="已计入",IF(Q74=0,"",S74/Q74),"") -> 0.6371007 | U74: =IF(AA74="正常",U73+IF(AND(I74="已计入",OR(B74="买入",B74="定投",B74="转换转入")),E74,0),"") -> 38746.01 | V74: =IF(AA74="正常",V73+IF(AND(I74="已计入",OR(B74="卖出",B74="现金分红")),E74,0),"") -> 0 | W74: =IF(AA74="正常",W73+IF(I74="已计入",N74,0),"") -> 0 | X74: =IF(AA74="正常",X73+IF(I74="已计入",P74,0),"") -> 0 | Y74: =IF(I74="已计入",ROUND(R74+V74-U74,2),"") -> 24685.11 | Z74: =IF(AA74="正常",IF(I74="已计入",A74,Z73),"") -> 46157 | AA74: =IF(OR(AA73="错误",AND(I74<>"",I74<>"已排除",I74<>"待确认",I74<>"已计入")),"错误","正常") -> 正常 | AB74: =IF(AA74="正常",IF(I74="已计入",C74,AB73),"") -> 3.3486
A75: 46160 | B75: 定投 | C75: 3.289 | D75: 30.36 | E75: 100 | F75: 0.15 | G75: 历史估算 | H75: 原下单 2026-05-18T11:05:01 份额、费用及净值日沿用旧表估算 | I75: =IF(COUNTA(A75:H75)=0,"",IF(OR(OR(OR(G75="撤单",G75="交易失败",G75="交易关闭"),G75="���易失败",G75="交易关闭"),G75="交易失败",G75="交易关闭"),"已排除",IF(G75="待确认","待确认",IF(NOT(OR(G75="已确认",G75="历史估算")),"请选择确认状态",IF(NOT(ISNUMBER(A75)),"缺少有效净值日期",IF(OR(A75<=0,A75<>INT(A75)),"净值日期无效",IF(NOT(OR(OR(B75="买入",B75="定投",B75="转换转入"),B75="卖出",B75="现金分红",B75="红利再投")),"请选择交易类型",IF(NOT(ISNUMBER(C75)),"缺少成交净值",IF(C75<=0,"成交净值须大于零",IF(NOT(ISNUMBER(D75)),"缺少确认份额（分红填0）",IF(NOT(ISNUMBER(E75)),"缺少确认金额（再投填0）",IF(NOT(ISNUMBER(F75)),"缺少手续费（无费用填0）",IF(OR(D75<0,E75<0,F75<0),"份额金额费用不能为负",IF(AA74="错误","前行待修正",IF(A75<Z74,"日期需按成交顺序递增",IF(AND(B75="现金分红",OR(D75<>0,E75<=0,F75<>0)),"分红填份额0、费用0、正金额",IF(AND(B75="红利再投",OR(D75<=0,E75<>0,F75<>0)),"再投填正份额、金额0、费用0",IF(AND(OR(B75="现金分红",B75="红利再投"),K74<=0),"分红或再投前须有持仓",IF(AND(OR(OR(B75="买入",B75="定投",B75="转换转入"),B75="卖出"),OR(D75<=0,E75<=0)),"买卖须填正份额、正金额",IF(AND(B75="卖出",D75>K74+0.000001),"卖出份额超过持仓",IF(AND(OR(B75="买入",B75="定投",B75="转换转入"),F75>=E75),"申购费不能达到总支出",IF(NOT(ISNUMBER(持仓总览!$H$6)),"请填写金额核对容差",IF(持仓总览!$H$6<0,"金额核对容差不能为负",IF(NOT(OR(持仓总览!$C$7="利润优先",持仓总览!$C$7="本金优先")),"请选择卖出分配模式",IF(AND(OR(B75="买入",B75="定投",B75="转换转入"),ABS(E75-F75-C75*D75)>持仓总览!$H$6),"买入金额与份额净值不符",IF(AND(B75="卖出",ABS(E75+F75-C75*D75)>持仓总览!$H$6),"到账加费用与赎回市值不符","已计入")))))))))))))))))))))))))) -> 已计入 | J75: =IF(AA75="正常",IF(I75="已计入",IF(OR(OR(B75="买入",B75="定投",B75="转换转入"),B75="红利再投"),D75,IF(B75="卖出",-D75,0)),0),"") -> 30.36 | K75: =IF(AA75="正常",ROUND(K74+J75,6),"") -> 18972.94 | L75: =IF(I75="已计入",ROUND(K74*C75,2),"") -> 62302.15 | M75: =IF(I75="已计入",IF(B75="卖出",MAX(0,L75-Q74-F75),IF(B75="现金分红",MAX(0,L75+E75-Q74),0)),"") -> 0 | N75: =IF(I75="已计入",IF(AND(B75="卖出",持仓总览!$C$7="本金优先"),MAX(0,E75-Q74),IF(OR(B75="卖出",B75="现金分红"),MIN(E75,M75),0)),"") -> 0 | O75: =IF(I75="已计入",IF(OR(B75="卖出",B75="现金分红"),MIN(Q74,MAX(0,E75-N75)),0),"") -> 0 | P75: =IF(I75="已计入",IF(AND(B75="卖出",K75=0),MAX(0,Q74-O75),0),"") -> 0 | Q75: =IF(AA75="正常",IF(I75="已计入",ROUND(Q74+IF(OR(B75="买入",B75="定投",B75="转换转入"),E75,0)-O75-P75,2),Q74),"") -> 38846.01 | R75: =IF(I75="已计入",ROUND(K75*C75,2),"") -> 62402 | S75: =IF(I75="已计入",ROUND(R75-Q75,2),"") -> 23555.99 | T75: =IF(I75="已计入",IF(Q75=0,"",S75/Q75),"") -> 0.60639407 | U75: =IF(AA75="正常",U74+IF(AND(I75="已计入",OR(B75="买入",B75="定投",B75="转换转入")),E75,0),"") -> 38846.01 | V75: =IF(AA75="正常",V74+IF(AND(I75="已计入",OR(B75="卖出",B75="现金分红")),E75,0),"") -> 0 | W75: =IF(AA75="正常",W74+IF(I75="已计入",N75,0),"") -> 0 | X75: =IF(AA75="正常",X74+IF(I75="已计入",P75,0),"") -> 0 | Y75: =IF(I75="已计入",ROUND(R75+V75-U75,2),"") -> 23555.99 | Z75: =IF(AA75="正常",IF(I75="已计入",A75,Z74),"") -> 46160 | AA75: =IF(OR(AA74="错误",AND(I75<>"",I75<>"已排除",I75<>"待确认",I75<>"已计入")),"错误","正常") -> 正常 | AB75: =IF(AA75="正常",IF(I75="已计入",C75,AB74),"") -> 3.289
A76: 46161 | B76: 定投 | C76: 3.2976 | D76: 30.28 | E76: 100 | F76: 0.15 | G76: 历史估算 | H76: 原下单 2026-05-19T10:53:11 份额、费用及净值日沿用旧表估算 | I76: =IF(COUNTA(A76:H76)=0,"",IF(OR(OR(OR(G76="撤单",G76="交易失败",G76="交易关闭"),G76="交易失败",G76="交易关闭"),G76="交易失败",G76="交易关闭"),"已排除",IF(G76="待确认","待确认",IF(NOT(OR(G76="已确认",G76="历史估算")),"请选择确认状态",IF(NOT(ISNUMBER(A76)),"缺少有效净值日期",IF(OR(A76<=0,A76<>INT(A76)),"净值日期无效",IF(NOT(OR(OR(B76="买入",B76="定投",B76="转换转入"),B76="卖出",B76="现金分红",B76="红利再投")),"请选择交易类型",IF(NOT(ISNUMBER(C76)),"缺少成交净值",IF(C76<=0,"成交净值须大于零",IF(NOT(ISNUMBER(D76)),"缺少确认份额（分红填0）",IF(NOT(ISNUMBER(E76)),"缺少确认金额（再投填0）",IF(NOT(ISNUMBER(F76)),"缺少手续费（无费用填0）",IF(OR(D76<0,E76<0,F76<0),"份额金额费用不能为负",IF(AA75="错误","前行待修正",IF(A76<Z75,"日期需按成交顺序递增",IF(AND(B76="现金分红",OR(D76<>0,E76<=0,F76<>0)),"分红填份额0、费用0、正金额",IF(AND(B76="红利再投",OR(D76<=0,E76<>0,F76<>0)),"再投填正份额、金额0、费用0",IF(AND(OR(B76="现金分红",B76="红利再投"),K75<=0),"分红或再投前须有持仓",IF(AND(OR(OR(B76="买入",B76="定投",B76="转换转入"),B76="卖出"),OR(D76<=0,E76<=0)),"买卖须填正份额、正金额",IF(AND(B76="卖出",D76>K75+0.000001),"卖出份额超过持仓",IF(AND(OR(B76="买入",B76="定投",B76="转换转入"),F76>=E76),"申购费不能达到总支出",IF(NOT(ISNUMBER(持仓总览!$H$6)),"请填写金额核对容差",IF(持仓总览!$H$6<0,"金额核对容差不能为负",IF(NOT(OR(持仓总览!$C$7="利润优先",持仓总览!$C$7="本金优先")),"请选择卖出分配模式",IF(AND(OR(B76="买入",B76="定投",B76="转换转入"),ABS(E76-F76-C76*D76)>持仓总览!$H$6),"买入金额与份额净值不符",IF(AND(B76="卖出",ABS(E76+F76-C76*D76)>持仓总览!$H$6),"到账加费用与赎回市值不符","已计入")))))))))))))))))))))))))) -> 已计入 | J76: =IF(AA76="正常",IF(I76="已计入",IF(OR(OR(B76="买入",B76="定投",B76="转换转入"),B76="红利再投"),D76,IF(B76="卖出",-D76,0)),0),"") -> 30.28 | K76: =IF(AA76="正常",ROUND(K75+J76,6),"") -> 19003.22 | L76: =IF(I76="已计入",ROUND(K75*C76,2),"") -> 62565.17 | M76: =IF(I76="已计入",IF(B76="卖出",MAX(0,L76-Q75-F76),IF(B76="现金分红",MAX(0,L76+E76-Q75),0)),"") -> 0 | N76: =IF(I76="已计入",IF(AND(B76="卖出",持仓总览!$C$7="本金优先"),MAX(0,E76-Q75),IF(OR(B76="卖出",B76="现金分红"),MIN(E76,M76),0)),"") -> 0 | O76: =IF(I76="已计入",IF(OR(B76="卖出",B76="现金分红"),MIN(Q75,MAX(0,E76-N76)),0),"") -> 0 | P76: =IF(I76="已计入",IF(AND(B76="卖出",K76=0),MAX(0,Q75-O76),0),"") -> 0 | Q76: =IF(AA76="正常",IF(I76="已计入",ROUND(Q75+IF(OR(B76="买入",B76="定投",B76="转换转入"),E76,0)-O76-P76,2),Q75),"") -> 38946.01 | R76: =IF(I76="已计入",ROUND(K76*C76,2),"") -> 62665.02 | S76: =IF(I76="已计入",ROUND(R76-Q76,2),"") -> 23719.01 | T76: =IF(I76="已计入",IF(Q76=0,"",S76/Q76),"") -> 0.60902285 | U76: =IF(AA76="正常",U75+IF(AND(I76="已计入",OR(B76="买入",B76="定投",B76="转换转入")),E76,0),"") -> 38946.01 | V76: =IF(AA76="正常",V75+IF(AND(I76="已计入",OR(B76="卖出",B76="现金分红")),E76,0),"") -> 0 | W76: =IF(AA76="正常",W75+IF(I76="已计入",N76,0),"") -> 0 | X76: =IF(AA76="正常",X75+IF(I76="已计入",P76,0),"") -> 0 | Y76: =IF(I76="已计入",ROUND(R76+V76-U76,2),"") -> 23719.01 | Z76: =IF(AA76="正常",IF(I76="已计入",A76,Z75),"") -> 46161 | AA76: =IF(OR(AA75="错误",AND(I76<>"",I76<>"已排除",I76<>"待确认",I76<>"已计入")),"错误","正常") -> 正常 | AB76: =IF(AA76="正常",IF(I76="已计入",C76,AB75),"") -> 3.2976
A77: 46162 | B77: 定投 | C77: 3.3782 | D77: 29.56 | E77: 100 | F77: 0.15 | G77: 历史估算 | H77: 原下单 2026-05-20T10:54:27 份额、费用及净值日沿用旧表估算 | I77: =IF(COUNTA(A77:H77)=0,"",IF(OR(OR(OR(G77="撤单",G77="交易失败",G77="交易关闭"),G77="交易失败",G77="交易关闭"),G77="交易失败",G77="交易关闭"),"已排除",IF(G77="待确认","待确认",IF(NOT(OR(G77="已确认",G77="历史估算")),"请选择确认状态",IF(NOT(ISNUMBER(A77)),"缺少有效净值日期",IF(OR(A77<=0,A77<>INT(A77)),"净值日期无效",IF(NOT(OR(OR(B77="买入",B77="定投",B77="转换转入"),B77="卖出",B77="现金分红",B77="红利再投")),"请选择交易类型",IF(NOT(ISNUMBER(C77)),"缺少成交净值",IF(C77<=0,"成交净值须大于零",IF(NOT(ISNUMBER(D77)),"缺少确认份额（分红填0）",IF(NOT(ISNUMBER(E77)),"缺少确认金额（再投填0）",IF(NOT(ISNUMBER(F77)),"缺少手续费（无费用填0）",IF(OR(D77<0,E77<0,F77<0),"份额金额费用不能为负",IF(AA76="错误","前行待修正",IF(A77<Z76,"日期需按成交顺序递增",IF(AND(B77="现金分红",OR(D77<>0,E77<=0,F77<>0)),"分红填份额0、费用0、正金额",IF(AND(B77="红利再投",OR(D77<=0,E77<>0,F77<>0)),"再投填正份额、金额0、费用0",IF(AND(OR(B77="现金分红",B77="红利再投"),K76<=0),"分红或再投前须有持仓",IF(AND(OR(OR(B77="买入",B77="定投",B77="转换转入"),B77="卖出"),OR(D77<=0,E77<=0)),"买卖须填正份额、正金额",IF(AND(B77="卖出",D77>K76+0.000001),"卖出份额超过持仓",IF(AND(OR(B77="买入",B77="定投",B77="转换转入"),F77>=E77),"申购费不能达到总支出",IF(NOT(ISNUMBER(持仓总览!$H$6)),"请填写金额核对容差",IF(持仓总览!$H$6<0,"金额核对容差不能为负",IF(NOT(OR(持仓总览!$C$7="利润优先",持仓总览!$C$7="本金优先")),"请选择卖出分配模式",IF(AND(OR(B77="买入",B77="定投",B77="转换转入"),ABS(E77-F77-C77*D77)>持仓总览!$H$6),"买入金额与份额净值不符",IF(AND(B77="卖出",ABS(E77+F77-C77*D77)>持仓总览!$H$6),"到账加费用与赎回市值不符","已计入")))))))))))))))))))))))))) -> 已计入 | J77: =IF(AA77="正常",IF(I77="已计入",IF(OR(OR(B77="买入",B77="定投",B77="转换转入"),B77="红利再投"),D77,IF(B77="卖出",-D77,0)),0),"") -> 29.56 | K77: =IF(AA77="正常",ROUND(K76+J77,6),"") -> 19032.78 | L77: =IF(I77="已计入",ROUND(K76*C77,2),"") -> 64196.68 | M77: =IF(I77="已计入",IF(B77="卖出",MAX(0,L77-Q76-F77),IF(B77="现金分红",MAX(0,L77+E77-Q76),0)),"") -> 0 | N77: =IF(I77="已计入",IF(AND(B77="卖出",持仓总览!$C$7="本金优先"),MAX(0,E77-Q76),IF(OR(B77="卖出",B77="现金分红"),MIN(E77,M77),0)),"") -> 0 | O77: =IF(I77="已计入",IF(OR(B77="卖出",B77="现金分红"),MIN(Q76,MAX(0,E77-N77)),0),"") -> 0 | P77: =IF(I77="已计入",IF(AND(B77="卖出",K77=0),MAX(0,Q76-O77),0),"") -> 0 | Q77: =IF(AA77="正常",IF(I77="已计入",ROUND(Q76+IF(OR(B77="买入",B77="定投",B77="转换转入"),E77,0)-O77-P77,2),Q76),"") -> 39046.01 | R77: =IF(I77="已计入",ROUND(K77*C77,2),"") -> 64296.54 | S77: =IF(I77="已计入",ROUND(R77-Q77,2),"") -> 25250.53 | T77: =IF(I77="已计入",IF(Q77=0,"",S77/Q77),"") -> 0.64668656 | U77: =IF(AA77="正常",U76+IF(AND(I77="已计入",OR(B77="买入",B77="定投",B77="转换转入")),E77,0),"") -> 39046.01 | V77: =IF(AA77="正常",V76+IF(AND(I77="已计入",OR(B77="卖出",B77="现金分红")),E77,0),"") -> 0 | W77: =IF(AA77="正常",W76+IF(I77="已计入",N77,0),"") -> 0 | X77: =IF(AA77="正常",X76+IF(I77="已计入",P77,0),"") -> 0 | Y77: =IF(I77="已计入",ROUND(R77+V77-U77,2),"") -> 25250.53 | Z77: =IF(AA77="正常",IF(I77="已计入",A77,Z76),"") -> 46162 | AA77: =IF(OR(AA76="错误",AND(I77<>"",I77<>"已排除",I77<>"待确认",I77<>"已计入")),"错误","正常") -> 正常 | AB77: =IF(AA77="正常",IF(I77="已计入",C77,AB76),"") -> 3.3782
A78: 46163 | B78: 定投 | C78: 3.359 | D78: 2.97 | E78: 10 | F78: 0.02 | G78: 历史估算 | H78: 原下单 2026-05-21T11:41:41 份额、费用及净值日沿用旧表估算 | I78: =IF(COUNTA(A78:H78)=0,"",IF(OR(OR(OR(G78="撤单",G78="交易失败",G78="交易关闭"),G78="交易失败",G78="交易关闭"),G78="交易失败",G78="交易关闭"),"已排除",IF(G78="待确认","待确认",IF(NOT(OR(G78="已确认",G78="历史估算")),"请选择确认状态",IF(NOT(ISNUMBER(A78)),"缺少有效净值日期",IF(OR(A78<=0,A78<>INT(A78)),"净值日期无效",IF(NOT(OR(OR(B78="买入",B78="定投",B78="转换转入"),B78="卖出",B78="现金分红",B78="红利再投")),"请选择交易类型",IF(NOT(ISNUMBER(C78)),"缺少成交净值",IF(C78<=0,"成交净值须大于零",IF(NOT(ISNUMBER(D78)),"缺少确认份额（分红填0）",IF(NOT(ISNUMBER(E78)),"缺少确认金额（再投填0）",IF(NOT(ISNUMBER(F78)),"缺少手续费（无费用填0）",IF(OR(D78<0,E78<0,F78<0),"份额金额费用不能为负",IF(AA77="错误","前行待修正",IF(A78<Z77,"日期需按成交顺序递增",IF(AND(B78="现金分红",OR(D78<>0,E78<=0,F78<>0)),"分红填份额0、费用0、正金额",IF(AND(B78="红利再投",OR(D78<=0,E78<>0,F78<>0)),"再投填正份额、金额0、费用0",IF(AND(OR(B78="现金分红",B78="红利再投"),K77<=0),"分红或再投前须有持仓",IF(AND(OR(OR(B78="买入",B78="定投",B78="转换转入"),B78="卖出"),OR(D78<=0,E78<=0)),"买卖须填正份额、正金额",IF(AND(B78="卖出",D78>K77+0.000001),"卖出份额超过持仓",IF(AND(OR(B78="买入",B78="定投",B78="转换转入"),F78>=E78),"申购费不能达到总支出",IF(NOT(ISNUMBER(持仓总览!$H$6)),"请填写金额核对容差",IF(持仓总览!$H$6<0,"金额核对容差不能为负",IF(NOT(OR(持仓总览!$C$7="利润优先",持仓总览!$C$7="本金优先")),"请选择卖出分配模式",IF(AND(OR(B78="买入",B78="定投",B78="转换转入"),ABS(E78-F78-C78*D78)>持仓总览!$H$6),"买入金额与份额净值不符",IF(AND(B78="卖出",ABS(E78+F78-C78*D78)>持仓总览!$H$6),"到账加费用与赎回市值不符","已计入")))))))))))))))))))))))))) -> 已计入 | J78: =IF(AA78="正常",IF(I78="已计入",IF(OR(OR(B78="买入",B78="定投",B78="转换转入"),B78="红利再投"),D78,IF(B78="卖出",-D78,0)),0),"") -> 2.97 | K78: =IF(AA78="正常",ROUND(K77+J78,6),"") -> 19035.75 | L78: =IF(I78="已计入",ROUND(K77*C78,2),"") -> 63931.11 | M78: =IF(I78="已计入",IF(B78="卖出",MAX(0,L78-Q77-F78),IF(B78="现金分红",MAX(0,L78+E78-Q77),0)),"") -> 0 | N78: =IF(I78="已计入",IF(AND(B78="卖出",持仓总览!$C$7="本金优先"),MAX(0,E78-Q77),IF(OR(B78="卖出",B78="现金分红"),MIN(E78,M78),0)),"") -> 0 | O78: =IF(I78="已计入",IF(OR(B78="卖出",B78="现金分红"),MIN(Q77,MAX(0,E78-N78)),0),"") -> 0 | P78: =IF(I78="已计入",IF(AND(B78="卖出",K78=0),MAX(0,Q77-O78),0),"") -> 0 | Q78: =IF(AA78="正常",IF(I78="已计入",ROUND(Q77+IF(OR(B78="买入",B78="定投",B78="转换转入"),E78,0)-O78-P78,2),Q77),"") -> 39056.01 | R78: =IF(I78="已计入",ROUND(K78*C78,2),"") -> 63941.08 | S78: =IF(I78="已计入",ROUND(R78-Q78,2),"") -> 24885.07 | T78: =IF(I78="已计入",IF(Q78=0,"",S78/Q78),"") -> 0.63716365 | U78: =IF(AA78="正常",U77+IF(AND(I78="已计入",OR(B78="买入",B78="定投",B78="转换转入")),E78,0),"") -> 39056.01 | V78: =IF(AA78="正常",V77+IF(AND(I78="已计入",OR(B78="卖出",B78="现金分红")),E78,0),"") -> 0 | W78: =IF(AA78="正常",W77+IF(I78="已计入",N78,0),"") -> 0 | X78: =IF(AA78="正常",X77+IF(I78="已计入",P78,0),"") -> 0 | Y78: =IF(I78="已计入",ROUND(R78+V78-U78,2),"") -> 24885.07 | Z78: =IF(AA78="正常",IF(I78="已计入",A78,Z77),"") -> 46163 | AA78: =IF(OR(AA77="错误",AND(I78<>"",I78<>"已排除",I78<>"待确认",I78<>"已计入")),"错误","正常") -> 正常 | AB78: =IF(AA78="正常",IF(I78="已计入",C78,AB77),"") -> 3.359
A79: 46164 | B79: 定投 | C79: 3.4943 | D79: 14.29 | E79: 50 | F79: 0.08 | G79: 历史估算 | H79: 原下单 2026-05-22T11:38:01 份额、费用及净值日沿用旧表估算 | I79: =IF(COUNTA(A79:H79)=0,"",IF(OR(OR(OR(G79="撤单",G79="交易失败",G79="交易关闭"),G79="交易失败",G79="交易关闭"),G79="交易失败",G79="交易关闭"),"已排除",IF(G79="待确认","待确认",IF(NOT(OR(G79="已确认",G79="历史估算")),"请选择确认状态",IF(NOT(ISNUMBER(A79)),"缺少有效净值日期",IF(OR(A79<=0,A79<>INT(A79)),"净值日期无效",IF(NOT(OR(OR(B79="买入",B79="定投",B79="转换转入"),B79="卖出",B79="现金分红",B79="红利再投")),"请选择交易类型",IF(NOT(ISNUMBER(C79)),"缺少成交净值",IF(C79<=0,"成交净值须大于零",IF(NOT(ISNUMBER(D79)),"缺少确认份额（分红填0）",IF(NOT(ISNUMBER(E79)),"缺少确认金额（再投填0）",IF(NOT(ISNUMBER(F79)),"缺少手续费（无费用填0）",IF(OR(D79<0,E79<0,F79<0),"份额金额费用不能为负",IF(AA78="错误","前行待修正",IF(A79<Z78,"日期需按成交顺序递增",IF(AND(B79="现金分红",OR(D79<>0,E79<=0,F79<>0)),"分红填份额0、费用0、正金额",IF(AND(B79="红利再投",OR(D79<=0,E79<>0,F79<>0)),"再投填正份额、金额0、费用0",IF(AND(OR(B79="现金分红",B79="红利再投"),K78<=0),"分红或再投前须有持仓",IF(AND(OR(OR(B79="买入",B79="定投",B79="转换转入"),B79="卖出"),OR(D79<=0,E79<=0)),"买卖须填正份额、正金额",IF(AND(B79="卖出",D79>K78+0.000001),"卖出份额超过持仓",IF(AND(OR(B79="买入",B79="定投",B79="转换转入"),F79>=E79),"申购费不能达到总支出",IF(NOT(ISNUMBER(持仓总览!$H$6)),"请填写金额核对容差",IF(持仓总览!$H$6<0,"金额核对容差不能为负",IF(NOT(OR(持仓总览!$C$7="利润优先",持仓总览!$C$7="本金优先")),"请选择卖出分配模式",IF(AND(OR(B79="买入",B79="定投",B79="转换转入"),ABS(E79-F79-C79*D79)>持仓总览!$H$6),"买入金额与份额净值不符",IF(AND(B79="卖出",ABS(E79+F79-C79*D79)>持仓总览!$H$6),"到账加费用与赎回市值不符","已计入")))))))))))))))))))))))))) -> 已计入 | J79: =IF(AA79="正常",IF(I79="已计入",IF(OR(OR(B79="买入",B79="定投",B79="转换转入"),B79="红利再投"),D79,IF(B79="卖出",-D79,0)),0),"") -> 14.29 | K79: =IF(AA79="正常",ROUND(K78+J79,6),"") -> 19050.04 | L79: =IF(I79="已计入",ROUND(K78*C79,2),"") -> 66516.62 | M79: =IF(I79="已计入",IF(B79="卖出",MAX(0,L79-Q78-F79),IF(B79="现金分红",MAX(0,L79+E79-Q78),0)),"") -> 0 | N79: =IF(I79="已计入",IF(AND(B79="卖出",持仓总览!$C$7="本金优先"),MAX(0,E79-Q78),IF(OR(B79="卖出",B79="现金分红"),MIN(E79,M79),0)),"") -> 0 | O79: =IF(I79="已计入",IF(OR(B79="卖出",B79="现金分红"),MIN(Q78,MAX(0,E79-N79)),0),"") -> 0 | P79: =IF(I79="已计入",IF(AND(B79="卖出",K79=0),MAX(0,Q78-O79),0),"") -> 0 | Q79: =IF(AA79="正常",IF(I79="已计入",ROUND(Q78+IF(OR(B79="买入",B79="定投",B79="转换转入"),E79,0)-O79-P79,2),Q78),"") -> 39106.01 | R79: =IF(I79="已计入",ROUND(K79*C79,2),"") -> 66566.55 | S79: =IF(I79="已计入",ROUND(R79-Q79,2),"") -> 27460.54 | T79: =IF(I79="已计入",IF(Q79=0,"",S79/Q79),"") -> 0.70220767 | U79: =IF(AA79="正常",U78+IF(AND(I79="已计入",OR(B79="买入",B79="定投",B79="转换转入")),E79,0),"") -> 39106.01 | V79: =IF(AA79="正常",V78+IF(AND(I79="已计入",OR(B79="卖出",B79="现金分红")),E79,0),"") -> 0 | W79: =IF(AA79="正常",W78+IF(I79="已计入",N79,0),"") -> 0 | X79: =IF(AA79="正常",X78+IF(I79="已计入",P79,0),"") -> 0 | Y79: =IF(I79="已计入",ROUND(R79+V79-U79,2),"") -> 27460.54 | Z79: =IF(AA79="正常",IF(I79="已计入",A79,Z78),"") -> 46164 | AA79: =IF(OR(AA78="错误",AND(I79<>"",I79<>"已排除",I79<>"待确认",I79<>"已计入")),"错误","正常") -> 正常 | AB79: =IF(AA79="正常",IF(I79="已计入",C79,AB78),"") -> 3.4943
A80: 46168 | B80: 定投 | C80: 3.6122 | D80: 13.82 | E80: 50 | F80: 0.08 | G80: 历史估算 | H80: 原下单 2026-05-26T10:56:44 份额、费用及净值日沿用旧表估算 | I80: =IF(COUNTA(A80:H80)=0,"",IF(OR(OR(OR(G80="撤单",G80="交易失败",G80="交易关闭"),G80="交易失败",G80="交易关闭"),G80="交易失败",G80="交易关闭"),"已排除",IF(G80="待确认","待确认",IF(NOT(OR(G80="已确认",G80="历史估算")),"请选择确认状态",IF(NOT(ISNUMBER(A80)),"缺少有效净值日期",IF(OR(A80<=0,A80<>INT(A80)),"净值日期无效",IF(NOT(OR(OR(B80="买入",B80="定投",B80="转换转入"),B80="卖出",B80="现金分红",B80="红利再投")),"请选择交易类型",IF(NOT(ISNUMBER(C80)),"缺少成交净值",IF(C80<=0,"成交净值须大于零",IF(NOT(ISNUMBER(D80)),"缺少确认份额（分红填0）",IF(NOT(ISNUMBER(E80)),"缺少确认金额（再投填0）",IF(NOT(ISNUMBER(F80)),"缺少手续费（无费用填0）",IF(OR(D80<0,E80<0,F80<0),"份额金额费用不能为负",IF(AA79="错误","前行待修正",IF(A80<Z79,"日期需按成交顺序递增",IF(AND(B80="现金分红",OR(D80<>0,E80<=0,F80<>0)),"分红填份额0、费用0、正金额",IF(AND(B80="红利再投",OR(D80<=0,E80<>0,F80<>0)),"再投填正份额、金额0、费用0",IF(AND(OR(B80="现金分红",B80="红利再投"),K79<=0),"分红或再投前须有持仓",IF(AND(OR(OR(B80="买入",B80="定投",B80="转换转入"),B80="卖出"),OR(D80<=0,E80<=0)),"买卖须填正份额、正金额",IF(AND(B80="卖出",D80>K79+0.000001),"卖出份额超过持仓",IF(AND(OR(B80="买入",B80="定投",B80="转换转入"),F80>=E80),"申购费不能达到总支出",IF(NOT(ISNUMBER(持仓总览!$H$6)),"请填写金额核对容差",IF(持仓总览!$H$6<0,"金额核对容差不能为负",IF(NOT(OR(持仓总览!$C$7="利润优先",持仓总览!$C$7="本金优先")),"请选择卖出分配模式",IF(AND(OR(B80="买入",B80="定投",B80="转换转入"),ABS(E80-F80-C80*D80)>持仓总览!$H$6),"买入金额与份额净值不符",IF(AND(B80="卖出",ABS(E80+F80-C80*D80)>持仓总览!$H$6),"到账加费用与赎回市值不符","已计入")))))))))))))))))))))))))) -> 已计入 | J80: =IF(AA80="正常",IF(I80="已计入",IF(OR(OR(B80="买入",B80="定投",B80="转换转入"),B80="红利再投"),D80,IF(B80="卖出",-D80,0)),0),"") -> 13.82 | K80: =IF(AA80="正常",ROUND(K79+J80,6),"") -> 19063.86 | L80: =IF(I80="已计入",ROUND(K79*C80,2),"") -> 68812.55 | M80: =IF(I80="已计入",IF(B80="卖出",MAX(0,L80-Q79-F80),IF(B80="现金分红",MAX(0,L80+E80-Q79),0)),"") -> 0 | N80: =IF(I80="已计入",IF(AND(B80="卖出",持仓总览!$C$7="本金优先"),MAX(0,E80-Q79),IF(OR(B80="卖出",B80="现金分红"),MIN(E80,M80),0)),"") -> 0 | O80: =IF(I80="已计入",IF(OR(B80="卖出",B80="现金分红"),MIN(Q79,MAX(0,E80-N80)),0),"") -> 0 | P80: =IF(I80="已计入",IF(AND(B80="卖出",K80=0),MAX(0,Q79-O80),0),"") -> 0 | Q80: =IF(AA80="正常",IF(I80="已计入",ROUND(Q79+IF(OR(B80="买入",B80="定投",B80="转换转入"),E80,0)-O80-P80,2),Q79),"") -> 39156.01 | R80: =IF(I80="已计入",ROUND(K80*C80,2),"") -> 68862.48 | S80: =IF(I80="已计入",ROUND(R80-Q80,2),"") -> 29706.47 | T80: =IF(I80="已计入",IF(Q80=0,"",S80/Q80),"") -> 0.75866949 | U80: =IF(AA80="正常",U79+IF(AND(I80="已计入",OR(B80="买入",B80="定投",B80="转换转入")),E80,0),"") -> 39156.01 | V80: =IF(AA80="正常",V79+IF(AND(I80="已计入",OR(B80="卖出",B80="现金分红")),E80,0),"") -> 0 | W80: =IF(AA80="正常",W79+IF(I80="已计入",N80,0),"") -> 0 | X80: =IF(AA80="正常",X79+IF(I80="已计入",P80,0),"") -> 0 | Y80: =IF(I80="已计入",ROUND(R80+V80-U80,2),"") -> 29706.47 | Z80: =IF(AA80="正常",IF(I80="已计入",A80,Z79),"") -> 46168 | AA80: =IF(OR(AA79="错误",AND(I80<>"",I80<>"已排除",I80<>"待确认",I80<>"已计入")),"错误","正常") -> 正常 | AB80: =IF(AA80="正常",IF(I80="已计入",C80,AB79),"") -> 3.6122
A81: 46169 | B81: 定投 | C81: 3.5766 | D81: 13.96 | E81: 50 | F81: 0.08 | G81: 历史估算 | H81: 原下单 2026-05-27T10:47:29 份额、费用及净值日沿用旧表估算 | I81: =IF(COUNTA(A81:H81)=0,"",IF(OR(OR(OR(G81="撤单",G81="交易失败",G81="交易关闭"),G81="交易失败",G81="交易关闭"),G81="交易失败",G81="交易关闭"),"已排除",IF(G81="待确认","待确认",IF(NOT(OR(G81="已确认",G81="历史估算")),"请选择确认状态",IF(NOT(ISNUMBER(A81)),"缺少有效净值日期",IF(OR(A81<=0,A81<>INT(A81)),"净值日期无效",IF(NOT(OR(OR(B81="买入",B81="定投",B81="转换转入"),B81="卖出",B81="现金分红",B81="红利再投")),"请选择交易类型",IF(NOT(ISNUMBER(C81)),"缺少成交净值",IF(C81<=0,"成交净值须大于零",IF(NOT(ISNUMBER(D81)),"缺少确认份额（分红填0）",IF(NOT(ISNUMBER(E81)),"缺少确认金额（再投填0）",IF(NOT(ISNUMBER(F81)),"缺少手续费（无费用填0）",IF(OR(D81<0,E81<0,F81<0),"份额金额费用不能为负",IF(AA80="错误","前行待修正",IF(A81<Z80,"日期需按成交顺序递增",IF(AND(B81="现金分红",OR(D81<>0,E81<=0,F81<>0)),"分红填份额0、费用0、正金额",IF(AND(B81="红利再投",OR(D81<=0,E81<>0,F81<>0)),"再投填正份额、金额0、费用0",IF(AND(OR(B81="现金分红",B81="红利再投"),K80<=0),"分红或再投前须有持仓",IF(AND(OR(OR(B81="买入",B81="定投",B81="转换转入"),B81="卖出"),OR(D81<=0,E81<=0)),"买卖须填正份额、正金额",IF(AND(B81="卖出",D81>K80+0.000001),"卖出份额超过持仓",IF(AND(OR(B81="买入",B81="定投",B81="转换转入"),F81>=E81),"申购费不能达到总支出",IF(NOT(ISNUMBER(持仓总览!$H$6)),"请填写金额核对容差",IF(持仓总览!$H$6<0,"金额核对容差不能为负",IF(NOT(OR(持仓总览!$C$7="利润优先",持仓总览!$C$7="本金优先")),"请选择卖出分配模式",IF(AND(OR(B81="买入",B81="定投",B81="转换转入"),ABS(E81-F81-C81*D81)>持仓总览!$H$6),"买入金额与份额净值不符",IF(AND(B81="卖出",ABS(E81+F81-C81*D81)>持仓总览!$H$6),"到账加费用与赎回市值不符","已计入")))))))))))))))))))))))))) -> 已计入 | J81: =IF(AA81="正常",IF(I81="已计入",IF(OR(OR(B81="买入",B81="定投",B81="转换转入"),B81="红利再投"),D81,IF(B81="卖出",-D81,0)),0),"") -> 13.96 | K81: =IF(AA81="正常",ROUND(K80+J81,6),"") -> 19077.82 | L81: =IF(I81="已计入",ROUND(K80*C81,2),"") -> 68183.8 | M81: =IF(I81="已计入",IF(B81="卖出",MAX(0,L81-Q80-F81),IF(B81="现金分红",MAX(0,L81+E81-Q80),0)),"") -> 0 | N81: =IF(I81="已计入",IF(AND(B81="卖出",持仓总览!$C$7="本金优先"),MAX(0,E81-Q80),IF(OR(B81="卖出",B81="现金分红"),MIN(E81,M81),0)),"") -> 0 | O81: =IF(I81="已计入",IF(OR(B81="卖出",B81="现金分红"),MIN(Q80,MAX(0,E81-N81)),0),"") -> 0 | P81: =IF(I81="已计入",IF(AND(B81="卖出",K81=0),MAX(0,Q80-O81),0),"") -> 0 | Q81: =IF(AA81="正常",IF(I81="已计入",ROUND(Q80+IF(OR(B81="买入",B81="定投",B81="转换转入"),E81,0)-O81-P81,2),Q80),"") -> 39206.01 | R81: =IF(I81="已计入",ROUND(K81*C81,2),"") -> 68233.73 | S81: =IF(I81="已计入",ROUND(R81-Q81,2),"") -> 29027.72 | T81: =IF(I81="已计入",IF(Q81=0,"",S81/Q81),"") -> 0.74038955 | U81: =IF(AA81="正常",U80+IF(AND(I81="已计入",OR(B81="买入",B81="定投",B81="转换转入")),E81,0),"") -> 39206.01 | V81: =IF(AA81="正常",V80+IF(AND(I81="已计入",OR(B81="卖出",B81="现金分红")),E81,0),"") -> 0 | W81: =IF(AA81="正常",W80+IF(I81="已计入",N81,0),"") -> 0 | X81: =IF(AA81="正常",X80+IF(I81="已计入",P81,0),"") -> 0 | Y81: =IF(I81="已计入",ROUND(R81+V81-U81,2),"") -> 29027.72 | Z81: =IF(AA81="正常",IF(I81="已计入",A81,Z80),"") -> 46169 | AA81: =IF(OR(AA80="错误",AND(I81<>"",I81<>"已排除",I81<>"待确认",I81<>"已计入")),"错误","正常") -> 正常 | AB81: =IF(AA81="正常",IF(I81="已计入",C81,AB80),"") -> 3.5766
A82: 46176 | B82: 买入 | C82: 3.7821 | D82: 264.01 | E82: 1000 | F82: 1.5 | G82: 历史估算 | H82: 原下单 2026-06-02T22:49:00 份额、费用及净值日沿用旧表估算 | I82: =IF(COUNTA(A82:H82)=0,"",IF(OR(OR(OR(G82="撤单",G82="交易失败",G82="交易关闭"),G82="交易失败",G82="交易关闭"),G82="交易失败",G82="交易关闭"),"已排除",IF(G82="待确认","待确认",IF(NOT(OR(G82="已确认",G82="历史估算")),"请选择确认状态",IF(NOT(ISNUMBER(A82)),"缺少有效净值日期",IF(OR(A82<=0,A82<>INT(A82)),"净值日期无效",IF(NOT(OR(OR(B82="买入",B82="定投",B82="转换转入"),B82="卖出",B82="现金分红",B82="红利再投")),"请选择交易类型",IF(NOT(ISNUMBER(C82)),"缺少成交净值",IF(C82<=0,"成交净值须大于零",IF(NOT(ISNUMBER(D82)),"缺少确认份额（分红填0）",IF(NOT(ISNUMBER(E82)),"缺少确认金额（再投填0）",IF(NOT(ISNUMBER(F82)),"缺少手续费（无费用填0）",IF(OR(D82<0,E82<0,F82<0),"份额金额费用不能为负",IF(AA81="错误","前行待修正",IF(A82<Z81,"日期需按成交顺序递增",IF(AND(B82="现金分红",OR(D82<>0,E82<=0,F82<>0)),"分红填份额0、费用0、正金额",IF(AND(B82="红利再投",OR(D82<=0,E82<>0,F82<>0)),"再投填正份额、金额0、费用0",IF(AND(OR(B82="现金分红",B82="红利再投"),K81<=0),"分红或再投前须有持仓",IF(AND(OR(OR(B82="买入",B82="定投",B82="转换转入"),B82="卖出"),OR(D82<=0,E82<=0)),"买卖须填正份额、正金额",IF(AND(B82="卖出",D82>K81+0.000001),"卖出份额超过持仓",IF(AND(OR(B82="买入",B82="定投",B82="转换转入"),F82>=E82),"申购费不能达到总支出",IF(NOT(ISNUMBER(持仓总览!$H$6)),"请填写金额核对容差",IF(持仓总览!$H$6<0,"金额核对容差不能为负",IF(NOT(OR(持仓总览!$C$7="利润优先",持仓总览!$C$7="本金优先")),"请选择卖出分配模式",IF(AND(OR(B82="买入",B82="定投",B82="转换转入"),ABS(E82-F82-C82*D82)>持仓总览!$H$6),"买入金额与份额净值不符",IF(AND(B82="卖出",ABS(E82+F82-C82*D82)>持仓总览!$H$6),"到账加费用与赎回市值不符","已计入")))))))))))))))))))))))))) -> 已计入 | J82: =IF(AA82="正常",IF(I82="已计入",IF(OR(OR(B82="买入",B82="定投",B82="转换转入"),B82="红利再投"),D82,IF(B82="卖出",-D82,0)),0),"") -> 264.01 | K82: =IF(AA82="正常",ROUND(K81+J82,6),"") -> 19341.83 | L82: =IF(I82="已计入",ROUND(K81*C82,2),"") -> 72154.22 | M82: =IF(I82="已计入",IF(B82="卖出",MAX(0,L82-Q81-F82),IF(B82="现金分红",MAX(0,L82+E82-Q81),0)),"") -> 0 | N82: =IF(I82="已计入",IF(AND(B82="卖出",持仓总览!$C$7="本金优先"),MAX(0,E82-Q81),IF(OR(B82="卖出",B82="现金分红"),MIN(E82,M82),0)),"") -> 0 | O82: =IF(I82="已计入",IF(OR(B82="卖出",B82="现金分红"),MIN(Q81,MAX(0,E82-N82)),0),"") -> 0 | P82: =IF(I82="已计入",IF(AND(B82="卖出",K82=0),MAX(0,Q81-O82),0),"") -> 0 | Q82: =IF(AA82="正常",IF(I82="已计入",ROUND(Q81+IF(OR(B82="买入",B82="定投",B82="转换转入"),E82,0)-O82-P82,2),Q81),"") -> 40206.01 | R82: =IF(I82="已计入",ROUND(K82*C82,2),"") -> 73152.74 | S82: =IF(I82="已计入",ROUND(R82-Q82,2),"") -> 32946.73 | T82: =IF(I82="已计入",IF(Q82=0,"",S82/Q82),"") -> 0.81944789 | U82: =IF(AA82="正常",U81+IF(AND(I82="已计入",OR(B82="买入",B82="定投",B82="转换转入")),E82,0),"") -> 40206.01 | V82: =IF(AA82="正常",V81+IF(AND(I82="已计入",OR(B82="卖出",B82="现金分红")),E82,0),"") -> 0 | W82: =IF(AA82="正常",W81+IF(I82="已计入",N82,0),"") -> 0 | X82: =IF(AA82="正常",X81+IF(I82="已计入",P82,0),"") -> 0 | Y82: =IF(I82="已计入",ROUND(R82+V82-U82,2),"") -> 32946.73 | Z82: =IF(AA82="正常",IF(I82="已计入",A82,Z81),"") -> 46176 | AA82: =IF(OR(AA81="错误",AND(I82<>"",I82<>"已排除",I82<>"待确认",I82<>"已计入")),"错误","正常") -> 正常 | AB82: =IF(AA82="正常",IF(I82="已计入",C82,AB81),"") -> 3.7821
A83: 46181 | B83: 定投 | C83: 3.4906 | D83: 14.3 | E83: 50 | F83: 0.08 | G83: 历史估算 | H83: 原下单 2026-06-08T12:22:09 份额、费用及净值日沿用旧表估算 | I83: =IF(COUNTA(A83:H83)=0,"",IF(OR(OR(OR(G83="撤单",G83="交易失败",G83="交易关闭"),G83="交易失败",G83="交易关闭"),G83="交易失败",G83="交易关闭"),"已排除",IF(G83="待确认","待确认",IF(NOT(OR(G83="已确认",G83="历史估算")),"请选择确认状态",IF(NOT(ISNUMBER(A83)),"缺少有效净值日期",IF(OR(A83<=0,A83<>INT(A83)),"净值日期无效",IF(NOT(OR(OR(B83="买入",B83="定投",B83="转换转入"),B83="卖出",B83="现金分红",B83="红利再投")),"请选择交易类型",IF(NOT(ISNUMBER(C83)),"缺少成交净值",IF(C83<=0,"成交净值须大于零",IF(NOT(ISNUMBER(D83)),"缺少确认份额（分红填0）",IF(NOT(ISNUMBER(E83)),"缺少确认金额（再投填0）",IF(NOT(ISNUMBER(F83)),"缺少手续费（无费用填0）",IF(OR(D83<0,E83<0,F83<0),"份额金额费用不能为负",IF(AA82="错误","前行待修正",IF(A83<Z82,"日期需按成交顺序递增",IF(AND(B83="现金分红",OR(D83<>0,E83<=0,F83<>0)),"分红填份额0、费用0、正金额",IF(AND(B83="红利再投",OR(D83<=0,E83<>0,F83<>0)),"再投填正份额、金额0、费用0",IF(AND(OR(B83="现金分红",B83="红利再投"),K82<=0),"分红或再投前须有持仓",IF(AND(OR(OR(B83="买入",B83="定投",B83="转换转入"),B83="卖出"),OR(D83<=0,E83<=0)),"买卖须填正份额、正金额",IF(AND(B83="卖出",D83>K82+0.000001),"卖出份额超过持仓",IF(AND(OR(B83="买入",B83="定投",B83="转换转入"),F83>=E83),"申购费不能达到总支出",IF(NOT(ISNUMBER(持仓总览!$H$6)),"请填写金额核对容差",IF(持仓总览!$H$6<0,"金额核对容差不能为负",IF(NOT(OR(持仓总览!$C$7="利润优先",持仓总览!$C$7="本金优先")),"请选择卖出分配模式",IF(AND(OR(B83="买入",B83="定投",B83="转换转入"),ABS(E83-F83-C83*D83)>持仓总览!$H$6),"买入金额与份额净值不符",IF(AND(B83="卖出",ABS(E83+F83-C83*D83)>持仓总览!$H$6),"到账加费用与赎回市值不符","已计入")))))))))))))))))))))))))) -> 已计入 | J83: =IF(AA83="正常",IF(I83="已计入",IF(OR(OR(B83="买入",B83="定投",B83="转换转入"),B83="红利再投"),D83,IF(B83="卖出",-D83,0)),0),"") -> 14.3 | K83: =IF(AA83="正常",ROUND(K82+J83,6),"") -> 19356.13 | L83: =IF(I83="已计入",ROUND(K82*C83,2),"") -> 67514.59 | M83: =IF(I83="已计入",IF(B83="卖出",MAX(0,L83-Q82-F83),IF(B83="现金分红",MAX(0,L83+E83-Q82),0)),"") -> 0 | N83: =IF(I83="已计入",IF(AND(B83="卖出",持仓总览!$C$7="本金优先"),MAX(0,E83-Q82),IF(OR(B83="卖出",B83="现金分红"),MIN(E83,M83),0)),"") -> 0 | O83: =IF(I83="已计入",IF(OR(B83="卖出",B83="现金分红"),MIN(Q82,MAX(0,E83-N83)),0),"") -> 0 | P83: =IF(I83="已计入",IF(AND(B83="卖出",K83=0),MAX(0,Q82-O83),0),"") -> 0 | Q83: =IF(AA83="正常",IF(I83="已计入",ROUND(Q82+IF(OR(B83="买入",B83="定投",B83="转换转入"),E83,0)-O83-P83,2),Q82),"") -> 40256.01 | R83: =IF(I83="已计入",ROUND(K83*C83,2),"") -> 67564.51 | S83: =IF(I83="已计入",ROUND(R83-Q83,2),"") -> 27308.5 | T83: =IF(I83="已计入",IF(Q83=0,"",S83/Q83),"") -> 0.67837076 | U83: =IF(AA83="正常",U82+IF(AND(I83="已计入",OR(B83="买入",B83="定投",B83="转换转入")),E83,0),"") -> 40256.01 | V83: =IF(AA83="正常",V82+IF(AND(I83="已计入",OR(B83="卖出",B83="现金分红")),E83,0),"") -> 0 | W83: =IF(AA83="正常",W82+IF(I83="已计入",N83,0),"") -> 0 | X83: =IF(AA83="正常",X82+IF(I83="已计入",P83,0),"") -> 0 | Y83: =IF(I83="已计入",ROUND(R83+V83-U83,2),"") -> 27308.5 | Z83: =IF(AA83="正常",IF(I83="已计入",A83,Z82),"") -> 46181 | AA83: =IF(OR(AA82="错误",AND(I83<>"",I83<>"已排除",I83<>"待确认",I83<>"已计入")),"错误","正常") -> 正常 | AB83: =IF(AA83="正常",IF(I83="已计入",C83,AB82),"") -> 3.4906
A84: 46182 | B84: 定投 | C84: 3.5462 | D84: 14.08 | E84: 50 | F84: 0.08 | G84: 历史估算 | H84: 原下单 2026-06-09T12:05:41 份额、费用及净值日沿用旧表估算 | I84: =IF(COUNTA(A84:H84)=0,"",IF(OR(OR(OR(G84="撤单",G84="交易失败",G84="交易关闭"),G84="交易失败",G84="交易关闭"),G84="交易失败",G84="交易关闭"),"已排除",IF(G84="待确认","待确认",IF(NOT(OR(G84="已确认",G84="历史估算")),"请选择确认状态",IF(NOT(ISNUMBER(A84)),"缺少有效净值日期",IF(OR(A84<=0,A84<>INT(A84)),"净值日期无效",IF(NOT(OR(OR(B84="买入",B84="定投",B84="转换转入"),B84="卖出",B84="现金分红",B84="红利再投")),"请选择交易类型",IF(NOT(ISNUMBER(C84)),"缺少成交净值",IF(C84<=0,"成交净值须大于零",IF(NOT(ISNUMBER(D84)),"缺少确认份额（分红填0）",IF(NOT(ISNUMBER(E84)),"缺少确认金额（再投填0）",IF(NOT(ISNUMBER(F84)),"缺少手续费（无费用填0）",IF(OR(D84<0,E84<0,F84<0),"份额金额费用不能为负",IF(AA83="错误","前行待修正",IF(A84<Z83,"日期需按成交顺序递增",IF(AND(B84="现金分红",OR(D84<>0,E84<=0,F84<>0)),"分红填份额0、费用0、正金额",IF(AND(B84="红利再投",OR(D84<=0,E84<>0,F84<>0)),"再投填正份额、金额0、费用0",IF(AND(OR(B84="现金分红",B84="红利再投"),K83<=0),"分红或再投前须有持仓",IF(AND(OR(OR(B84="买入",B84="定投",B84="转换转入"),B84="卖出"),OR(D84<=0,E84<=0)),"买卖须填正份额、正金额",IF(AND(B84="卖出",D84>K83+0.000001),"卖出份额超过持仓",IF(AND(OR(B84="买入",B84="定投",B84="转换转入"),F84>=E84),"申购费不能达到总支出",IF(NOT(ISNUMBER(持仓总览!$H$6)),"请填写金额核对容差",IF(持仓总览!$H$6<0,"金额核对容差不能为负",IF(NOT(OR(持仓总览!$C$7="利润优先",持仓总览!$C$7="本金优先")),"请选择卖出分配模式",IF(AND(OR(B84="买入",B84="定投",B84="转换转入"),ABS(E84-F84-C84*D84)>持仓总览!$H$6),"买入金额与份额净值不符",IF(AND(B84="卖出",ABS(E84+F84-C84*D84)>持仓总览!$H$6),"到账加费用与赎回市值不符","已计入")))))))))))))))))))))))))) -> 已计入 | J84: =IF(AA84="正常",IF(I84="已计入",IF(OR(OR(B84="买入",B84="定投",B84="转换转入"),B84="红利再投"),D84,IF(B84="卖出",-D84,0)),0),"") -> 14.08 | K84: =IF(AA84="正常",ROUND(K83+J84,6),"") -> 19370.21 | L84: =IF(I84="已计入",ROUND(K83*C84,2),"") -> 68640.71 | M84: =IF(I84="已计入",IF(B84="卖出",MAX(0,L84-Q83-F84),IF(B84="现金分红",MAX(0,L84+E84-Q83),0)),"") -> 0 | N84: =IF(I84="已计入",IF(AND(B84="卖出",持仓总览!$C$7="本金优先"),MAX(0,E84-Q83),IF(OR(B84="卖出",B84="现金分红"),MIN(E84,M84),0)),"") -> 0 | O84: =IF(I84="已计入",IF(OR(B84="卖出",B84="现金分红"),MIN(Q83,MAX(0,E84-N84)),0),"") -> 0 | P84: =IF(I84="已计入",IF(AND(B84="卖出",K84=0),MAX(0,Q83-O84),0),"") -> 0 | Q84: =IF(AA84="正常",IF(I84="已计入",ROUND(Q83+IF(OR(B84="买入",B84="定投",B84="转换转入"),E84,0)-O84-P84,2),Q83),"") -> 40306.01 | R84: =IF(I84="已计入",ROUND(K84*C84,2),"") -> 68690.64 | S84: =IF(I84="已计入",ROUND(R84-Q84,2),"") -> 28384.63 | T84: =IF(I84="已计入",IF(Q84=0,"",S84/Q84),"") -> 0.70422823 | U84: =IF(AA84="正常",U83+IF(AND(I84="已计入",OR(B84="买入",B84="定投",B84="转换转入")),E84,0),"") -> 40306.01 | V84: =IF(AA84="正常",V83+IF(AND(I84="已计入",OR(B84="卖出",B84="现金分红")),E84,0),"") -> 0 | W84: =IF(AA84="正常",W83+IF(I84="已计入",N84,0),"") -> 0 | X84: =IF(AA84="正常",X83+IF(I84="已计入",P84,0),"") -> 0 | Y84: =IF(I84="已计入",ROUND(R84+V84-U84,2),"") -> 28384.63 | Z84: =IF(AA84="正常",IF(I84="已计入",A84,Z83),"") -> 46182 | AA84: =IF(OR(AA83="错误",AND(I84<>"",I84<>"已排除",I84<>"待确认",I84<>"已计入")),"错误","正常") -> 正常 | AB84: =IF(AA84="正常",IF(I84="已计入",C84,AB83),"") -> 3.5462
A85: 46183 | B85: 定投 | C85: 3.4274 | D85: 14.56 | E85: 50 | F85: 0.08 | G85: 历史估算 | H85: 原下单 2026-06-10T12:03:23 份额、费用及净值日沿用旧表估算 | I85: =IF(COUNTA(A85:H85)=0,"",IF(OR(OR(OR(G85="撤单",G85="交易失败",G85="交易关闭"),G85="交易失败",G85="交易关闭"),G85="交易失败",G85="交易关闭"),"已排除",IF(G85="待确认","待确认",IF(NOT(OR(G85="已确认",G85="历史估算")),"请选择确认状态",IF(NOT(ISNUMBER(A85)),"缺少有效净值日期",IF(OR(A85<=0,A85<>INT(A85)),"净值日期无效",IF(NOT(OR(OR(B85="买入",B85="定投",B85="转换转入"),B85="卖出",B85="现金分红",B85="红利再投")),"请选择交易类型",IF(NOT(ISNUMBER(C85)),"缺少成交净值",IF(C85<=0,"成交净值须大于零",IF(NOT(ISNUMBER(D85)),"缺少确认份额（分红填0）",IF(NOT(ISNUMBER(E85)),"缺少确认金额（再投填0）",IF(NOT(ISNUMBER(F85)),"缺少手续费（无费用填0）",IF(OR(D85<0,E85<0,F85<0),"份额金额费用不能为负",IF(AA84="错误","前行待修正",IF(A85<Z84,"日期需按成交顺序递增",IF(AND(B85="现金分红",OR(D85<>0,E85<=0,F85<>0)),"分红填份额0、费用0、正金额",IF(AND(B85="红利再投",OR(D85<=0,E85<>0,F85<>0)),"再投填正份额、金额0、费用0",IF(AND(OR(B85="现金分红",B85="红利再投"),K84<=0),"分红或再投前须有持仓",IF(AND(OR(OR(B85="买入",B85="定投",B85="转换转入"),B85="卖出"),OR(D85<=0,E85<=0)),"买卖须填正份额、正金额",IF(AND(B85="卖出",D85>K84+0.000001),"卖出份额超过持仓",IF(AND(OR(B85="买入",B85="定投",B85="转换转入"),F85>=E85),"申购费不能达到总支出",IF(NOT(ISNUMBER(持仓总览!$H$6)),"请填写金额核对容差",IF(持仓总览!$H$6<0,"金额核对容差不能为负",IF(NOT(OR(持仓总览!$C$7="利润优先",持仓总览!$C$7="本金优先")),"请选择卖出分配模式",IF(AND(OR(B85="买入",B85="定投",B85="转换转入"),ABS(E85-F85-C85*D85)>持仓总览!$H$6),"买入金额与份额净值不符",IF(AND(B85="卖出",ABS(E85+F85-C85*D85)>持仓总览!$H$6),"到账加费用与赎回市值不符","已计入")))))))))))))))))))))))))) -> 已计入 | J85: =IF(AA85="正常",IF(I85="已计入",IF(OR(OR(B85="买入",B85="定投",B85="转换转入"),B85="红利再投"),D85,IF(B85="卖出",-D85,0)),0),"") -> 14.56 | K85: =IF(AA85="正常",ROUND(K84+J85,6),"") -> 19384.77 | L85: =IF(I85="已计入",ROUND(K84*C85,2),"") -> 66389.46 | M85: =IF(I85="已计入",IF(B85="卖出",MAX(0,L85-Q84-F85),IF(B85="现金分红",MAX(0,L85+E85-Q84),0)),"") -> 0 | N85: =IF(I85="已计入",IF(AND(B85="卖出",持仓总览!$C$7="本金优先"),MAX(0,E85-Q84),IF(OR(B85="卖出",B85="现金分红"),MIN(E85,M85),0)),"") -> 0 | O85: =IF(I85="已计入",IF(OR(B85="卖出",B85="现金分红"),MIN(Q84,MAX(0,E85-N85)),0),"") -> 0 | P85: =IF(I85="已计入",IF(AND(B85="卖出",K85=0),MAX(0,Q84-O85),0),"") -> 0 | Q85: =IF(AA85="正常",IF(I85="已计入",ROUND(Q84+IF(OR(B85="买入",B85="定投",B85="转换转入"),E85,0)-O85-P85,2),Q84),"") -> 40356.01 | R85: =IF(I85="已计入",ROUND(K85*C85,2),"") -> 66439.36 | S85: =IF(I85="已计入",ROUND(R85-Q85,2),"") -> 26083.35 | T85: =IF(I85="已计入",IF(Q85=0,"",S85/Q85),"") -> 0.64633124 | U85: =IF(AA85="正常",U84+IF(AND(I85="已计入",OR(B85="买入",B85="定投",B85="转换转入")),E85,0),"") -> 40356.01 | V85: =IF(AA85="正常",V84+IF(AND(I85="已计入",OR(B85="卖出",B85="现金分红")),E85,0),"") -> 0 | W85: =IF(AA85="正常",W84+IF(I85="已计入",N85,0),"") -> 0 | X85: =IF(AA85="正常",X84+IF(I85="已计入",P85,0),"") -> 0 | Y85: =IF(I85="已计入",ROUND(R85+V85-U85,2),"") -> 26083.35 | Z85: =IF(AA85="正常",IF(I85="已计入",A85,Z84),"") -> 46183 | AA85: =IF(OR(AA84="错误",AND(I85<>"",I85<>"已排除",I85<>"待确认",I85<>"已计入")),"错误","正常") -> 正常 | AB85: =IF(AA85="正常",IF(I85="已计入",C85,AB84),"") -> 3.4274
A86: 46184 | B86: 定投 | C86: 3.5625 | D86: 28.03 | E86: 100 | F86: 0.15 | G86: 历史估算 | H86: 原下单 2026-06-11T12:18:01 份额、费用及净值日沿用旧表估算 | I86: =IF(COUNTA(A86:H86)=0,"",IF(OR(OR(OR(G86="撤单",G86="交易失败",G86="交易关闭"),G86="交易失败",G86="交易关闭"),G86="交易失败",G86="交易关闭"),"已排除",IF(G86="待确认","待确认",IF(NOT(OR(G86="已确认",G86="历史估算")),"请选择确认状态",IF(NOT(ISNUMBER(A86)),"缺少有效净值日期",IF(OR(A86<=0,A86<>INT(A86)),"净值日期无效",IF(NOT(OR(OR(B86="买入",B86="定投",B86="转换转入"),B86="卖出",B86="现金分红",B86="红利再投")),"请选择交易类型",IF(NOT(ISNUMBER(C86)),"缺少成交净值",IF(C86<=0,"成交净值须大于零",IF(NOT(ISNUMBER(D86)),"缺少确认份额（分红填0）",IF(NOT(ISNUMBER(E86)),"缺少确认金额（再投填0）",IF(NOT(ISNUMBER(F86)),"缺少手续费（无费用填0）",IF(OR(D86<0,E86<0,F86<0),"份额金额费用不能为负",IF(AA85="错误","前行待修正",IF(A86<Z85,"日期需按成交顺序递增",IF(AND(B86="现金分红",OR(D86<>0,E86<=0,F86<>0)),"分红填份额0、费用0、正金额",IF(AND(B86="红利再投",OR(D86<=0,E86<>0,F86<>0)),"再投填正份额、金额0、费用0",IF(AND(OR(B86="现金分红",B86="红利再投"),K85<=0),"分红或再投前须有持仓",IF(AND(OR(OR(B86="买入",B86="定投",B86="转换转入"),B86="卖出"),OR(D86<=0,E86<=0)),"买卖须填正份额、正金额",IF(AND(B86="卖出",D86>K85+0.000001),"卖出份额超过持仓",IF(AND(OR(B86="买入",B86="定投",B86="转换转入"),F86>=E86),"申购费不能达到总支出",IF(NOT(ISNUMBER(持仓总览!$H$6)),"请填写金额核对容差",IF(持仓总览!$H$6<0,"金额核对容差不能为负",IF(NOT(OR(持仓总览!$C$7="利润优先",持仓总览!$C$7="本金优先")),"请选择卖出分配模式",IF(AND(OR(B86="买入",B86="定投",B86="转换转入"),ABS(E86-F86-C86*D86)>持仓总览!$H$6),"买入金额与份额净值不符",IF(AND(B86="卖出",ABS(E86+F86-C86*D86)>持仓总览!$H$6),"到账加费用与赎回市值不符","已计入")))))))))))))))))))))))))) -> 已计入 | J86: =IF(AA86="正常",IF(I86="已计入",IF(OR(OR(B86="买入",B86="定投",B86="转换转入"),B86="红利再投"),D86,IF(B86="卖出",-D86,0)),0),"") -> 28.03 | K86: =IF(AA86="正常",ROUND(K85+J86,6),"") -> 19412.8 | L86: =IF(I86="已计入",ROUND(K85*C86,2),"") -> 69058.24 | M86: =IF(I86="已计入",IF(B86="卖出",MAX(0,L86-Q85-F86),IF(B86="现金分红",MAX(0,L86+E86-Q85),0)),"") -> 0 | N86: =IF(I86="已计入",IF(AND(B86="卖出",持仓总览!$C$7="本金优先"),MAX(0,E86-Q85),IF(OR(B86="卖出",B86="现金分红"),MIN(E86,M86),0)),"") -> 0 | O86: =IF(I86="已计入",IF(OR(B86="卖出",B86="现金分红"),MIN(Q85,MAX(0,E86-N86)),0),"") -> 0 | P86: =IF(I86="已计入",IF(AND(B86="卖出",K86=0),MAX(0,Q85-O86),0),"") -> 0 | Q86: =IF(AA86="正常",IF(I86="已计入",ROUND(Q85+IF(OR(B86="买入",B86="定投",B86="转换转入"),E86,0)-O86-P86,2),Q85),"") -> 40456.01 | R86: =IF(I86="已计入",ROUND(K86*C86,2),"") -> 69158.1 | S86: =IF(I86="已计入",ROUND(R86-Q86,2),"") -> 28702.09 | T86: =IF(I86="已计入",IF(Q86=0,"",S86/Q86),"") -> 0.70946418 | U86: =IF(AA86="正常",U85+IF(AND(I86="已计入",OR(B86="买入",B86="定投",B86="转换转入")),E86,0),"") -> 40456.01 | V86: =IF(AA86="正常",V85+IF(AND(I86="已计入",OR(B86="卖出",B86="现金分红")),E86,0),"") -> 0 | W86: =IF(AA86="正常",W85+IF(I86="已计入",N86,0),"") -> 0 | X86: =IF(AA86="正常",X85+IF(I86="已计入",P86,0),"") -> 0 | Y86: =IF(I86="已计入",ROUND(R86+V86-U86,2),"") -> 28702.09 | Z86: =IF(AA86="正常",IF(I86="已计入",A86,Z85),"") -> 46184 | AA86: =IF(OR(AA85="错误",AND(I86<>"",I86<>"已排除",I86<>"待确认",I86<>"已计入")),"错误","正常") -> 正常 | AB86: =IF(AA86="正常",IF(I86="已计入",C86,AB85),"") -> 3.5625
A87: 46185 | B87: 定投 | C87: 3.5728 | D87: 27.95 | E87: 100 | F87: 0.15 | G87: 历史估算 | H87: 原下单 2026-06-12T12:04:41 份额、费用及净值日沿用旧表估算 | I87: =IF(COUNTA(A87:H87)=0,"",IF(OR(OR(OR(G87="撤单",G87="交易失败",G87="交易关闭"),G87="交易失败",G87="交易关闭"),G87="交易失败",G87="交易关闭"),"已排除",IF(G87="待确认","待确认",IF(NOT(OR(G87="已确认",G87="历史估算")),"请选择确认状态",IF(NOT(ISNUMBER(A87)),"缺少有效净值日期",IF(OR(A87<=0,A87<>INT(A87)),"净值日期无效",IF(NOT(OR(OR(B87="买入",B87="定投",B87="转换转入"),B87="卖出",B87="现金分红",B87="红利再投")),"请选择交易类型",IF(NOT(ISNUMBER(C87)),"缺少成交净值",IF(C87<=0,"成交净值须大于零",IF(NOT(ISNUMBER(D87)),"缺少确认份额（分红填0）",IF(NOT(ISNUMBER(E87)),"缺少确认金额（再投填0）",IF(NOT(ISNUMBER(F87)),"缺少手续费（无费用填0）",IF(OR(D87<0,E87<0,F87<0),"份额金额费用不能为负",IF(AA86="错误","前行待修正",IF(A87<Z86,"日期需按成交顺序递增",IF(AND(B87="现金分红",OR(D87<>0,E87<=0,F87<>0)),"分红填份额0、费用0、正金额",IF(AND(B87="红利再投",OR(D87<=0,E87<>0,F87<>0)),"再投填正份额、金额0、费用0",IF(AND(OR(B87="现金分红",B87="红利再投"),K86<=0),"分红或再投前须有持仓",IF(AND(OR(OR(B87="买入",B87="定投",B87="转换转入"),B87="卖出"),OR(D87<=0,E87<=0)),"买卖须填正份额、正金额",IF(AND(B87="卖出",D87>K86+0.000001),"卖出份额超过持仓",IF(AND(OR(B87="买入",B87="定投",B87="转换转入"),F87>=E87),"申购费不能达到总支出",IF(NOT(ISNUMBER(持仓总览!$H$6)),"请填写金额核对容差",IF(持仓总览!$H$6<0,"金额核对容差不能为负",IF(NOT(OR(持仓总览!$C$7="利润优先",持仓总览!$C$7="本金优先")),"请选择卖出分配模式",IF(AND(OR(B87="买入",B87="定投",B87="转换转入"),ABS(E87-F87-C87*D87)>持仓总览!$H$6),"买入金额与份额净值不符",IF(AND(B87="卖出",ABS(E87+F87-C87*D87)>持仓总览!$H$6),"到账加费用与赎回市值不符","已计入")))))))))))))))))))))))))) -> 已计入 | J87: =IF(AA87="正常",IF(I87="已计入",IF(OR(OR(B87="买入",B87="定投",B87="转换转入"),B87="红利再投"),D87,IF(B87="卖出",-D87,0)),0),"") -> 27.95 | K87: =IF(AA87="正常",ROUND(K86+J87,6),"") -> 19440.75 | L87: =IF(I87="已计入",ROUND(K86*C87,2),"") -> 69358.05 | M87: =IF(I87="已计入",IF(B87="卖出",MAX(0,L87-Q86-F87),IF(B87="现金分红",MAX(0,L87+E87-Q86),0)),"") -> 0 | N87: =IF(I87="已计入",IF(AND(B87="卖出",持仓总览!$C$7="本金优先"),MAX(0,E87-Q86),IF(OR(B87="卖出",B87="现金分红"),MIN(E87,M87),0)),"") -> 0 | O87: =IF(I87="已计入",IF(OR(B87="卖出",B87="现金分红"),MIN(Q86,MAX(0,E87-N87)),0),"") -> 0 | P87: =IF(I87="已计入",IF(AND(B87="卖出",K87=0),MAX(0,Q86-O87),0),"") -> 0 | Q87: =IF(AA87="正常",IF(I87="已计入",ROUND(Q86+IF(OR(B87="买入",B87="定投",B87="转换转入"),E87,0)-O87-P87,2),Q86),"") -> 40556.01 | R87: =IF(I87="已计入",ROUND(K87*C87,2),"") -> 69457.91 | S87: =IF(I87="已计入",ROUND(R87-Q87,2),"") -> 28901.9 | T87: =IF(I87="已计入",IF(Q87=0,"",S87/Q87),"") -> 0.7126416 | U87: =IF(AA87="正常",U86+IF(AND(I87="已计入",OR(B87="买入",B87="定投",B87="转换转入")),E87,0),"") -> 40556.01 | V87: =IF(AA87="正常",V86+IF(AND(I87="已计入",OR(B87="卖出",B87="现金分红")),E87,0),"") -> 0 | W87: =IF(AA87="正常",W86+IF(I87="已计入",N87,0),"") -> 0 | X87: =IF(AA87="正常",X86+IF(I87="已计入",P87,0),"") -> 0 | Y87: =IF(I87="已计入",ROUND(R87+V87-U87,2),"") -> 28901.9 | Z87: =IF(AA87="正常",IF(I87="已计入",A87,Z86),"") -> 46185 | AA87: =IF(OR(AA86="错误",AND(I87<>"",I87<>"已排除",I87<>"待确认",I87<>"已计入")),"错误","正常") -> 正常 | AB87: =IF(AA87="正常",IF(I87="已计入",C87,AB86),"") -> 3.5728
... A91: 46212 | B91: 定投 | C91: 3.5558 | D91: 280.81 | E91: 1000 | F91: 1.5 | G91: 历史估算 | H91: 原下单 2026-07-09T12:30:04 份额、费用及净值日沿用旧表估算 | I91: =IF(COUNTA(A91:H91)=0,"",IF(OR(OR(OR(G91="撤单",G91="交易失败",G91="交易关闭"),G91="交易失败",G91="交易关闭"),G91="交易失败",G91="交易关闭"),"已排除",IF(G91="待确认","待确认",IF(NOT(OR(G91="已确认",G91="历史估算")),"请选择确认状态",IF(NOT(ISNUMBER(A91)),"缺少有效净值日期",IF(OR(A91<=0,A91<>INT(A91)),"净值日期无效",IF(NOT(OR(OR(B91="买入",B91="定投",B91="转换转入"),B91="卖出",B91="现金分红",B91="红利再投")),"请选择交易类型",IF(NOT(ISNUMBER(C91)),"缺少成交净值",IF(C91<=0,"成交净值须大于零",IF(NOT(ISNUMBER(D91)),"缺少确认份额（分红填0）",IF(NOT(ISNUMBER(E91)),"缺少确认金额（再投填0）",IF(NOT(ISNUMBER(F91)),"缺少手续费（无费用填0）",IF(OR(D91<0,E91<0,F91<0),"份额金额费用不能为负",IF(AA90="错误","前行待修正",IF(A91<Z90,"日期需按成交顺序递增",IF(AND(B91="现金分红",OR(D91<>0,E91<=0,F91<>0)),"分红填份额0、费用0、正金额",IF(AND(B91="红利再投",OR(D91<=0,E91<>0,F91<>0)),"再投填正份额、金额0、费用0",IF(AND(OR(B91="现金分红",B91="红利再投"),K90<=0),"分红或再投前须有持仓",IF(AND(OR(OR(B91="买入",B91="定投",B91="转换转入"),B91="卖出"),OR(D91<=0,E91<=0)),"买卖须填正份额、正金额",IF(AND(B91="卖出",D91>K90+0.000001),"卖出份额超过持仓",IF(AND(OR(B91="买入",B91="定投",B91="转换转入"),F91>=E91),"申购费不能达到总支出",IF(NOT(ISNUMBER(持仓总览!$H$6)),"请填写金额核对容差",IF(持仓总览!$H$6<0,"金额核对容差不能为负",IF(NOT(OR(持仓总览!$C$7="利润优先",持仓总览!$C$7="本金优先")),"请选择卖出分配模式",IF(AND(OR(B91="买入",B91="定投",B91="转换转入"),ABS(E91-F91-C91*D91)>持仓总览!$H$6),"买入金额与份额净值不符",IF(AND(B91="卖出",ABS(E91+F91-C91*D91)>持仓总览!$H$6),"到账加费用与赎回市值不符","已计入")))))))))))))))))))))))))) -> 已计入 | J91: =IF(AA91="正常",IF(I91="已计入",IF(OR(OR(B91="买入",B91="定投",B91="转换转入"),B91="红利再投"),D91,IF(B91="卖出",-D91,0)),0),"") -> 280.81 | K91: =IF(AA91="正常",ROUND(K90+J91,6),"") -> 20602.18 | L91: =IF(I91="已计入",ROUND(K90*C91,2),"") -> 72258.73 | M91: =IF(I91="已计入",IF(B91="卖出",MAX(0,L91-Q90-F91),IF(B91="现金分红",MAX(0,L91+E91-Q90),0)),"") -> 0 | N91: =IF(I91="已计入",IF(AND(B91="卖出",持仓总览!$C$7="本金优先"),MAX(0,E91-Q90),IF(OR(B91="卖出",B91="现金分红"),MIN(E91,M91),0)),"") -> 0 | O91: =IF(I91="已计入",IF(OR(B91="卖出",B91="现金分红"),MIN(Q90,MAX(0,E91-N91)),0),"") -> 0 | P91: =IF(I91="已计入",IF(AND(B91="卖出",K91=0),MAX(0,Q90-O91),0),"") -> 0 | Q91: =IF(AA91="正常",IF(I91="已计入",ROUND(Q90+IF(OR(B91="买入",B91="定投",B91="转换转入"),E91,0)-O91-P91,2),Q90),"") -> 44556.01 | R91: =IF(I91="已计入",ROUND(K91*C91,2),"") -> 73257.23 | S91: =IF(I91="已计入",ROUND(R91-Q91,2),"") -> 28701.22 | T91: =IF(I91="已计入",IF(Q91=0,"",S91/Q91),"") -> 0.64416046 | U91: =IF(AA91="正常",U90+IF(AND(I91="已计入",OR(B91="买入",B91="定投",B91="转换转入")),E91,0),"") -> 44556.01 | V91: =IF(AA91="正常",V90+IF(AND(I91="已计入",OR(B91="卖出",B91="现金分红")),E91,0),"") -> 0 | W91: =IF(AA91="正常",W90+IF(I91="已计入",N91,0),"") -> 0 | X91: =IF(AA91="正常",X90+IF(I91="已计入",P91,0),"") -> 0 | Y91: =IF(I91="已计入",ROUND(R91+V91-U91,2),"") -> 28701.22 | Z91: =IF(AA91="正常",IF(I91="已计入",A91,Z90),"") -> 46212 | AA91: =IF(OR(AA90="错误",AND(I91<>"",I91<>"已排除",I91<>"待确认",I91<>"已计入")),"错误","正常") -> 正常 | AB91: =IF(AA91="正常",IF(I91="已计入",C91,AB90),"") -> 3.5558
A92: 46213 | B92: 买入 | C92: 3.3943 | D92: 294.17 | E92: 1000 | F92: 1.5 | G92: 历史估算 | H92: 原下单 2026-07-10T14:28:45 份额、费用及净值日沿用旧表估算 | I92: =IF(COUNTA(A92:H92)=0,"",IF(OR(OR(OR(G92="撤单",G92="交易失败",G92="交易关闭"),G92="交易失败",G92="交易关闭"),G92="交易失败",G92="交易关闭"),"已排除",IF(G92="待确认","待确认",IF(NOT(OR(G92="已确认",G92="历史估算")),"请选择确认状态",IF(NOT(ISNUMBER(A92)),"缺少有效净值日期",IF(OR(A92<=0,A92<>INT(A92)),"净值日期无效",IF(NOT(OR(OR(B92="买入",B92="定投",B92="转换转入"),B92="卖出",B92="现金分红",B92="红利再投")),"请选择���易类型",IF(NOT(ISNUMBER(C92)),"缺少成交净值",IF(C92<=0,"成交净值须大于零",IF(NOT(ISNUMBER(D92)),"缺少确认份额（分红填0）",IF(NOT(ISNUMBER(E92)),"缺少确认金额（再投填0）",IF(NOT(ISNUMBER(F92)),"缺少手续费（无费用填0）",IF(OR(D92<0,E92<0,F92<0),"份额金额费用不能为负",IF(AA91="错误","前行待修正",IF(A92<Z91,"日期需按成交顺序递增",IF(AND(B92="现金分红",OR(D92<>0,E92<=0,F92<>0)),"分红填份额0、费用0、正金额",IF(AND(B92="红利再投",OR(D92<=0,E92<>0,F92<>0)),"再投填正份额、金额0、费用0",IF(AND(OR(B92="现金分红",B92="红利再投"),K91<=0),"分红或再投前须有持仓",IF(AND(OR(OR(B92="买入",B92="定投",B92="转换转入"),B92="卖出"),OR(D92<=0,E92<=0)),"买卖须填正份额、正金额",IF(AND(B92="卖出",D92>K91+0.000001),"卖出份额超过持仓",IF(AND(OR(B92="买入",B92="定投",B92="转换转入"),F92>=E92),"申购费不能达到总支出",IF(NOT(ISNUMBER(持仓总览!$H$6)),"请填写金额核对容差",IF(持仓总览!$H$6<0,"金额核对容差不能为负",IF(NOT(OR(持仓总览!$C$7="利润优先",持仓总览!$C$7="本金优先")),"请选择卖出分配模式",IF(AND(OR(B92="买入",B92="定投",B92="转换转入"),ABS(E92-F92-C92*D92)>持仓总览!$H$6),"买入金额与份额净值不符",IF(AND(B92="卖出",ABS(E92+F92-C92*D92)>持仓总览!$H$6),"到账加费用与赎回市值不符","已计入")))))))))))))))))))))))))) -> 已计入 | J92: =IF(AA92="正常",IF(I92="已计入",IF(OR(OR(B92="买入",B92="定投",B92="转换转入"),B92="红利再投"),D92,IF(B92="卖出",-D92,0)),0),"") -> 294.17 | K92: =IF(AA92="正常",ROUND(K91+J92,6),"") -> 20896.35 | L92: =IF(I92="已计入",ROUND(K91*C92,2),"") -> 69929.98 | M92: =IF(I92="已计入",IF(B92="卖出",MAX(0,L92-Q91-F92),IF(B92="现金分红",MAX(0,L92+E92-Q91),0)),"") -> 0 | N92: =IF(I92="已计入",IF(AND(B92="卖出",持仓总览!$C$7="本金优先"),MAX(0,E92-Q91),IF(OR(B92="卖出",B92="现金分红"),MIN(E92,M92),0)),"") -> 0 | O92: =IF(I92="已计入",IF(OR(B92="卖出",B92="现金分红"),MIN(Q91,MAX(0,E92-N92)),0),"") -> 0 | P92: =IF(I92="已计入",IF(AND(B92="卖出",K92=0),MAX(0,Q91-O92),0),"") -> 0 | Q92: =IF(AA92="正常",IF(I92="已计入",ROUND(Q91+IF(OR(B92="买入",B92="定投",B92="转换转入"),E92,0)-O92-P92,2),Q91),"") -> 45556.01 | R92: =IF(I92="已计入",ROUND(K92*C92,2),"") -> 70928.48 | S92: =IF(I92="已计入",ROUND(R92-Q92,2),"") -> 25372.47 | T92: =IF(I92="已计入",IF(Q92=0,"",S92/Q92),"") -> 0.5569511 | U92: =IF(AA92="正常",U91+IF(AND(I92="已计入",OR(B92="买入",B92="定投",B92="转换转入")),E92,0),"") -> 45556.01 | V92: =IF(AA92="正常",V91+IF(AND(I92="已计入",OR(B92="卖出",B92="现金分红")),E92,0),"") -> 0 | W92: =IF(AA92="正常",W91+IF(I92="已计入",N92,0),"") -> 0 | X92: =IF(AA92="正常",X91+IF(I92="已计入",P92,0),"") -> 0 | Y92: =IF(I92="已计入",ROUND(R92+V92-U92,2),"") -> 25372.47 | Z92: =IF(AA92="正常",IF(I92="已计入",A92,Z91),"") -> 46213 | AA92: =IF(OR(AA91="错误",AND(I92<>"",I92<>"已排除",I92<>"待确认",I92<>"已计入")),"错误","正常") -> 正常 | AB92: =IF(AA92="正常",IF(I92="已计入",C92,AB91),"") -> 3.3943
A93: 46216 | B93: 定投 | C93: 3.1753 | D93: 314.46 | E93: 1000 | F93: 1.5 | G93: 历史估算 | H93: 原下单 2026-07-13T12:38:35 份额、费用及净值日沿用旧表估算 | I93: =IF(COUNTA(A93:H93)=0,"",IF(OR(OR(OR(G93="撤单",G93="交易失败",G93="交易关闭"),G93="交易失败",G93="交易关闭"),G93="交易失败",G93="交易关闭"),"已排除",IF(G93="待确认","待确认",IF(NOT(OR(G93="已确认",G93="历史估算")),"请选择确认状态",IF(NOT(ISNUMBER(A93)),"缺少有效净值日期",IF(OR(A93<=0,A93<>INT(A93)),"净值日期无效",IF(NOT(OR(OR(B93="买入",B93="定投",B93="转换转入"),B93="卖出",B93="现金分红",B93="红利再投")),"请选择交易类型",IF(NOT(ISNUMBER(C93)),"缺少成交净值",IF(C93<=0,"成交净值须大于零",IF(NOT(ISNUMBER(D93)),"缺少确认份额（分红填0）",IF(NOT(ISNUMBER(E93)),"缺少确认金额（再投填0）",IF(NOT(ISNUMBER(F93)),"缺少手续费（无费用填0）",IF(OR(D93<0,E93<0,F93<0),"份额金额费用不能为负",IF(AA92="错误","前行待修正",IF(A93<Z92,"日期需按成交顺序递增",IF(AND(B93="现金分红",OR(D93<>0,E93<=0,F93<>0)),"分红填份额0、费用0、正金额",IF(AND(B93="红利再投",OR(D93<=0,E93<>0,F93<>0)),"再投填正份额、金额0、费用0",IF(AND(OR(B93="现金分红",B93="红利再投"),K92<=0),"分红或再投前须有持仓",IF(AND(OR(OR(B93="买入",B93="定投",B93="转换转入"),B93="卖出"),OR(D93<=0,E93<=0)),"买卖须填正份额、正金额",IF(AND(B93="卖出",D93>K92+0.000001),"卖出份额超过持仓",IF(AND(OR(B93="买入",B93="定投",B93="转换转入"),F93>=E93),"申购费不能达到总支出",IF(NOT(ISNUMBER(持仓总览!$H$6)),"请填写金额核对容差",IF(持仓总览!$H$6<0,"金额核对容差不能为负",IF(NOT(OR(持仓总览!$C$7="利润优先",持仓总览!$C$7="本金优先")),"请选择卖出分配模式",IF(AND(OR(B93="买入",B93="定投",B93="转换转入"),ABS(E93-F93-C93*D93)>持仓总览!$H$6),"买入金额与份额净值不符",IF(AND(B93="卖出",ABS(E93+F93-C93*D93)>持仓总览!$H$6),"到账加费用与赎回市值不符","已计入")))))))))))))))))))))))))) -> 已计入 | J93: =IF(AA93="正常",IF(I93="已计入",IF(OR(OR(B93="买入",B93="定投",B93="转换转入"),B93="红利再投"),D93,IF(B93="卖出",-D93,0)),0),"") -> 314.46 | K93: =IF(AA93="正常",ROUND(K92+J93,6),"") -> 21210.81 | L93: =IF(I93="已计入",ROUND(K92*C93,2),"") -> 66352.18 | M93: =IF(I93="已计入",IF(B93="卖出",MAX(0,L93-Q92-F93),IF(B93="现金分红",MAX(0,L93+E93-Q92),0)),"") -> 0 | N93: =IF(I93="已计入",IF(AND(B93="卖出",持仓总览!$C$7="本金优先"),MAX(0,E93-Q92),IF(OR(B93="卖出",B93="现金分红"),MIN(E93,M93),0)),"") -> 0 | O93: =IF(I93="已计入",IF(OR(B93="卖出",B93="现金分红"),MIN(Q92,MAX(0,E93-N93)),0),"") -> 0 | P93: =IF(I93="已计入",IF(AND(B93="卖出",K93=0),MAX(0,Q92-O93),0),"") -> 0 | Q93: =IF(AA93="正常",IF(I93="已计入",ROUND(Q92+IF(OR(B93="买入",B93="定投",B93="转换转入"),E93,0)-O93-P93,2),Q92),"") -> 46556.01 | R93: =IF(I93="已计入",ROUND(K93*C93,2),"") -> 67350.68 | S93: =IF(I93="已计入",ROUND(R93-Q93,2),"") -> 20794.67 | T93: =IF(I93="已计入",IF(Q93=0,"",S93/Q93),"") -> 0.4466592 | U93: =IF(AA93="正常",U92+IF(AND(I93="已计入",OR(B93="买入",B93="定投",B93="转换转入")),E93,0),"") -> 46556.01 | V93: =IF(AA93="正常",V92+IF(AND(I93="已计入",OR(B93="卖出",B93="现金分红")),E93,0),"") -> 0 | W93: =IF(AA93="正常",W92+IF(I93="已计入",N93,0),"") -> 0 | X93: =IF(AA93="正常",X92+IF(I93="已计入",P93,0),"") -> 0 | Y93: =IF(I93="已计入",ROUND(R93+V93-U93,2),"") -> 20794.67 | Z93: =IF(AA93="正常",IF(I93="已计入",A93,Z92),"") -> 46216 | AA93: =IF(OR(AA92="错误",AND(I93<>"",I93<>"已排除",I93<>"待确认",I93<>"已计入")),"错误","正常") -> 正常 | AB93: =IF(AA93="正常",IF(I93="已计入",C93,AB92),"") -> 3.1753
A94: 46217 | B94: 定投 | C94: 3.2807 | D94: 304.36 | E94: 1000 | F94: 1.5 | G94: 历史估算 | H94: 原下单 2026-07-14T12:25:58 份额、费用及净值日沿用旧表估算 | I94: =IF(COUNTA(A94:H94)=0,"",IF(OR(OR(OR(G94="撤单",G94="交易失败",G94="交易关闭"),G94="交易失败",G94="交易关闭"),G94="交易失败",G94="交易关闭"),"已排除",IF(G94="待确认","待确认",IF(NOT(OR(G94="已确认",G94="历史估算")),"请选择确认状态",IF(NOT(ISNUMBER(A94)),"缺少有效净值日期",IF(OR(A94<=0,A94<>INT(A94)),"净值日期无效",IF(NOT(OR(OR(B94="买入",B94="定投",B94="转换转入"),B94="卖出",B94="现金分红",B94="红利再投")),"请选择交易类型",IF(NOT(ISNUMBER(C94)),"缺少成交净值",IF(C94<=0,"成交净值须大于零",IF(NOT(ISNUMBER(D94)),"缺少确认份额（分红填0）",IF(NOT(ISNUMBER(E94)),"缺少确认金额（再投填0）",IF(NOT(ISNUMBER(F94)),"缺少手续费（无费用填0）",IF(OR(D94<0,E94<0,F94<0),"份额金额费用不能为负",IF(AA93="错误","前行待修正",IF(A94<Z93,"日期需按成交顺序递增",IF(AND(B94="现金分红",OR(D94<>0,E94<=0,F94<>0)),"分红填份额0、费用0、正金额",IF(AND(B94="红利再投",OR(D94<=0,E94<>0,F94<>0)),"再投填正份额、金额0、费用0",IF(AND(OR(B94="现金分红",B94="红利再投"),K93<=0),"分红或再投前须有持仓",IF(AND(OR(OR(B94="买入",B94="定投",B94="转换转入"),B94="卖出"),OR(D94<=0,E94<=0)),"买卖须填正份额、正金额",IF(AND(B94="卖出",D94>K93+0.000001),"卖出份额超过持仓",IF(AND(OR(B94="买入",B94="定投",B94="转换转入"),F94>=E94),"申购费不能达到总支出",IF(NOT(ISNUMBER(持仓总览!$H$6)),"请填写金额核对容差",IF(持仓总览!$H$6<0,"金额核对容差不能为负",IF(NOT(OR(持仓总览!$C$7="利润优先",持仓总览!$C$7="本金优先")),"请选择卖出分配模式",IF(AND(OR(B94="买入",B94="定投",B94="转换转入"),ABS(E94-F94-C94*D94)>持仓总览!$H$6),"买入金额与份额净值不符",IF(AND(B94="卖出",ABS(E94+F94-C94*D94)>持仓总览!$H$6),"到账加费用与赎回市值不符","已计入")))))))))))))))))))))))))) -> 已计入 | J94: =IF(AA94="正常",IF(I94="已计入",IF(OR(OR(B94="买入",B94="定投",B94="转换转入"),B94="红利再投"),D94,IF(B94="卖出",-D94,0)),0),"") -> 304.36 | K94: =IF(AA94="正常",ROUND(K93+J94,6),"") -> 21515.17 | L94: =IF(I94="已计入",ROUND(K93*C94,2),"") -> 69586.3 | M94: =IF(I94="已计入",IF(B94="卖出",MAX(0,L94-Q93-F94),IF(B94="现金分红",MAX(0,L94+E94-Q93),0)),"") -> 0 | N94: =IF(I94="已计入",IF(AND(B94="卖出",持仓总览!$C$7="本金优先"),MAX(0,E94-Q93),IF(OR(B94="卖出",B94="现金分红"),MIN(E94,M94),0)),"") -> 0 | O94: =IF(I94="已计入",IF(OR(B94="卖出",B94="现金分红"),MIN(Q93,MAX(0,E94-N94)),0),"") -> 0 | P94: =IF(I94="已计入",IF(AND(B94="卖出",K94=0),MAX(0,Q93-O94),0),"") -> 0 | Q94: =IF(AA94="正常",IF(I94="已计入",ROUND(Q93+IF(OR(B94="买入",B94="定投",B94="转换转入"),E94,0)-O94-P94,2),Q93),"") -> 47556.01 | R94: =IF(I94="已计入",ROUND(K94*C94,2),"") -> 70584.82 | S94: =IF(I94="已计入",ROUND(R94-Q94,2),"") -> 23028.81 | T94: =IF(I94="已计入",IF(Q94=0,"",S94/Q94),"") -> 0.48424605 | U94: =IF(AA94="正常",U93+IF(AND(I94="已计入",OR(B94="买入",B94="定投",B94="转换转入")),E94,0),"") -> 47556.01 | V94: =IF(AA94="正常",V93+IF(AND(I94="已计入",OR(B94="卖出",B94="现金分红")),E94,0),"") -> 0 | W94: =IF(AA94="正常",W93+IF(I94="已计入",N94,0),"") -> 0 | X94: =IF(AA94="正常",X93+IF(I94="已计入",P94,0),"") -> 0 | Y94: =IF(I94="已计入",ROUND(R94+V94-U94,2),"") -> 23028.81 | Z94: =IF(AA94="正常",IF(I94="已计入",A94,Z93),"") -> 46217 | AA94: =IF(OR(AA93="错误",AND(I94<>"",I94<>"已排除",I94<>"待确认",I94<>"已计入")),"错误","正常") -> 正常 | AB94: =IF(AA94="正常",IF(I94="已计入",C94,AB93),"") -> 3.2807
A95: 46218 | B95: 定投 | C95: 3.1877 | D95: 313.24 | E95: 1000 | F95: 1.5 | G95: 历史估算 | H95: 原下单 2026-07-15T12:21:48 份额、费用及净值日沿用旧表估算 | I95: =IF(COUNTA(A95:H95)=0,"",IF(OR(OR(OR(G95="撤单",G95="交易失败",G95="交易关闭"),G95="交易失败",G95="交易关闭"),G95="交易失败",G95="交易关闭"),"已排除",IF(G95="待确认","待确认",IF(NOT(OR(G95="已确认",G95="历史估算")),"请选择确认状态",IF(NOT(ISNUMBER(A95)),"缺少有效净值日期",IF(OR(A95<=0,A95<>INT(A95)),"净值日期无效",IF(NOT(OR(OR(B95="买入",B95="定投",B95="转换转入"),B95="卖出",B95="现金分红",B95="红利再投")),"请选择交易类型",IF(NOT(ISNUMBER(C95)),"缺少成交净值",IF(C95<=0,"成交净值须大于零",IF(NOT(ISNUMBER(D95)),"缺少确认份额（分红填0）",IF(NOT(ISNUMBER(E95)),"缺少确认金额（再投填0）",IF(NOT(ISNUMBER(F95)),"缺少手续费（无费用填0）",IF(OR(D95<0,E95<0,F95<0),"份额金额费用不能为负",IF(AA94="错误","前行待修正",IF(A95<Z94,"日期需按成交顺序递增",IF(AND(B95="现金分红",OR(D95<>0,E95<=0,F95<>0)),"分红填份额0、费用0、正金额",IF(AND(B95="红利再投",OR(D95<=0,E95<>0,F95<>0)),"再投填正份额、金额0、费用0",IF(AND(OR(B95="现金分红",B95="红利再投"),K94<=0),"分红或再投前须有持仓",IF(AND(OR(OR(B95="买入",B95="定投",B95="转换转入"),B95="卖出"),OR(D95<=0,E95<=0)),"买卖须填正份额、正金额",IF(AND(B95="卖出",D95>K94+0.000001),"卖出份额超过持仓",IF(AND(OR(B95="买入",B95="定投",B95="转换转入"),F95>=E95),"申购费不能达到总支出",IF(NOT(ISNUMBER(持仓总览!$H$6)),"请填写金额核对容差",IF(持仓总览!$H$6<0,"金额核对容差不能为负",IF(NOT(OR(持仓总览!$C$7="利润优先",持仓总览!$C$7="本金优先")),"请选择卖出分配模式",IF(AND(OR(B95="买入",B95="定投",B95="转换转入"),ABS(E95-F95-C95*D95)>持仓总览!$H$6),"买入金额与份额净值不符",IF(AND(B95="卖出",ABS(E95+F95-C95*D95)>持仓总览!$H$6),"到账加费用与赎回市值不符","已计入")))))))))))))))))))))))))) -> 已计入 | J95: =IF(AA95="正常",IF(I95="已计入",IF(OR(OR(B95="买入",B95="定投",B95="转换转入"),B95="红利再投"),D95,IF(B95="卖出",-D95,0)),0),"") -> 313.24 | K95: =IF(AA95="正常",ROUND(K94+J95,6),"") -> 21828.41 | L95: =IF(I95="已计入",ROUND(K94*C95,2),"") -> 68583.91 | M95: =IF(I95="已计入",IF(B95="卖出",MAX(0,L95-Q94-F95),IF(B95="现金分红",MAX(0,L95+E95-Q94),0)),"") -> 0 | N95: =IF(I95="已计入",IF(AND(B95="卖出",持仓总览!$C$7="本金优先"),MAX(0,E95-Q94),IF(OR(B95="卖出",B95="现金分红"),MIN(E95,M95),0)),"") -> 0 | O95: =IF(I95="已计入",IF(OR(B95="卖出",B95="现金分红"),MIN(Q94,MAX(0,E95-N95)),0),"") -> 0 | P95: =IF(I95="已计入",IF(AND(B95="卖出",K95=0),MAX(0,Q94-O95),0),"") -> 0 | Q95: =IF(AA95="正常",IF(I95="已计入",ROUND(Q94+IF(OR(B95="买入",B95="定投",B95="转换转入"),E95,0)-O95-P95,2),Q94),"") -> 48556.01 | R95: =IF(I95="已计入",ROUND(K95*C95,2),"") -> 69582.42 | S95: =IF(I95="已计入",ROUND(R95-Q95,2),"") -> 21026.41 | T95: =IF(I95="已计入",IF(Q95=0,"",S95/Q95),"") -> 0.43303414 | U95: =IF(AA95="正常",U94+IF(AND(I95="已计入",OR(B95="买入",B95="定投",B95="转换转入")),E95,0),"") -> 48556.01 | V95: =IF(AA95="正常",V94+IF(AND(I95="已计入",OR(B95="卖出",B95="现金分红")),E95,0),"") -> 0 | W95: =IF(AA95="正常",W94+IF(I95="已计入",N95,0),"") -> 0 | X95: =IF(AA95="正常",X94+IF(I95="已计入",P95,0),"") -> 0 | Y95: =IF(I95="已计入",ROUND(R95+V95-U95,2),"") -> 21026.41 | Z95: =IF(AA95="正常",IF(I95="已计入",A95,Z94),"") -> 46218 | AA95: =IF(OR(AA94="错误",AND(I95<>"",I95<>"已排除",I95<>"待确认",I95<>"已计入")),"错误","正常") -> 正常 | AB95: =IF(AA95="正常",IF(I95="已计入",C95,AB94),"") -> 3.1877
A96: 46219 | B96: 定投 | C96: 3.02 | D96: 330.63 | E96: 1000 | F96: 1.5 | G96: 历史估算 | H96: 原下单 2026-07-16T12:22:48 份额、费用及净值日沿用旧表估算 | I96: =IF(COUNTA(A96:H96)=0,"",IF(OR(OR(OR(G96="撤单",G96="交易失败",G96="交易关闭"),G96="交易失败",G96="交易关闭"),G96="交易失败",G96="交易关闭"),"已排除",IF(G96="待确认","待确认",IF(NOT(OR(G96="已确认",G96="历史估算")),"请选择确认状态",IF(NOT(ISNUMBER(A96)),"缺少有效净值日期",IF(OR(A96<=0,A96<>INT(A96)),"净值日期无效",IF(NOT(OR(OR(B96="买入",B96="定投",B96="转换转入"),B96="卖出",B96="现金分红",B96="红利再投")),"请选择交易类型",IF(NOT(ISNUMBER(C96)),"缺少成交净值",IF(C96<=0,"成交净值须大于零",IF(NOT(ISNUMBER(D96)),"缺少确认份额（分红填0）",IF(NOT(ISNUMBER(E96)),"缺少确认金额（再投填0）",IF(NOT(ISNUMBER(F96)),"缺少手续费（无费用填0）",IF(OR(D96<0,E96<0,F96<0),"份额金额费用不能为负",IF(AA95="错误","前行待修正",IF(A96<Z95,"日期需按成交顺序递增",IF(AND(B96="现金分红",OR(D96<>0,E96<=0,F96<>0)),"分红填份额0、费用0、正金额",IF(AND(B96="红利再投",OR(D96<=0,E96<>0,F96<>0)),"再投填正份额、金额0、费用0",IF(AND(OR(B96="现金分红",B96="红利再投"),K95<=0),"分红或再投前须有持仓",IF(AND(OR(OR(B96="买入",B96="定投",B96="转换转入"),B96="卖出"),OR(D96<=0,E96<=0)),"买卖须填正份额、正金额",IF(AND(B96="卖出",D96>K95+0.000001),"卖出份额超过持仓",IF(AND(OR(B96="买入",B96="定投",B96="转换转入"),F96>=E96),"申购费不能达到总支出",IF(NOT(ISNUMBER(持仓总览!$H$6)),"请填写金额核对容差",IF(持仓总览!$H$6<0,"金额核对容差不能为负",IF(NOT(OR(持仓总览!$C$7="利润优先",持仓总览!$C$7="本金优先")),"请选择卖出分配模式",IF(AND(OR(B96="买入",B96="定投",B96="转换转入"),ABS(E96-F96-C96*D96)>持仓总览!$H$6),"买入金额与份额净值不符",IF(AND(B96="卖出",ABS(E96+F96-C96*D96)>持仓总览!$H$6),"到账加费用与赎回市值不符","已计入")))))))))))))))))))))))))) -> 已计入 | J96: =IF(AA96="正常",IF(I96="已计入",IF(OR(OR(B96="买入",B96="定投",B96="转换转入"),B96="红利再投"),D96,IF(B96="卖出",-D96,0)),0),"") -> 330.63 | K96: =IF(AA96="正常",ROUND(K95+J96,6),"") -> 22159.04 | L96: =IF(I96="已计入",ROUND(K95*C96,2),"") -> 65921.8 | M96: =IF(I96="已计入",IF(B96="卖出",MAX(0,L96-Q95-F96),IF(B96="现金分红",MAX(0,L96+E96-Q95),0)),"") -> 0 | N96: =IF(I96="已计入",IF(AND(B96="卖出",持仓总览!$C$7="本金优先"),MAX(0,E96-Q95),IF(OR(B96="卖出",B96="现金分红"),MIN(E96,M96),0)),"") -> 0 | O96: =IF(I96="已计入",IF(OR(B96="卖出",B96="现金分红"),MIN(Q95,MAX(0,E96-N96)),0),"") -> 0 | P96: =IF(I96="已计入",IF(AND(B96="卖出",K96=0),MAX(0,Q95-O96),0),"") -> 0 | Q96: =IF(AA96="正常",IF(I96="已计入",ROUND(Q95+IF(OR(B96="买入",B96="定投",B96="转换转入"),E96,0)-O96-P96,2),Q95),"") -> 49556.01 | R96: =IF(I96="已计入",ROUND(K96*C96,2),"") -> 66920.3 | S96: =IF(I96="已计入",ROUND(R96-Q96,2),"") -> 17364.29 | T96: =IF(I96="已计入",IF(Q96=0,"",S96/Q96),"") -> 0.35039726 | U96: =IF(AA96="正常",U95+IF(AND(I96="已计入",OR(B96="买入",B96="定投",B96="转换转入")),E96,0),"") -> 49556.01 | V96: =IF(AA96="正常",V95+IF(AND(I96="已计入",OR(B96="卖出",B96="现金分红")),E96,0),"") -> 0 | W96: =IF(AA96="正常",W95+IF(I96="已计入",N96,0),"") -> 0 | X96: =IF(AA96="正常",X95+IF(I96="已计入",P96,0),"") -> 0 | Y96: =IF(I96="已计入",ROUND(R96+V96-U96,2),"") -> 17364.29 | Z96: =IF(AA96="正常",IF(I96="已计入",A96,Z95),"") -> 46219 | AA96: =IF(OR(AA95="错误",AND(I96<>"",I96<>"已排除",I96<>"待确认",I96<>"已计入")),"错误","正常") -> 正常 | AB96: =IF(AA96="正常",IF(I96="已计入",C96,AB95),"") -> 3.02
A97: 46220 | B97: 定投 | C97: 2.8423 | D97: 351.3 | E97: 1000 | F97: 1.5 | G97: 历史估算 | H97: 原下单 2026-07-17T12:12:45 份额、费用及净值日沿用旧表估算 | I97: =IF(COUNTA(A97:H97)=0,"",IF(OR(OR(OR(G97="撤单",G97="交易失败",G97="交易关闭"),G97="交易失败",G97="交易关闭"),G97="交易失败",G97="交易关闭"),"已排除",IF(G97="待确认","待确认",IF(NOT(OR(G97="已确认",G97="历史估算")),"请选择确认状态",IF(NOT(ISNUMBER(A97)),"缺少有效净值日期",IF(OR(A97<=0,A97<>INT(A97)),"净值日期无效",IF(NOT(OR(OR(B97="买入",B97="定投",B97="转换转入"),B97="卖出",B97="现金分红",B97="红利再投")),"请选择交易类型",IF(NOT(ISNUMBER(C97)),"缺少成交净值",IF(C97<=0,"成交净值须大于零",IF(NOT(ISNUMBER(D97)),"缺少确认份额（分红填0）",IF(NOT(ISNUMBER(E97)),"缺少确认金额（再投填0）",IF(NOT(ISNUMBER(F97)),"缺少手续费（无费用填0）",IF(OR(D97<0,E97<0,F97<0),"份额金额费用不能为负",IF(AA96="错误","前行待修正",IF(A97<Z96,"日期需按成交顺序递增",IF(AND(B97="现金分红",OR(D97<>0,E97<=0,F97<>0)),"分红填份额0、费用0、正金额",IF(AND(B97="红利再投",OR(D97<=0,E97<>0,F97<>0)),"再投填正份额、金额0、费用0",IF(AND(OR(B97="现金分红",B97="红利再投"),K96<=0),"分红或再投前须有持仓",IF(AND(OR(OR(B97="买入",B97="定投",B97="转换转入"),B97="卖出"),OR(D97<=0,E97<=0)),"买卖须填正份额、正金额",IF(AND(B97="卖出",D97>K96+0.000001),"卖出份额超过持仓",IF(AND(OR(B97="买入",B97="定投",B97="转换转入"),F97>=E97),"申购费不能达到总支出",IF(NOT(ISNUMBER(持仓总览!$H$6)),"请填写金额核对容差",IF(持仓总览!$H$6<0,"金额核对容差不能为负",IF(NOT(OR(持仓总览!$C$7="利润优先",持仓总览!$C$7="本金优先")),"请选择卖出分配模式",IF(AND(OR(B97="买入",B97="定投",B97="转换转入"),ABS(E97-F97-C97*D97)>持仓总览!$H$6),"买入金额与份额净值不符",IF(AND(B97="卖出",ABS(E97+F97-C97*D97)>持仓总览!$H$6),"到账加费用与赎回市值不符","已计入")))))))))))))))))))))))))) -> 已计入 | J97: =IF(AA97="正常",IF(I97="已计入",IF(OR(OR(B97="买入",B97="定投",B97="转换转入"),B97="红利再投"),D97,IF(B97="卖出",-D97,0)),0),"") -> 351.3 | K97: =IF(AA97="正常",ROUND(K96+J97,6),"") -> 22510.34 | L97: =IF(I97="已计入",ROUND(K96*C97,2),"") -> 62982.64 | M97: =IF(I97="已计入",IF(B97="卖出",MAX(0,L97-Q96-F97),IF(B97="现金分红",MAX(0,L97+E97-Q96),0)),"") -> 0 | N97: =IF(I97="已计入",IF(AND(B97="卖出",持仓总览!$C$7="本金优先"),MAX(0,E97-Q96),IF(OR(B97="卖出",B97="现金分红"),MIN(E97,M97),0)),"") -> 0 | O97: =IF(I97="已计入",IF(OR(B97="卖出",B97="现金分红"),MIN(Q96,MAX(0,E97-N97)),0),"") -> 0 | P97: =IF(I97="已计入",IF(AND(B97="卖出",K97=0),MAX(0,Q96-O97),0),"") -> 0 | Q97: =IF(AA97="正常",IF(I97="已计入",ROUND(Q96+IF(OR(B97="买入",B97="定投",B97="转换转入"),E97,0)-O97-P97,2),Q96),"") -> 50556.01 | R97: =IF(I97="已计入",ROUND(K97*C97,2),"") -> 63981.14 | S97: =IF(I97="已计入",ROUND(R97-Q97,2),"") -> 13425.13 | T97: =IF(I97="已计入",IF(Q97=0,"",S97/Q97),"") -> 0.26554963 | U97: =IF(AA97="正常",U96+IF(AND(I97="已计入",OR(B97="买入",B97="定投",B97="转换转入")),E97,0),"") -> 50556.01 | V97: =IF(AA97="正常",V96+IF(AND(I97="已计入",OR(B97="卖出",B97="现金分红")),E97,0),"") -> 0 | W97: =IF(AA97="正常",W96+IF(I97="已计入",N97,0),"") -> 0 | X97: =IF(AA97="正常",X96+IF(I97="已计入",P97,0),"") -> 0 | Y97: =IF(I97="已计入",ROUND(R97+V97-U97,2),"") -> 13425.13 | Z97: =IF(AA97="正常",IF(I97="已计入",A97,Z96),"") -> 46220 | AA97: =IF(OR(AA96="错误",AND(I97<>"",I97<>"已排除",I97<>"待确认",I97<>"已计入")),"错误","正常") -> 正常 | AB97: =IF(AA97="正常",IF(I97="已计入",C97,AB96),"") -> 2.8423
A98: 46223 | B98: 定投 | C98: 2.8312 | D98: 70.54 | E98: 200 | F98: 0.3 | G98: 历史估算 | H98: 原下单 2026-07-20T12:24:05 份额、费用及净值日沿用旧表估算 | I98: =IF(COUNTA(A98:H98)=0,"",IF(OR(OR(OR(G98="撤单",G98="交易失败",G98="交易关闭"),G98="交易失败",G98="交易关闭"),G98="交易失败",G98="交易关闭"),"已排除",IF(G98="待确认","待确认",IF(NOT(OR(G98="已确认",G98="历史估算")),"请选择确认状态",IF(NOT(ISNUMBER(A98)),"缺少有效净值日期",IF(OR(A98<=0,A98<>INT(A98)),"净值日期无效",IF(NOT(OR(OR(B98="买入",B98="定投",B98="转换转入"),B98="卖出",B98="现金分红",B98="红利再投")),"请选择交易类型",IF(NOT(ISNUMBER(C98)),"缺少成交净值",IF(C98<=0,"成交净值须大于零",IF(NOT(ISNUMBER(D98)),"缺少确认份额（分红填0）",IF(NOT(ISNUMBER(E98)),"缺少确认金额（再投填0）",IF(NOT(ISNUMBER(F98)),"缺少手续费（无费用填0）",IF(OR(D98<0,E98<0,F98<0),"份额金额费用不能为负",IF(AA97="错误","前行待修正",IF(A98<Z97,"日期需按成交顺序递增",IF(AND(B98="现金分红",OR(D98<>0,E98<=0,F98<>0)),"分红填份额0、费用0、正金额",IF(AND(B98="红利再投",OR(D98<=0,E98<>0,F98<>0)),"再投填正份额、金额0、费用0",IF(AND(OR(B98="现金分红",B98="红利再投"),K97<=0),"分红或再投前须有持仓",IF(AND(OR(OR(B98="买入",B98="定投",B98="转换转入"),B98="卖出"),OR(D98<=0,E98<=0)),"买卖须填正份额、正金额",IF(AND(B98="卖出",D98>K97+0.000001),"卖出份额超过持仓",IF(AND(OR(B98="买入",B98="定投",B98="转换转入"),F98>=E98),"申购费不能达到总支出",IF(NOT(ISNUMBER(持仓总览!$H$6)),"请填写金额核对容差",IF(持仓总览!$H$6<0,"金额核对容差不能为负",IF(NOT(OR(持仓总览!$C$7="利润优先",持仓总览!$C$7="本金优先")),"请选择卖出分配模式",IF(AND(OR(B98="买入",B98="定投",B98="转换转入"),ABS(E98-F98-C98*D98)>持仓总览!$H$6),"买入金额与份额净值不符",IF(AND(B98="卖出",ABS(E98+F98-C98*D98)>持仓总览!$H$6),"到账加费用与赎回市值不符","已计入")))))))))))))))))))))))))) -> 已计入 | J98: =IF(AA98="正常",IF(I98="已计入",IF(OR(OR(B98="买入",B98="定投",B98="转换转入"),B98="红利再投"),D98,IF(B98="卖出",-D98,0)),0),"") -> 70.54 | K98: =IF(AA98="正常",ROUND(K97+J98,6),"") -> 22580.88 | L98: =IF(I98="已计入",ROUND(K97*C98,2),"") -> 63731.27 | M98: =IF(I98="已计入",IF(B98="卖出",MAX(0,L98-Q97-F98),IF(B98="现金分红",MAX(0,L98+E98-Q97),0)),"") -> 0 | N98: =IF(I98="已计入",IF(AND(B98="卖出",持仓总览!$C$7="本金优先"),MAX(0,E98-Q97),IF(OR(B98="卖出",B98="现金分红"),MIN(E98,M98),0)),"") -> 0 | O98: =IF(I98="已计入",IF(OR(B98="卖出",B98="现金分红"),MIN(Q97,MAX(0,E98-N98)),0),"") -> 0 | P98: =IF(I98="已计入",IF(AND(B98="卖出",K98=0),MAX(0,Q97-O98),0),"") -> 0 | Q98: =IF(AA98="正常",IF(I98="已计入",ROUND(Q97+IF(OR(B98="买入",B98="定投",B98="转换转入"),E98,0)-O98-P98,2),Q97),"") -> 50756.01 | R98: =IF(I98="已计入",ROUND(K98*C98,2),"") -> 63930.99 | S98: =IF(I98="已计入",ROUND(R98-Q98,2),"") -> 13174.98 | T98: =IF(I98="已计入",IF(Q98=0,"",S98/Q98),"") -> 0.25957478 | U98: =IF(AA98="正常",U97+IF(AND(I98="已计入",OR(B98="买入",B98="定投",B98="转换转入")),E98,0),"") -> 50756.01 | V98: =IF(AA98="正常",V97+IF(AND(I98="已计入",OR(B98="卖出",B98="现金分红")),E98,0),"") -> 0 | W98: =IF(AA98="正常",W97+IF(I98="已计入",N98,0),"") -> 0 | X98: =IF(AA98="正常",X97+IF(I98="已计入",P98,0),"") -> 0 | Y98: =IF(I98="已计入",ROUND(R98+V98-U98,2),"") -> 13174.98 | Z98: =IF(AA98="正常",IF(I98="已计入",A98,Z97),"") -> 46223 | AA98: =IF(OR(AA97="错误",AND(I98<>"",I98<>"已排除",I98<>"待确认",I98<>"已计入")),"错误","正常") -> 正常 | AB98: =IF(AA98="正常",IF(I98="已计入",C98,AB97),"") -> 2.8312
A99: 46224 | B99: 定投 | C99: 2.9654 | D99: 16.83 | E99: 50 | F99: 0.08 | G99: 历史估算 | H99: 原下单 2026-07-21T12:11:54 份额、费用及净值日沿用旧表估算 | I99: =IF(COUNTA(A99:H99)=0,"",IF(OR(OR(OR(G99="撤单",G99="交易失败",G99="交易关闭"),G99="交易失败",G99="交易关闭"),G99="交易失败",G99="交易关闭"),"已排除",IF(G99="待确认","待确认",IF(NOT(OR(G99="已确认",G99="历史估算")),"请选择确认状态",IF(NOT(ISNUMBER(A99)),"缺少有效净值日期",IF(OR(A99<=0,A99<>INT(A99)),"净值日期无效",IF(NOT(OR(OR(B99="买入",B99="定投",B99="转换转入"),B99="卖出",B99="现金分红",B99="红利再投")),"请选择交易类型",IF(NOT(ISNUMBER(C99)),"缺少成交净值",IF(C99<=0,"成交净值须大于零",IF(NOT(ISNUMBER(D99)),"缺少确认份额（分红填0）",IF(NOT(ISNUMBER(E99)),"缺少确认金额（再投填0）",IF(NOT(ISNUMBER(F99)),"缺少手续费（无费用填0）",IF(OR(D99<0,E99<0,F99<0),"份额金额费用不能为负",IF(AA98="错误","前行待修正",IF(A99<Z98,"日期需按成交顺序递增",IF(AND(B99="现金分红",OR(D99<>0,E99<=0,F99<>0)),"分红填份额0、费用0、正金额",IF(AND(B99="红利再投",OR(D99<=0,E99<>0,F99<>0)),"再投填正份额、金额0、费用0",IF(AND(OR(B99="现金分红",B99="红利再投"),K98<=0),"分红或再投前须有持仓",IF(AND(OR(OR(B99="买入",B99="定投",B99="转换转入"),B99="卖出"),OR(D99<=0,E99<=0)),"买卖须填正份额、正金额",IF(AND(B99="卖出",D99>K98+0.000001),"卖出份额超过持仓",IF(AND(OR(B99="买入",B99="定投",B99="转换转入"),F99>=E99),"申购费不能达到总支出",IF(NOT(ISNUMBER(持仓总览!$H$6)),"请填写金额核对容差",IF(持仓总览!$H$6<0,"金额核对容差不能为负",IF(NOT(OR(持仓总览!$C$7="利润优先",持仓总览!$C$7="本金优先")),"请选择卖出分配模式",IF(AND(OR(B99="买入",B99="定投",B99="转换转入"),ABS(E99-F99-C99*D99)>持仓总览!$H$6),"买入金额与份额净值不符",IF(AND(B99="卖出",ABS(E99+F99-C99*D99)>持仓总览!$H$6),"到账加费用与赎回市值不符","已计入")))))))))))))))))))))))))) -> 已计入 | J99: =IF(AA99="正常",IF(I99="已计入",IF(OR(OR(B99="买入",B99="定投",B99="转换转入"),B99="红利再投"),D99,IF(B99="卖出",-D99,0)),0),"") -> 16.83 | K99: =IF(AA99="正常",ROUND(K98+J99,6),"") -> 22597.71 | L99: =IF(I99="已计入",ROUND(K98*C99,2),"") -> 66961.34 | M99: =IF(I99="已计入",IF(B99="卖出",MAX(0,L99-Q98-F99),IF(B99="现金分红",MAX(0,L99+E99-Q98),0)),"") -> 0 | N99: =IF(I99="已计入",IF(AND(B99="卖出",持仓总览!$C$7="本金优先"),MAX(0,E99-Q98),IF(OR(B99="卖出",B99="现金分红"),MIN(E99,M99),0)),"") -> 0 | O99: =IF(I99="已计入",IF(OR(B99="卖出",B99="现金分红"),MIN(Q98,MAX(0,E99-N99)),0),"") -> 0 | P99: =IF(I99="已计入",IF(AND(B99="卖出",K99=0),MAX(0,Q98-O99),0),"") -> 0 | Q99: =IF(AA99="正常",IF(I99="已计入",ROUND(Q98+IF(OR(B99="买入",B99="定投",B99="转换转入"),E99,0)-O99-P99,2),Q98),"") -> 50806.01 | R99: =IF(I99="已计入",ROUND(K99*C99,2),"") -> 67011.25 | S99: =IF(I99="已计入",ROUND(R99-Q99,2),"") -> 16205.24 | T99: =IF(I99="已计入",IF(Q99=0,"",S99/Q99),"") -> 0.31896305 | U99: =IF(AA99="正常",U98+IF(AND(I99="已计入",OR(B99="买入",B99="定投",B99="转换转入")),E99,0),"") -> 50806.01 | V99: =IF(AA99="正常",V98+IF(AND(I99="已计入",OR(B99="卖出",B99="现金分红")),E99,0),"") -> 0 | W99: =IF(AA99="正常",W98+IF(I99="已计入",N99,0),"") -> 0 | X99: =IF(AA99="正常",X98+IF(I99="已计入",P99,0),"") -> 0 | Y99: =IF(I99="已计入",ROUND(R99+V99-U99,2),"") -> 16205.24 | Z99: =IF(AA99="正常",IF(I99="已计入",A99,Z98),"") -> 46224 | AA99: =IF(OR(AA98="错误",AND(I99<>"",I99<>"已排除",I99<>"待确认",I99<>"已计入")),"错误","正常") -> 正常 | AB99: =IF(AA99="正常",IF(I99="已计入",C99,AB98),"") -> 2.9654
A100: 46225 | B100: 定投 | C100: 2.9094 | D100: 68.64 | E100: 200 | F100: 0.3 | G100: 历史估算 | H100: 原下单 2026-07-22T12:10:17 份额、费用及净值日沿用旧表估算 | I100: =IF(COUNTA(A100:H100)=0,"",IF(OR(OR(OR(G100="撤单",G100="交易失败",G100="交易关闭"),G100="交易失败",G100="交易关闭"),G100="交易失败",G100="交易关闭"),"已排除",IF(G100="待确认","待确认",IF(NOT(OR(G100="已确认",G100="历史估算")),"请选择确认状态",IF(NOT(ISNUMBER(A100)),"缺少有效净值日期",IF(OR(A100<=0,A100<>INT(A100)),"净值日期无效",IF(NOT(OR(OR(B100="买入",B100="定投",B100="转换转入"),B100="卖出",B100="现金分红",B100="红利再投")),"请选择交易类型",IF(NOT(ISNUMBER(C100)),"缺少成交净值",IF(C100<=0,"成交净值须大于零",IF(NOT(ISNUMBER(D100)),"缺少确认份额（分红填0）",IF(NOT(ISNUMBER(E100)),"缺少确认金额（再投填0）",IF(NOT(ISNUMBER(F100)),"缺少手续费（无费用填0）",IF(OR(D100<0,E100<0,F100<0),"份额金额费用不能为负",IF(AA99="错误","前行待修正",IF(A100<Z99,"日期需按成交顺序递增",IF(AND(B100="现金分红",OR(D100<>0,E100<=0,F100<>0)),"分红填份额0、费用0、正金额",IF(AND(B100="红利再投",OR(D100<=0,E100<>0,F100<>0)),"再投填正份额、金额0、费用0",IF(AND(OR(B100="现金分红",B100="红利再投"),K99<=0),"分红或再投前须有持仓",IF(AND(OR(OR(B100="买入",B100="定投",B100="转换转入"),B100="卖出"),OR(D100<=0,E100<=0)),"买卖须填正份额、正金额",IF(AND(B100="卖出",D100>K99+0.000001),"卖出份额超过持仓",IF(AND(OR(B100="买入",B100="定投",B100="转换转入"),F100>=E100),"申购费不能达到总支出",IF(NOT(ISNUMBER(持仓总览!$H$6)),"请填写金额核对容差",IF(持仓总览!$H$6<0,"金额核对容差不能为负",IF(NOT(OR(持仓总览!$C$7="利润优先",持仓总览!$C$7="本金优先")),"请选择卖出分配模式",IF(AND(OR(B100="买入",B100="定投",B100="转换转入"),ABS(E100-F100-C100*D100)>持仓总览!$H$6),"买入金额与份额净值不符",IF(AND(B100="卖出",ABS(E100+F100-C100*D100)>持仓总览!$H$6),"到账加费用与赎回市值不符","已计入")))))))))))))))))))))))))) -> 已计入 | J100: =IF(AA100="正常",IF(I100="已计入",IF(OR(OR(B100="买入",B100="定投",B100="转换转入"),B100="红利再投"),D100,IF(B100="卖出",-D100,0)),0),"") -> 68.64 | K100: =IF(AA100="正常",ROUND(K99+J100,6),"") -> 22666.35 | L100: =IF(I100="已计入",ROUND(K99*C100,2),"") -> 65745.78 | M100: =IF(I100="已计入",IF(B100="卖出",MAX(0,L100-Q99-F100),IF(B100="现金分红",MAX(0,L100+E100-Q99),0)),"") -> 0 | N100: =IF(I100="已计入",IF(AND(B100="卖出",持仓总览!$C$7="本金优先"),MAX(0,E100-Q99),IF(OR(B100="卖出",B100="现金分红"),MIN(E100,M100),0)),"") -> 0 | O100: =IF(I100="已计入",IF(OR(B100="卖出",B100="现金分红"),MIN(Q99,MAX(0,E100-N100)),0),"") -> 0 | P100: =IF(I100="已计入",IF(AND(B100="卖出",K100=0),MAX(0,Q99-O100),0),"") -> 0 | Q100: =IF(AA100="正常",IF(I100="已计入",ROUND(Q99+IF(OR(B100="买入",B100="定投",B100="转换转入"),E100,0)-O100-P100,2),Q99),"") -> 51006.01 | R100: =IF(I100="已计入",ROUND(K100*C100,2),"") -> 65945.48 | S100: =IF(I100="已计入",ROUND(R100-Q100,2),"") -> 14939.47 | T100: =IF(I100="已计入",IF(Q100=0,"",S100/Q100),"") -> 0.29289627 | U100: =IF(AA100="正常",U99+IF(AND(I100="已计入",OR(B100="买入",B100="定投",B100="转换转入")),E100,0),"") -> 51006.01 | V100: =IF(AA100="正常",V99+IF(AND(I100="已计入",OR(B100="卖出",B100="现金分红")),E100,0),"") -> 0 | W100: =IF(AA100="正常",W99+IF(I100="已计入",N100,0),"") -> 0 | X100: =IF(AA100="正常",X99+IF(I100="已计入",P100,0),"") -> 0 | Y100: =IF(I100="已计入",ROUND(R100+V100-U100,2),"") -> 14939.47 | Z100: =IF(AA100="正常",IF(I100="已计入",A100,Z99),"") -> 46225 | AA100: =IF(OR(AA99="错误",AND(I100<>"",I100<>"已排除",I100<>"待确认",I100<>"已计入")),"错误","正常") -> 正常 | AB100: =IF(AA100="正常",IF(I100="已计入",C100,AB99),"") -> 2.9094
A101: 46226 | B101: 定投 | C101: 2.8739 | D101: 69.49 | E101: 200 | F101: 0.3 | G101: 历史估算 | H101: 原下单 2026-07-23T12:11:28 份额、费用及净值日沿用旧表估算 | I101: =IF(COUNTA(A101:H101)=0,"",IF(OR(OR(OR(G101="撤单",G101="交易失败",G101="交易关闭"),G101="交易失败",G101="交易关闭"),G101="交易失败",G101="交易关闭"),"已排除",IF(G101="待确认","待确认",IF(NOT(OR(G101="已确认",G101="历史估算")),"请选择确认状态",IF(NOT(ISNUMBER(A101)),"缺少有效净值日期",IF(OR(A101<=0,A101<>INT(A101)),"净值日期无效",IF(NOT(OR(OR(B101="买入",B101="定投",B101="转换转入"),B101="卖出",B101="现金分红",B101="红利再投")),"请选择交易类型",IF(NOT(ISNUMBER(C101)),"缺少成交净值",IF(C101<=0,"成交净值须大于零",IF(NOT(ISNUMBER(D101)),"缺少确认份额（分红填0）",IF(NOT(ISNUMBER(E101)),"缺少确认金额（再投填0）",IF(NOT(ISNUMBER(F101)),"缺少手续费（无费用填0）",IF(OR(D101<0,E101<0,F101<0),"份额金额费用不能为负",IF(AA100="错误","前行待修正",IF(A101<Z100,"日期需按成交顺序递增",IF(AND(B101="现金分红",OR(D101<>0,E101<=0,F101<>0)),"分红填份额0、费用0、正金额",IF(AND(B101="红利再投",OR(D101<=0,E101<>0,F101<>0)),"再投填正份额、金额0、费用0",IF(AND(OR(B101="现金分红",B101="红利再投"),K100<=0),"分红或再投前须有持仓",IF(AND(OR(OR(B101="买入",B101="定投",B101="转换转入"),B101="卖出"),OR(D101<=0,E101<=0)),"买卖须填正份额、正金额",IF(AND(B101="卖出",D101>K100+0.000001),"卖出份额超过持仓",IF(AND(OR(B101="买入",B101="定投",B101="转换转入"),F101>=E101),"申购费不能达到总支出",IF(NOT(ISNUMBER(持仓总览!$H$6)),"请填写金额核对容差",IF(持仓总览!$H$6<0,"金额核对容差不能为负",IF(NOT(OR(持仓总览!$C$7="利润优先",持仓总览!$C$7="本金优先")),"请选择卖出分配模式",IF(AND(OR(B101="买入",B101="定投",B101="转换转入"),ABS(E101-F101-C101*D101)>持仓总览!$H$6),"买入金额与份额净值不符",IF(AND(B101="卖出",ABS(E101+F101-C101*D101)>持仓总览!$H$6),"到账加费用与赎回市值不符","已计入")))))))))))))))))))))))))) -> 已计入 | J101: =IF(AA101="正常",IF(I101="已计入",IF(OR(OR(B101="买入",B101="定投",B101="转换转入"),B101="红利再投"),D101,IF(B101="卖出",-D101,0)),0),"") -> 69.49 | K101: =IF(AA101="正常",ROUND(K100+J101,6),"") -> 22735.84 | L101: =IF(I101="已计入",ROUND(K100*C101,2),"") -> 65140.82 | M101: =IF(I101="已计入",IF(B101="卖出",MAX(0,L101-Q100-F101),IF(B101="现金分红",MAX(0,L101+E101-Q100),0)),"") -> 0 | N101: =IF(I101="已计入",IF(AND(B101="卖出",持仓总览!$C$7="本金优先"),MAX(0,E101-Q100),IF(OR(B101="卖出",B101="现金分红"),MIN(E101,M101),0)),"") -> 0 | O101: =IF(I101="已计入",IF(OR(B101="卖出",B101="现金分红"),MIN(Q100,MAX(0,E101-N101)),0),"") -> 0 | P101: =IF(I101="已计入",IF(AND(B101="卖出",K101=0),MAX(0,Q100-O101),0),"") -> 0 | Q101: =IF(AA101="正常",IF(I101="已计入",ROUND(Q100+IF(OR(B101="买入",B101="定投",B101="转换转入"),E101,0)-O101-P101,2),Q100),"") -> 51206.01 | R101: =IF(I101="已计入",ROUND(K101*C101,2),"") -> 65340.53 | S101: =IF(I101="已计入",ROUND(R101-Q101,2),"") -> 14134.52 | T101: =IF(I101="已计入",IF(Q101=0,"",S101/Q101),"") -> 0.27603244 | U101: =IF(AA101="正常",U100+IF(AND(I101="已计入",OR(B101="买入",B101="定投",B101="转换转入")),E101,0),"") -> 51206.01 | V101: =IF(AA101="正常",V100+IF(AND(I101="已计入",OR(B101="卖出",B101="现金分红")),E101,0),"") -> 0 | W101: =IF(AA101="正常",W100+IF(I101="已计入",N101,0),"") -> 0 | X101: =IF(AA101="正常",X100+IF(I101="已计入",P101,0),"") -> 0 | Y101: =IF(I101="已计入",ROUND(R101+V101-U101,2),"") -> 14134.52 | Z101: =IF(AA101="正常",IF(I101="已计入",A101,Z100),"") -> 46226 | AA101: =IF(OR(AA100="错误",AND(I101<>"",I101<>"已排除",I101<>"待确认",I101<>"已计入")),"错误","正常") -> 正常 | AB101: =IF(AA101="正常",IF(I101="已计入",C101,AB100),"") -> 2.8739
A102: 46227 | B102: 定投 | C102: 2.7838 | D102: 71.74 | E102: 200 | F102: 0.3 | G102: 历史估算 | H102: 原下单 2026-07-24T12:03:05 份额、费用及净值日沿用旧表估算 | I102: =IF(COUNTA(A102:H102)=0,"",IF(OR(OR(OR(G102="撤单",G102="交易失败",G102="交易关闭"),G102="交易失败",G102="交易关闭"),G102="交易失败",G102="交易关闭"),"已排除",IF(G102="待确认","待确认",IF(NOT(OR(G102="已确认",G102="历史估算")),"请选择确认状态",IF(NOT(ISNUMBER(A102)),"缺少有效净值日期",IF(OR(A102<=0,A102<>INT(A102)),"净值日期无效",IF(NOT(OR(OR(B102="买入",B102="定投",B102="转换转入"),B102="卖出",B102="现金分红",B102="红利再投")),"请选择交易类型",IF(NOT(ISNUMBER(C102)),"缺少成交净值",IF(C102<=0,"成交净值须大于零",IF(NOT(ISNUMBER(D102)),"缺少确认份额（分红填0）",IF(NOT(ISNUMBER(E102)),"缺少确认金额（再投填0）",IF(NOT(ISNUMBER(F102)),"缺少手续费（无费用填0）",IF(OR(D102<0,E102<0,F102<0),"份额金额费用不能为负",IF(AA101="错误","前行待修正",IF(A102<Z101,"日期需按成交顺序递增",IF(AND(B102="现金分红",OR(D102<>0,E102<=0,F102<>0)),"分红填份额0、费用0、正金额",IF(AND(B102="红利再投",OR(D102<=0,E102<>0,F102<>0)),"再投填正份额、金额0、费用0",IF(AND(OR(B102="现金分红",B102="红利再投"),K101<=0),"分红或再投前须有持仓",IF(AND(OR(OR(B102="买入",B102="定投",B102="转换转入"),B102="卖出"),OR(D102<=0,E102<=0)),"买卖须填正份额、正金额",IF(AND(B102="卖出",D102>K101+0.000001),"卖出份额超过持仓",IF(AND(OR(B102="买入",B102="定投",B102="转换转入"),F102>=E102),"申购费不能达到总支出",IF(NOT(ISNUMBER(持仓总览!$H$6)),"请填写金额核对容差",IF(持仓总览!$H$6<0,"金额核对容差不能为负",IF(NOT(OR(持仓总览!$C$7="利润优先",持仓总览!$C$7="本金优先")),"请选择卖出分配模式",IF(AND(OR(B102="买入",B102="定投",B102="转换转入"),ABS(E102-F102-C102*D102)>持仓总览!$H$6),"买入金额与份额净值不符",IF(AND(B102="卖出",ABS(E102+F102-C102*D102)>持仓总览!$H$6),"到账加费用与赎回市值不符","已计入")))))))))))))))))))))))))) -> 已计入 | J102: =IF(AA102="正常",IF(I102="已计入",IF(OR(OR(B102="买入",B102="定投",B102="转换转入"),B102="红利再投"),D102,IF(B102="卖出",-D102,0)),0),"") -> 71.74 | K102: =IF(AA102="正常",ROUND(K101+J102,6),"") -> 22807.58 | L102: =IF(I102="已计入",ROUND(K101*C102,2),"") -> 63292.03 | M102: =IF(I102="已计入",IF(B102="卖出",MAX(0,L102-Q101-F102),IF(B102="现金分红",MAX(0,L102+E102-Q101),0)),"") -> 0 | N102: =IF(I102="已计入",IF(AND(B102="卖出",持仓总览!$C$7="本金优先"),MAX(0,E102-Q101),IF(OR(B102="卖出",B102="现金分红"),MIN(E102,M102),0)),"") -> 0 | O102: =IF(I102="已计入",IF(OR(B102="卖出",B102="现金分红"),MIN(Q101,MAX(0,E102-N102)),0),"") -> 0 | P102: =IF(I102="已计入",IF(AND(B102="卖出",K102=0),MAX(0,Q101-O102),0),"") -> 0 | Q102: =IF(AA102="正常",IF(I102="已计入",ROUND(Q101+IF(OR(B102="买入",B102="定投",B102="转换转入"),E102,0)-O102-P102,2),Q101),"") -> 51406.01 | R102: =IF(I102="已计入",ROUND(K102*C102,2),"") -> 63491.74 | S102: =IF(I102="已计入",ROUND(R102-Q102,2),"") -> 12085.73 | T102: =IF(I102="已计入",IF(Q102=0,"",S102/Q102),"") -> 0.23510344 | U102: =IF(AA102="正常",U101+IF(AND(I102="已计入",OR(B102="买入",B102="定投",B102="转换转入")),E102,0),"") -> 51406.01 | V102: =IF(AA102="正常",V101+IF(AND(I102="已计入",OR(B102="卖出",B102="现金分红")),E102,0),"") -> 0 | W102: =IF(AA102="正常",W101+IF(I102="已计入",N102,0),"") -> 0 | X102: =IF(AA102="正常",X101+IF(I102="已计入",P102,0),"") -> 0 | Y102: =IF(I102="已计入",ROUND(R102+V102-U102,2),"") -> 12085.73 | Z102: =IF(AA102="正常",IF(I102="已计入",A102,Z101),"") -> 46227 | AA102: =IF(OR(AA101="错误",AND(I102<>"",I102<>"已排除",I102<>"待确认",I102<>"已计入")),"错误","正常") -> 正常 | AB102: =IF(AA102="正常",IF(I102="已计入",C102,AB101),"") -> 2.7838
A103: 46230 | B103: 定投 | C103: 2.7755 | D103: 71.95 | E103: 200 | F103: 0.3 | G103: 历史估算 | H103: 原下单 2026-07-27T12:20:11 份额、费用及净值日沿用旧表估算 | I103: =IF(COUNTA(A103:H103)=0,"",IF(OR(OR(OR(G103="撤单",G103="交易失败",G103="交易关闭"),G103="交易失败",G103="交易关闭"),G103="交易失败",G103="交易关闭"),"已排除",IF(G103="待确认","待确认",IF(NOT(OR(G103="已确认",G103="历史估算")),"请选择确认状态",IF(NOT(ISNUMBER(A103)),"缺少有效净值日期",IF(OR(A103<=0,A103<>INT(A103)),"净值日期无效",IF(NOT(OR(OR(B103="买入",B103="定投",B103="转换转入"),B103="卖出",B103="现金分红",B103="红利再投")),"请选择交易类型",IF(NOT(ISNUMBER(C103)),"缺少成交净值",IF(C103<=0,"成交净值须大于零",IF(NOT(ISNUMBER(D103)),"缺少确认份额（分红填0）",IF(NOT(ISNUMBER(E103)),"缺少确认金额（再投填0）",IF(NOT(ISNUMBER(F103)),"缺少手续费（无费用填0）",IF(OR(D103<0,E103<0,F103<0),"份额金额费用不能为负",IF(AA102="错误","前行待修正",IF(A103<Z102,"日期需按成交顺序递增",IF(AND(B103="现金分红",OR(D103<>0,E103<=0,F103<>0)),"分红填份额0、费用0、正金额",IF(AND(B103="红利再投",OR(D103<=0,E103<>0,F103<>0)),"再投填正份额、金额0、费用0",IF(AND(OR(B103="现金分红",B103="红利再投"),K102<=0),"分红或再投前须有持仓",IF(AND(OR(OR(B103="买入",B103="定投",B103="转换转入"),B103="卖出"),OR(D103<=0,E103<=0)),"买卖须填正份额、正金额",IF(AND(B103="卖出",D103>K102+0.000001),"卖出份额超过持仓",IF(AND(OR(B103="买入",B103="定投",B103="转换转入"),F103>=E103),"申购费不能达到总支出",IF(NOT(ISNUMBER(持仓总览!$H$6)),"请填写金额核对容差",IF(持仓总览!$H$6<0,"金额核对容差不能为负",IF(NOT(OR(持仓总览!$C$7="利润优先",持仓总览!$C$7="本金优先")),"请选择卖出分配模式",IF(AND(OR(B103="买入",B103="定投",B103="转换转入"),ABS(E103-F103-C103*D103)>持仓总览!$H$6),"买入金额与份额净值不符",IF(AND(B103="卖出",ABS(E103+F103-C103*D103)>持仓总览!$H$6),"到账加费用与赎回市值不符","已计入")))))))))))))))))))))))))) -> 已计入 | J103: =IF(AA103="正常",IF(I103="已计入",IF(OR(OR(B103="买入",B103="定投",B103="转换转入"),B103="红利再投"),D103,IF(B103="卖出",-D103,0)),0),"") -> 71.95 | K103: =IF(AA103="正常",ROUND(K102+J103,6),"") -> 22879.53 | L103: =IF(I103="已计入",ROUND(K102*C103,2),"") -> 63302.44 | M103: =IF(I103="已计入",IF(B103="卖出",MAX(0,L103-Q102-F103),IF(B103="现金分红",MAX(0,L103+E103-Q102),0)),"") -> 0 | N103: =IF(I103="已计入",IF(AND(B103="卖出",持仓总览!$C$7="本金优先"),MAX(0,E103-Q102),IF(OR(B103="卖出",B103="现金分红"),MIN(E103,M103),0)),"") -> 0 | O103: =IF(I103="已计入",IF(OR(B103="卖出",B103="现金分红"),MIN(Q102,MAX(0,E103-N103)),0),"") -> 0 | P103: =IF(I103="已计入",IF(AND(B103="卖出",K103=0),MAX(0,Q102-O103),0),"") -> 0 | Q103: =IF(AA103="正常",IF(I103="已计入",ROUND(Q102+IF(OR(B103="买入",B103="定投",B103="转换转入"),E103,0)-O103-P103,2),Q102),"") -> 51606.01 | R103: =IF(I103="已计入",ROUND(K103*C103,2),"") -> 63502.14 | S103: =IF(I103="已计入",ROUND(R103-Q103,2),"") -> 11896.13 | T103: =IF(I103="已计入",IF(Q103=0,"",S103/Q103),"") -> 0.23051831 | U103: =IF(AA103="正常",U102+IF(AND(I103="已计入",OR(B103="买入",B103="定投",B103="转换转入")),E103,0),"") -> 51606.01 | V103: =IF(AA103="正常",V102+IF(AND(I103="已计入",OR(B103="卖出",B103="现金分红")),E103,0),"") -> 0 | W103: =IF(AA103="正常",W102+IF(I103="已计入",N103,0),"") -> 0 | X103: =IF(AA103="正常",X102+IF(I103="已计入",P103,0),"") -> 0 | Y103: =IF(I103="已计入",ROUND(R103+V103-U103,2),"") -> 11896.13 | Z103: =IF(AA103="正常",IF(I103="已计入",A103,Z102),"") -> 46230 | AA103: =IF(OR(AA102="错误",AND(I103<>"",I103<>"已排除",I103<>"待确认",I103<>"已计入")),"错误","正常") -> 正常 | AB103: =IF(AA103="正常",IF(I103="已计入",C103,AB102),"") -> 2.7755
A104: 46231 | B104: 定投 | C104: 2.5659 | D104: 77.83 | E104: 200 | F104: 0.3 | G104: 历史估算 | H104: 原下单 2026-07-28T12:05:31 份额、费用及净值日沿用旧表估算 | I104: =IF(COUNTA(A104:H104)=0,"",IF(OR(OR(OR(G104="撤单",G104="交易失败",G104="交易关闭"),G104="交易失败",G104="交易关闭"),G104="交易失败",G104="交易关闭"),"已排除",IF(G104="待确认","待确认",IF(NOT(OR(G104="已确认",G104="历史估算")),"请选择确认状态",IF(NOT(ISNUMBER(A104)),"缺少有效净值日期",IF(OR(A104<=0,A104<>INT(A104)),"净值日期无效",IF(NOT(OR(OR(B104="买入",B104="定投",B104="转换转入"),B104="卖出",B104="现金分红",B104="红利再投")),"请选择交易类型",IF(NOT(ISNUMBER(C104)),"缺少成交净值",IF(C104<=0,"成交净值须大于零",IF(NOT(ISNUMBER(D104)),"缺少确认份额（分红填0）",IF(NOT(ISNUMBER(E104)),"缺少确认金额（再投填0）",IF(NOT(ISNUMBER(F104)),"缺少手续费（无费用填0）",IF(OR(D104<0,E104<0,F104<0),"份额金额费用不能为负",IF(AA103="错误","前行待修正",IF(A104<Z103,"日期需按成交顺序递增",IF(AND(B104="现金分红",OR(D104<>0,E104<=0,F104<>0)),"分红填份额0、费用0、正金额",IF(AND(B104="红利再投",OR(D104<=0,E104<>0,F104<>0)),"再投填正份额、金额0、费用0",IF(AND(OR(B104="现金分红",B104="红利再投"),K103<=0),"分红或再投前须有持仓",IF(AND(OR(OR(B104="买入",B104="定投",B104="转换转入"),B104="卖出"),OR(D104<=0,E104<=0)),"买卖须填正份额、正金额",IF(AND(B104="卖出",D104>K103+0.000001),"卖出份额超过持仓",IF(AND(OR(B104="买入",B104="定投",B104="转换转入"),F104>=E104),"申购费不能达到总支出",IF(NOT(ISNUMBER(持仓总览!$H$6)),"请填写金额核对容差",IF(持仓总览!$H$6<0,"金额核对容差不能为负",IF(NOT(OR(持仓总览!$C$7="利润优先",持仓总览!$C$7="本金优先")),"请选择卖出分配模式",IF(AND(OR(B104="买入",B104="定投",B104="转换转入"),ABS(E104-F104-C104*D104)>持仓总览!$H$6),"买入金额与份额净值不符",IF(AND(B104="卖出",ABS(E104+F104-C104*D104)>持仓总览!$H$6),"到账加费用与赎回市值不符","已计入")))))))))))))))))))))))))) -> 已计入 | J104: =IF(AA104="正常",IF(I104="已计入",IF(OR(OR(B104="买入",B104="定投",B104="转换转入"),B104="红利再投"),D104,IF(B104="卖出",-D104,0)),0),"") -> 77.83 | K104: =IF(AA104="正常",ROUND(K103+J104,6),"") -> 22957.36 | L104: =IF(I104="已计入",ROUND(K103*C104,2),"") -> 58706.59 | M104: =IF(I104="已计入",IF(B104="卖出",MAX(0,L104-Q103-F104),IF(B104="现金分红",MAX(0,L104+E104-Q103),0)),"") -> 0 | N104: =IF(I104="已计入",IF(AND(B104="卖出",持仓总览!$C$7="本金优先"),MAX(0,E104-Q103),IF(OR(B104="卖出",B104="现金分红"),MIN(E104,M104),0)),"") -> 0 | O104: =IF(I104="已计入",IF(OR(B104="卖出",B104="现金分红"),MIN(Q103,MAX(0,E104-N104)),0),"") -> 0 | P104: =IF(I104="已计入",IF(AND(B104="卖出",K104=0),MAX(0,Q103-O104),0),"") -> 0 | Q104: =IF(AA104="正常",IF(I104="已计入",ROUND(Q103+IF(OR(B104="买入",B104="定投",B104="转换转入"),E104,0)-O104-P104,2),Q103),"") -> 51806.01 | R104: =IF(I104="已计入",ROUND(K104*C104,2),"") -> 58906.29 | S104: =IF(I104="已计入",ROUND(R104-Q104,2),"") -> 7100.28 | T104: =IF(I104="已计入",IF(Q104=0,"",S104/Q104),"") -> 0.13705514 | U104: =IF(AA104="正常",U103+IF(AND(I104="已计入",OR(B104="买入",B104="定投",B104="转换转入")),E104,0),"") -> 51806.01 | V104: =IF(AA104="正常",V103+IF(AND(I104="已计入",OR(B104="卖出",B104="现金分红")),E104,0),"") -> 0 | W104: =IF(AA104="正常",W103+IF(I104="已计入",N104,0),"") -> 0 | X104: =IF(AA104="正常",X103+IF(I104="已计入",P104,0),"") -> 0 | Y104: =IF(I104="已计入",ROUND(R104+V104-U104,2),"") -> 7100.28 | Z104: =IF(AA104="正常",IF(I104="已计入",A104,Z103),"") -> 46231 | AA104: =IF(OR(AA103="错误",AND(I104<>"",I104<>"已排除",I104<>"待确认",I104<>"已计入")),"错误","正常") -> 正常 | AB104: =IF(AA104="正常",IF(I104="已计入",C104,AB103),"") -> 2.5659
... A116: 46247 | B116: 定投 | C116: 2.7686 | D116: 1803.26 | E116: 5000 | F116: 7.5 | G116: 历史估算 | H116: 原下单 2026-08-13T11:57:52 份额、费用及净值日沿用旧表估算 | I116: =IF(COUNTA(A116:H116)=0,"",IF(OR(OR(OR(G116="撤单",G116="交易失败",G116="交易关闭"),G116="交易失败",G116="交易关闭"),G116="交易失败",G116="交易关闭"),"已排除",IF(G116="待确认","待确认",IF(NOT(OR(G116="已确认",G116="历史估算")),"请选择确认状态",IF(NOT(ISNUMBER(A116)),"缺少有效净值日期",IF(OR(A116<=0,A116<>INT(A116)),"净值日期无效",IF(NOT(OR(OR(B116="买入",B116="定投",B116="转换转入"),B116="卖出",B116="现金分红",B116="红利再投")),"请选择交易类型",IF(NOT(ISNUMBER(C116)),"缺少成交净值",IF(C116<=0,"成交净值须大于零",IF(NOT(ISNUMBER(D116)),"缺少确认份额（分红填0）",IF(NOT(ISNUMBER(E116)),"缺少确认金额（再投填0）",IF(NOT(ISNUMBER(F116)),"缺少手续费（无费用填0）",IF(OR(D116<0,E116<0,F116<0),"份额金额费用不能为负",IF(AA115="错误","前行待修正",IF(A116<Z115,"日期需按成交顺序递增",IF(AND(B116="现金分红",OR(D116<>0,E116<=0,F116<>0)),"分红填份额0、费用0、正金额",IF(AND(B116="红利再投",OR(D116<=0,E116<>0,F116<>0)),"再投填正份额、金额0、费用0",IF(AND(OR(B116="现金分红",B116="红利再投"),K115<=0),"分红或再投前须有持仓",IF(AND(OR(OR(B116="买入",B116="定投",B116="转换转入"),B116="卖出"),OR(D116<=0,E116<=0)),"买卖须填正份额、正金额",IF(AND(B116="卖出",D116>K115+0.000001),"卖出份额超过持仓",IF(AND(OR(B116="买入",B116="定投",B116="转换转入"),F116>=E116),"申购费不能达到总支出",IF(NOT(ISNUMBER(持仓总览!$H$6)),"请填写金额核对容差",IF(持仓总览!$H$6<0,"金额核对容差不能为负",IF(NOT(OR(持仓总览!$C$7="利润优先",持仓总览!$C$7="本金优先")),"请选择卖出分配模式",IF(AND(OR(B116="买入",B116="定投",B116="转换转入"),ABS(E116-F116-C116*D116)>持仓总览!$H$6),"买入金额与份额净值不符",IF(AND(B116="卖出",ABS(E116+F116-C116*D116)>持仓总览!$H$6),"到账加费用与赎回市值不符","已计入")))))))))))))))))))))))))) -> 已计入 | J116: =IF(AA116="正常",IF(I116="已计入",IF(OR(OR(B116="买入",B116="定投",B116="转换转入"),B116="红利再投"),D116,IF(B116="卖出",-D116,0)),0),"") -> 1803.26 | K116: =IF(AA116="正常",ROUND(K115+J116,6),"") -> 34284.43 | L116: =IF(I116="已计入",ROUND(K115*C116,2),"") -> 89927.37 | M116: =IF(I116="已计入",IF(B116="卖出",MAX(0,L116-Q115-F116),IF(B116="现金分红",MAX(0,L116+E116-Q115),0)),"") -> 0 | N116: =IF(I116="已计入",IF(AND(B116="卖出",持仓总览!$C$7="本金优先"),MAX(0,E116-Q115),IF(OR(B116="卖出",B116="现金分红"),MIN(E116,M116),0)),"") -> 0 | O116: =IF(I116="已计入",IF(OR(B116="卖出",B116="现金分红"),MIN(Q115,MAX(0,E116-N116)),0),"") -> 0 | P116: =IF(I116="已计入",IF(AND(B116="卖出",K116=0),MAX(0,Q115-O116),0),"") -> 0 | Q116: =IF(AA116="正常",IF(I116="已计入",ROUND(Q115+IF(OR(B116="买入",B116="定投",B116="转换转入"),E116,0)-O116-P116,2),Q115),"") -> 82516.01 | R116: =IF(I116="已计入",ROUND(K116*C116,2),"") -> 94919.87 | S116: =IF(I116="已计入",ROUND(R116-Q116,2),"") -> 12403.86 | T116: =IF(I116="已计入",IF(Q116=0,"",S116/Q116),"") -> 0.15032065 | U116: =IF(AA116="正常",U115+IF(AND(I116="已计入",OR(B116="买入",B116="定投",B116="转换转入")),E116,0),"") -> 82516.01 | V116: =IF(AA116="正常",V115+IF(AND(I116="已计入",OR(B116="卖出",B116="现金分红")),E116,0),"") -> 0 | W116: =IF(AA116="正常",W115+IF(I116="已计入",N116,0),"") -> 0 | X116: =IF(AA116="正常",X115+IF(I116="已计入",P116,0),"") -> 0 | Y116: =IF(I116="已计入",ROUND(R116+V116-U116,2),"") -> 12403.86 | Z116: =IF(AA116="正常",IF(I116="已计入",A116,Z115),"") -> 46247 | AA116: =IF(OR(AA115="错误",AND(I116<>"",I116<>"已排除",I116<>"待确认",I116<>"已计入")),"错误","正常") -> 正常 | AB116: =IF(AA116="正常",IF(I116="已计入",C116,AB115),"") -> 2.7686
E117: =IF(AND(ISNUMBER(C117),ISNUMBER(D117),ISNUMBER(F117)),IF(OR(B117="买入",B117="定投"),ROUND(C117*D117+F117,2),IF(B117="卖出",ROUND(C117*D117-F117,2),IF(B117="红利再投",0,""))),"") | G117: =IF(COUNTA(A117:D117,F117)=0,"",IF(I117="已计入","已录入","待修正")) | H117: =IF(COUNTA(A117:D117,F117)=0,"",IF(B117="红利再投","仅增加份额，不增加现金投入","金额由份额、净值和手续费推算")) | I117: =IF(COUNTA(A117:D117,F117)=0,"",IF(NOT(ISNUMBER(A117)),"缺少有效净值日期",IF(OR(A117<=0,A117<>INT(A117)),"净值日期无效",IF(OR(B117="转换转入",B117="现金分红"),"该类型需实际金额，五项录入不适用",IF(NOT(OR(OR(B117="买入",B117="定投"),B117="卖出",B117="红利再投")),"请选择交易类型",IF(NOT(ISNUMBER(C117)),"缺少成交净值",IF(C117<=0,"成交净值须大于零",IF(NOT(ISNUMBER(D117)),"缺少确认份额",IF(D117<=0,"确认份额须大于零",IF(NOT(ISNUMBER(F117)),"缺少手续费，无费用请填 0",IF(F117<0,"手续费不能为负",IF(AA116="错误","前行待修正",IF(A117<Z116,"日期需按成交顺序递增",IF(AND(B117="红利再投",F117<>0),"红利再投手续费应填 0",IF(AND(B117="红利再投",K116<=0),"红利再投前须有持仓",IF(AND(B117="卖出",D117>K116+0.000001),"卖出份额超过持仓",IF(AND(B117="卖出",F117>=C117*D117),"赎回费不能达到赎回总额",IF(NOT(ISNUMBER(E117)),"自动金额未生成，请检查五项输入",IF(NOT(OR(持仓总览!$C$7="利润优先",持仓总览!$C$7="本金优先")),"请选择卖出分配模式","已计入"))))))))))))))))))) | J117: =IF(AA117="正常",IF(I117="已计入",IF(OR(OR(B117="买入",B117="定投",B117="转换转入"),B117="红利再投"),D117,IF(B117="卖出",-D117,0)),0),"") -> 0 | K117: =IF(AA117="正常",ROUND(K116+J117,6),"") -> 34284.43 | L117: =IF(I117="已计入",ROUND(K116*C117,2),"") | M117: =IF(I117="已计入",IF(B117="卖出",MAX(0,L117-Q116-F117),IF(B117="现金分红",MAX(0,L117+E117-Q116),0)),"") | N117: =IF(I117="已计入",IF(AND(B117="卖出",持仓总览!$C$7="本金优先"),MAX(0,E117-Q116),IF(OR(B117="卖出",B117="现金分红"),MIN(E117,M117),0)),"") | O117: =IF(I117="已计入",IF(OR(B117="卖出",B117="现金分红"),MIN(Q116,MAX(0,E117-N117)),0),"") | P117: =IF(I117="已计入",IF(AND(B117="卖出",K117=0),MAX(0,Q116-O117),0),"") | Q117: =IF(AA117="正常",IF(I117="已计入",ROUND(Q116+IF(OR(B117="买入",B117="定投",B117="转换转入"),E117,0)-O117-P117,2),Q116),"") -> 82516.01 | R117: =IF(I117="已计入",ROUND(K117*C117,2),"") | S117: =IF(I117="已计入",ROUND(R117-Q117,2),"") | T117: =IF(I117="已计入",IF(Q117=0,"",S117/Q117),"") | U117: =IF(AA117="正常",U116+IF(AND(I117="已计入",OR(B117="买入",B117="定投",B117="转换转入")),E117,0),"") -> 82516.01 | V117: =IF(AA117="正常",V116+IF(AND(I117="已计入",OR(B117="卖出",B117="现金分红")),E117,0),"") -> 0 | W117: =IF(AA117="正常",W116+IF(I117="已计入",N117,0),"") -> 0 | X117: =IF(AA117="正常",X116+IF(I117="已计入",P117,0),"") -> 0 | Y117: =IF(I117="已计入",ROUND(R117+V117-U117,2),"") | Z117: =IF(AA117="正常",IF(I117="已计入",A117,Z116),"") -> 46247 | AA117: =IF(OR(AA116="错误",AND(I117<>"",I117<>"已排除",I117<>"待确认",I117<>"已计入")),"错误","正常") -> 正常 | AB117: =IF(AA117="正常",IF(I117="已计入",C117,AB116),"") -> 2.7686
E118: =IF(AND(ISNUMBER(C118),ISNUMBER(D118),ISNUMBER(F118)),IF(OR(B118="买入",B118="定投"),ROUND(C118*D118+F118,2),IF(B118="卖出",ROUND(C118*D118-F118,2),IF(B118="红利再投",0,""))),"") | G118: =IF(COUNTA(A118:D118,F118)=0,"",IF(I118="已计入","已录入","待修正")) | H118: =IF(COUNTA(A118:D118,F118)=0,"",IF(B118="红利再投","仅增加份额，不增加现金投入","金额由份额、净值和手续费推算")) | I118: =IF(COUNTA(A118:D118,F118)=0,"",IF(NOT(ISNUMBER(A118)),"缺少有效净值日期",IF(OR(A118<=0,A118<>INT(A118)),"净值日期无效",IF(OR(B118="转换转入",B118="现金分红"),"该类型需实际金额，五项录入不适用",IF(NOT(OR(OR(B118="买入",B118="定投"),B118="卖出",B118="红利再投")),"请选择交易类型",IF(NOT(ISNUMBER(C118)),"缺少成交净值",IF(C118<=0,"成交净值须大于零",IF(NOT(ISNUMBER(D118)),"缺少确认份额",IF(D118<=0,"确认份额须大于零",IF(NOT(ISNUMBER(F118)),"缺少手续费，无费用请填 0",IF(F118<0,"手续费不能为负",IF(AA117="错误","前行待修正",IF(A118<Z117,"日期需按成交顺序递增",IF(AND(B118="红利再投",F118<>0),"红利再投手续费应填 0",IF(AND(B118="红利再投",K117<=0),"红利再投前须有持仓",IF(AND(B118="卖出",D118>K117+0.000001),"卖出份额超过持仓",IF(AND(B118="卖出",F118>=C118*D118),"赎回费不能达到赎回总额",IF(NOT(ISNUMBER(E118)),"自动金额未生成，请检查五项输入",IF(NOT(OR(持仓总览!$C$7="利润优先",持仓总览!$C$7="本金优先")),"请选择卖出分配模式","已计入"))))))))))))))))))) | J118: =IF(AA118="正常",IF(I118="已计入",IF(OR(OR(B118="买入",B118="定投",B118="转换转入"),B118="红利再投"),D118,IF(B118="卖出",-D118,0)),0),"") -> 0 | K118: =IF(AA118="正常",ROUND(K117+J118,6),"") -> 34284.43 | L118: =IF(I118="已计入",ROUND(K117*C118,2),"") | M118: =IF(I118="已计入",IF(B118="卖出",MAX(0,L118-Q117-F118),IF(B118="现金分红",MAX(0,L118+E118-Q117),0)),"") | N118: =IF(I118="已计入",IF(AND(B118="卖出",持仓总览!$C$7="本金优先"),MAX(0,E118-Q117),IF(OR(B118="卖出",B118="现金分红"),MIN(E118,M118),0)),"") | O118: =IF(I118="已计入",IF(OR(B118="卖出",B118="现金分红"),MIN(Q117,MAX(0,E118-N118)),0),"") | P118: =IF(I118="已计入",IF(AND(B118="卖出",K118=0),MAX(0,Q117-O118),0),"") | Q118: =IF(AA118="正常",IF(I118="已计入",ROUND(Q117+IF(OR(B118="买入",B118="定投",B118="转换转入"),E118,0)-O118-P118,2),Q117),"") -> 82516.01 | R118: =IF(I118="已计入",ROUND(K118*C118,2),"") | S118: =IF(I118="已计入",ROUND(R118-Q118,2),"") | T118: =IF(I118="已计入",IF(Q118=0,"",S118/Q118),"") | U118: =IF(AA118="正常",U117+IF(AND(I118="已计入",OR(B118="买入",B118="定投",B118="转换转入")),E118,0),"") -> 82516.01 | V118: =IF(AA118="正常",V117+IF(AND(I118="已计入",OR(B118="卖出",B118="现金分红")),E118,0),"") -> 0 | W118: =IF(AA118="正常",W117+IF(I118="已计入",N118,0),"") -> 0 | X118: =IF(AA118="正常",X117+IF(I118="已计入",P118,0),"") -> 0 | Y118: =IF(I118="已计入",ROUND(R118+V118-U118,2),"") | Z118: =IF(AA118="正常",IF(I118="已计入",A118,Z117),"") -> 46247 | AA118: =IF(OR(AA117="错误",AND(I118<>"",I118<>"已排除",I118<>"待确认",I118<>"已计入")),"错误","正常") -> 正常 | AB118: =IF(AA118="正常",IF(I118="已计入",C118,AB117),"") -> 2.7686
E119: =IF(AND(ISNUMBER(C119),ISNUMBER(D119),ISNUMBER(F119)),IF(OR(B119="买入",B119="定投"),ROUND(C119*D119+F119,2),IF(B119="卖出",ROUND(C119*D119-F119,2),IF(B119="红利再投",0,""))),"") | G119: =IF(COUNTA(A119:D119,F119)=0,"",IF(I119="已计入","已录入","待修正")) | H119: =IF(COUNTA(A119:D119,F119)=0,"",IF(B119="红利再投","仅增加份额，不增加现金投入","金额由份额、净值和手续费推算")) | I119: =IF(COUNTA(A119:D119,F119)=0,"",IF(NOT(ISNUMBER(A119)),"缺少有效净值日期",IF(OR(A119<=0,A119<>INT(A119)),"净值日期无效",IF(OR(B119="转换转入",B119="现金分红"),"该类型需实际金额，五项录入不适用",IF(NOT(OR(OR(B119="买入",B119="定投"),B119="卖出",B119="红利再投")),"请选择交易类型",IF(NOT(ISNUMBER(C119)),"缺少成交净值",IF(C119<=0,"成交净值须大于零",IF(NOT(ISNUMBER(D119)),"缺少确认份额",IF(D119<=0,"确认份额须大于零",IF(NOT(ISNUMBER(F119)),"缺少手续费，无费用请填 0",IF(F119<0,"手续费不能为负",IF(AA118="错误","前行待修正",IF(A119<Z118,"日期需按成交顺序递增",IF(AND(B119="红利再投",F119<>0),"红利再投手续费应填 0",IF(AND(B119="红利再投",K118<=0),"红利再投前须有持仓",IF(AND(B119="卖出",D119>K118+0.000001),"卖出份额超过持仓",IF(AND(B119="卖出",F119>=C119*D119),"赎回费不能达到赎回总额",IF(NOT(ISNUMBER(E119)),"自动金额未生成，请检查五项输入",IF(NOT(OR(持仓总览!$C$7="利润优先",持仓总览!$C$7="本金优先")),"请选择卖出分配模式","已计入"))))))))))))))))))) | J119: =IF(AA119="正常",IF(I119="已计入",IF(OR(OR(B119="买入",B119="定投",B119="转换转入"),B119="红利再投"),D119,IF(B119="卖出",-D119,0)),0),"") -> 0 | K119: =IF(AA119="正常",ROUND(K118+J119,6),"") -> 34284.43 | L119: =IF(I119="已计入",ROUND(K118*C119,2),"") | M119: =IF(I119="已计入",IF(B119="卖出",MAX(0,L119-Q118-F119),IF(B119="现金分红",MAX(0,L119+E119-Q118),0)),"") | N119: =IF(I119="已计入",IF(AND(B119="卖出",持仓总览!$C$7="本金优先"),MAX(0,E119-Q118),IF(OR(B119="卖出",B119="现金分红"),MIN(E119,M119),0)),"") | O119: =IF(I119="已计入",IF(OR(B119="卖出",B119="现金分红"),MIN(Q118,MAX(0,E119-N119)),0),"") | P119: =IF(I119="已计入",IF(AND(B119="卖出",K119=0),MAX(0,Q118-O119),0),"") | Q119: =IF(AA119="正常",IF(I119="已计入",ROUND(Q118+IF(OR(B119="买入",B119="定投",B119="转换转入"),E119,0)-O119-P119,2),Q118),"") -> 82516.01 | R119: =IF(I119="已计入",ROUND(K119*C119,2),"") | S119: =IF(I119="已计入",ROUND(R119-Q119,2),"") | T119: =IF(I119="已计入",IF(Q119=0,"",S119/Q119),"") | U119: =IF(AA119="正常",U118+IF(AND(I119="已计入",OR(B119="买入",B119="定投",B119="转换转入")),E119,0),"") -> 82516.01 | V119: =IF(AA119="正常",V118+IF(AND(I119="已计入",OR(B119="卖出",B119="现金分红")),E119,0),"") -> 0 | W119: =IF(AA119="正常",W118+IF(I119="已计入",N119,0),"") -> 0 | X119: =IF(AA119="正常",X118+IF(I119="已计入",P119,0),"") -> 0 | Y119: =IF(I119="已计入",ROUND(R119+V119-U119,2),"") | Z119: =IF(AA119="正常",IF(I119="已计入",A119,Z118),"") -> 46247 | AA119: =IF(OR(AA118="错误",AND(I119<>"",I119<>"已排除",I119<>"待确认",I119<>"已计入")),"错误","正常") -> 正常 | AB119: =IF(AA119="正常",IF(I119="已计入",C119,AB118),"") -> 2.7686
E120: =IF(AND(ISNUMBER(C120),ISNUMBER(D120),ISNUMBER(F120)),IF(OR(B120="买入",B120="定投"),ROUND(C120*D120+F120,2),IF(B120="卖出",ROUND(C120*D120-F120,2),IF(B120="红利再投",0,""))),"") | G120: =IF(COUNTA(A120:D120,F120)=0,"",IF(I120="已计入","已录入","待修正")) | H120: =IF(COUNTA(A120:D120,F120)=0,"",IF(B120="红利再投","仅增加份额，不增加现金投入","金额由份额、净值和手续费推算")) | I120: =IF(COUNTA(A120:D120,F120)=0,"",IF(NOT(ISNUMBER(A120)),"缺少有效净值日期",IF(OR(A120<=0,A120<>INT(A120)),"净值日期无效",IF(OR(B120="转换转入",B120="现金分红"),"该类型需实际金额，五项录入不适用",IF(NOT(OR(OR(B120="买入",B120="定投"),B120="卖出",B120="红利再投")),"请选择交易类型",IF(NOT(ISNUMBER(C120)),"缺少成交净值",IF(C120<=0,"成交净值须大于零",IF(NOT(ISNUMBER(D120)),"缺少确认份额",IF(D120<=0,"确认份额须大于零",IF(NOT(ISNUMBER(F120)),"缺少手续费，无费用请填 0",IF(F120<0,"手续费不能为负",IF(AA119="错误","前行待修正",IF(A120<Z119,"日期需按成交顺序递增",IF(AND(B120="红利再投",F120<>0),"红利再投手续费应填 0",IF(AND(B120="红利再投",K119<=0),"红利再投前须有持仓",IF(AND(B120="卖出",D120>K119+0.000001),"卖出份额超过持仓",IF(AND(B120="卖出",F120>=C120*D120),"赎回费不能达到赎回总额",IF(NOT(ISNUMBER(E120)),"自动金额未生成，请检查五项输入",IF(NOT(OR(持仓总览!$C$7="利润优先",持仓总览!$C$7="本金优先")),"请选择卖出分配模式","已计入"))))))))))))))))))) | J120: =IF(AA120="正常",IF(I120="已计入",IF(OR(OR(B120="买入",B120="定投",B120="转换转入"),B120="红利再投"),D120,IF(B120="卖出",-D120,0)),0),"") -> 0 | K120: =IF(AA120="正常",ROUND(K119+J120,6),"") -> 34284.43 | L120: =IF(I120="已计入",ROUND(K119*C120,2),"") | M120: =IF(I120="已计入",IF(B120="卖出",MAX(0,L120-Q119-F120),IF(B120="现金分红",MAX(0,L120+E120-Q119),0)),"") | N120: =IF(I120="已计入",IF(AND(B120="卖出",持仓总览!$C$7="本金优先"),MAX(0,E120-Q119),IF(OR(B120="卖出",B120="现金分红"),MIN(E120,M120),0)),"") | O120: =IF(I120="已计入",IF(OR(B120="卖出",B120="现金分红"),MIN(Q119,MAX(0,E120-N120)),0),"") | P120: =IF(I120="已计入",IF(AND(B120="卖出",K120=0),MAX(0,Q119-O120),0),"") | Q120: =IF(AA120="正常",IF(I120="已计入",ROUND(Q119+IF(OR(B120="买入",B120="定投",B120="转换转入"),E120,0)-O120-P120,2),Q119),"") -> 82516.01 | R120: =IF(I120="已计入",ROUND(K120*C120,2),"") | S120: =IF(I120="已计入",ROUND(R120-Q120,2),"") | T120: =IF(I120="已计入",IF(Q120=0,"",S120/Q120),"") | U120: =IF(AA120="正常",U119+IF(AND(I120="已计入",OR(B120="买入",B120="定投",B120="转换转入")),E120,0),"") -> 82516.01 | V120: =IF(AA120="正常",V119+IF(AND(I120="已计入",OR(B120="卖出",B120="现金分红")),E120,0),"") -> 0 | W120: =IF(AA120="正常",W119+IF(I120="已计入",N120,0),"") -> 0 | X120: =IF(AA120="正常",X119+IF(I120="已计入",P120,0),"") -> 0 | Y120: =IF(I120="已计入",ROUND(R120+V120-U120,2),"") | Z120: =IF(AA120="正常",IF(I120="已计入",A120,Z119),"") -> 46247 | AA120: =IF(OR(AA119="错误",AND(I120<>"",I120<>"已排除",I120<>"待确认",I120<>"已计入")),"错误","正常") -> 正常 | AB120: =IF(AA120="正常",IF(I120="已计入",C120,AB119),"") -> 2.7686
E121: =IF(AND(ISNUMBER(C121),ISNUMBER(D121),ISNUMBER(F121)),IF(OR(B121="买入",B121="定投"),ROUND(C121*D121+F121,2),IF(B121="卖出",ROUND(C121*D121-F121,2),IF(B121="红利再投",0,""))),"") | G121: =IF(COUNTA(A121:D121,F121)=0,"",IF(I121="已计入","已录入","待修正")) | H121: =IF(COUNTA(A121:D121,F121)=0,"",IF(B121="红利再投","仅增加份额，不增加现金投入","金额由份额、净值和手续费推算")) | I121: =IF(COUNTA(A121:D121,F121)=0,"",IF(NOT(ISNUMBER(A121)),"缺少有效净值日期",IF(OR(A121<=0,A121<>INT(A121)),"净值日期无效",IF(OR(B121="转换转入",B121="现金分红"),"该类型需实际金额，五项录入不适用",IF(NOT(OR(OR(B121="买入",B121="定投"),B121="卖出",B121="红利再投")),"请选择交易类型",IF(NOT(ISNUMBER(C121)),"缺少成交净值",IF(C121<=0,"成交净值须大于零",IF(NOT(ISNUMBER(D121)),"缺少确认份额",IF(D121<=0,"确认份额须大于零",IF(NOT(ISNUMBER(F121)),"缺少手续费，无费用请填 0",IF(F121<0,"手续费不能为负",IF(AA120="错误","前行待修正",IF(A121<Z120,"日期需按成交顺序递增",IF(AND(B121="红利再投",F121<>0),"红利再投手续费应填 0",IF(AND(B121="红利再投",K120<=0),"红利再投前须有持仓",IF(AND(B121="卖出",D121>K120+0.000001),"卖出份额超过持仓",IF(AND(B121="卖出",F121>=C121*D121),"赎回费不能达到赎回总额",IF(NOT(ISNUMBER(E121)),"自动金额未生成，请检查五项输入",IF(NOT(OR(持仓总览!$C$7="利润优先",持仓总览!$C$7="本金优先")),"请选择卖出分配模式","已计入"))))))))))))))))))) | J121: =IF(AA121="正常",IF(I121="已计入",IF(OR(OR(B121="买入",B121="定投",B121="转换转入"),B121="红利再投"),D121,IF(B121="卖出",-D121,0)),0),"") -> 0 | K121: =IF(AA121="正常",ROUND(K120+J121,6),"") -> 34284.43 | L121: =IF(I121="已计入",ROUND(K120*C121,2),"") | M121: =IF(I121="已计入",IF(B121="卖出",MAX(0,L121-Q120-F121),IF(B121="现金分红",MAX(0,L121+E121-Q120),0)),"") | N121: =IF(I121="已计入",IF(AND(B121="卖出",持仓总览!$C$7="本金优先"),MAX(0,E121-Q120),IF(OR(B121="卖出",B121="现金分红"),MIN(E121,M121),0)),"") | O121: =IF(I121="已计入",IF(OR(B121="卖出",B121="现金分红"),MIN(Q120,MAX(0,E121-N121)),0),"") | P121: =IF(I121="已计入",IF(AND(B121="卖出",K121=0),MAX(0,Q120-O121),0),"") | Q121: =IF(AA121="正常",IF(I121="已计入",ROUND(Q120+IF(OR(B121="买入",B121="定投",B121="转换转入"),E121,0)-O121-P121,2),Q120),"") -> 82516.01 | R121: =IF(I121="已计入",ROUND(K121*C121,2),"") | S121: =IF(I121="已计入",ROUND(R121-Q121,2),"") | T121: =IF(I121="已计入",IF(Q121=0,"",S121/Q121),"") | U121: =IF(AA121="正常",U120+IF(AND(I121="已计入",OR(B121="买入",B121="定投",B121="转换转入")),E121,0),"") -> 82516.01 | V121: =IF(AA121="正常",V120+IF(AND(I121="已计入",OR(B121="卖出",B121="现金分红")),E121,0),"") -> 0 | W121: =IF(AA121="正常",W120+IF(I121="已计入",N121,0),"") -> 0 | X121: =IF(AA121="正常",X120+IF(I121="已计入",P121,0),"") -> 0 | Y121: =IF(I121="已计入",ROUND(R121+V121-U121,2),"") | Z121: =IF(AA121="正常",IF(I121="已计入",A121,Z120),"") -> 46247 | AA121: =IF(OR(AA120="错误",AND(I121<>"",I121<>"已排除",I121<>"待确认",I121<>"已计入")),"错误","正常") -> 正常 | AB121: =IF(AA121="正常",IF(I121="已计入",C121,AB120),"") -> 2.7686
E122: =IF(AND(ISNUMBER(C122),ISNUMBER(D122),ISNUMBER(F122)),IF(OR(B122="买入",B122="定投"),ROUND(C122*D122+F122,2),IF(B122="卖出",ROUND(C122*D122-F122,2),IF(B122="红利再投",0,""))),"") | G122: =IF(COUNTA(A122:D122,F122)=0,"",IF(I122="已计入","已录入","待修正")) | H122: =IF(COUNTA(A122:D122,F122)=0,"",IF(B122="红利再投","仅增加份额，不增加现金投入","金额由份额、净值和手续费推算")) | I122: =IF(COUNTA(A122:D122,F122)=0,"",IF(NOT(ISNUMBER(A122)),"缺少有效净值日期",IF(OR(A122<=0,A122<>INT(A122)),"净值日期无效",IF(OR(B122="转换转入",B122="现金分红"),"该类型需实际金额，五项录入不适用",IF(NOT(OR(OR(B122="买入",B122="定投"),B122="卖出",B122="红利再投")),"请选择交易类型",IF(NOT(ISNUMBER(C122)),"缺少成交净值",IF(C122<=0,"成交净值须大于零",IF(NOT(ISNUMBER(D122)),"缺少确认份额",IF(D122<=0,"确认份额须大于零",IF(NOT(ISNUMBER(F122)),"缺少手续费，无费用请填 0",IF(F122<0,"手续费不能为负",IF(AA121="错误","前行待修正",IF(A122<Z121,"日期需按成交顺序递增",IF(AND(B122="红利再投",F122<>0),"红利再投手续费应填 0",IF(AND(B122="红利再投",K121<=0),"红利再投前须有持仓",IF(AND(B122="卖出",D122>K121+0.000001),"卖出份额超过持仓",IF(AND(B122="卖出",F122>=C122*D122),"赎回费不能达到赎回总额",IF(NOT(ISNUMBER(E122)),"自动金额未生成，请检查五项输入",IF(NOT(OR(持仓总览!$C$7="利润优先",持仓总览!$C$7="本金优先")),"请选择卖出分配模式","已计入"))))))))))))))))))) | J122: =IF(AA122="正常",IF(I122="已计入",IF(OR(OR(B122="买入",B122="定投",B122="转换转入"),B122="红利再投"),D122,IF(B122="卖出",-D122,0)),0),"") -> 0 | K122: =IF(AA122="正常",ROUND(K121+J122,6),"") -> 34284.43 | L122: =IF(I122="已计入",ROUND(K121*C122,2),"") | M122: =IF(I122="已计入",IF(B122="卖出",MAX(0,L122-Q121-F122),IF(B122="现金分红",MAX(0,L122+E122-Q121),0)),"") | N122: =IF(I122="已计入",IF(AND(B122="卖出",持仓总览!$C$7="本金优先"),MAX(0,E122-Q121),IF(OR(B122="卖出",B122="现金分红"),MIN(E122,M122),0)),"") | O122: =IF(I122="已计入",IF(OR(B122="卖出",B122="现金分红"),MIN(Q121,MAX(0,E122-N122)),0),"") | P122: =IF(I122="已计入",IF(AND(B122="卖出",K122=0),MAX(0,Q121-O122),0),"") | Q122: =IF(AA122="正常",IF(I122="已计入",ROUND(Q121+IF(OR(B122="买入",B122="定投",B122="转换转入"),E122,0)-O122-P122,2),Q121),"") -> 82516.01 | R122: =IF(I122="已计入",ROUND(K122*C122,2),"") | S122: =IF(I122="已计入",ROUND(R122-Q122,2),"") | T122: =IF(I122="已计入",IF(Q122=0,"",S122/Q122),"") | U122: =IF(AA122="正常",U121+IF(AND(I122="已计入",OR(B122="买入",B122="定投",B122="转换转入")),E122,0),"") -> 82516.01 | V122: =IF(AA122="正常",V121+IF(AND(I122="已计入",OR(B122="卖出",B122="现金分红")),E122,0),"") -> 0 | W122: =IF(AA122="正常",W121+IF(I122="已计入",N122,0),"") -> 0 | X122: =IF(AA122="正常",X121+IF(I122="已计入",P122,0),"") -> 0 | Y122: =IF(I122="已计入",ROUND(R122+V122-U122,2),"") | Z122: =IF(AA122="正常",IF(I122="已计入",A122,Z121),"") -> 46247 | AA122: =IF(OR(AA121="错误",AND(I122<>"",I122<>"已排除",I122<>"待确认",I122<>"已计入")),"错误","正常") -> 正常 | AB122: =IF(AA122="正常",IF(I122="已计入",C122,AB121),"") -> 2.7686
E123: =IF(AND(ISNUMBER(C123),ISNUMBER(D123),ISNUMBER(F123)),IF(OR(B123="买入",B123="定投"),ROUND(C123*D123+F123,2),IF(B123="卖出",ROUND(C123*D123-F123,2),IF(B123="红利再投",0,""))),"") | G123: =IF(COUNTA(A123:D123,F123)=0,"",IF(I123="已计入","已录入","待修正")) | H123: =IF(COUNTA(A123:D123,F123)=0,"",IF(B123="红利再投","仅增加份额，不增加现金投入","金额由份额、净值和手续费推算")) | I123: =IF(COUNTA(A123:D123,F123)=0,"",IF(NOT(ISNUMBER(A123)),"缺少有效净值日期",IF(OR(A123<=0,A123<>INT(A123)),"净值日期无效",IF(OR(B123="转换转入",B123="现金分红"),"该类型需实际金额，五项录入不适用",IF(NOT(OR(OR(B123="买入",B123="定投"),B123="卖出",B123="红利再投")),"请选择交易类型",IF(NOT(ISNUMBER(C123)),"缺少成交净值",IF(C123<=0,"成交净值须大于零",IF(NOT(ISNUMBER(D123)),"缺少确认份额",IF(D123<=0,"确认份额须大于零",IF(NOT(ISNUMBER(F123)),"缺少手续费，无费用请填 0",IF(F123<0,"手续费不能为负",IF(AA122="错误","前行待修正",IF(A123<Z122,"日期需按成交顺序递增",IF(AND(B123="红利再投",F123<>0),"红利再投手续费应填 0",IF(AND(B123="红利再投",K122<=0),"红利再投前须有持仓",IF(AND(B123="卖出",D123>K122+0.000001),"卖出份额超过持仓",IF(AND(B123="卖出",F123>=C123*D123),"赎回费不能达到赎回总额",IF(NOT(ISNUMBER(E123)),"自动金额未生成，请检查五项输入",IF(NOT(OR(持仓总览!$C$7="利润优先",持仓总览!$C$7="本金优先")),"请选择卖出分配模式","已计入"))))))))))))))))))) | J123: =IF(AA123="正常",IF(I123="已计入",IF(OR(OR(B123="买入",B123="定投",B123="转换转入"),B123="红利再投"),D123,IF(B123="卖出",-D123,0)),0),"") -> 0 | K123: =IF(AA123="正常",ROUND(K122+J123,6),"") -> 34284.43 | L123: =IF(I123="已计入",ROUND(K122*C123,2),"") | M123: =IF(I123="已计入",IF(B123="卖出",MAX(0,L123-Q122-F123),IF(B123="现金分红",MAX(0,L123+E123-Q122),0)),"") | N123: =IF(I123="已计入",IF(AND(B123="卖出",持仓总览!$C$7="本金优先"),MAX(0,E123-Q122),IF(OR(B123="卖出",B123="现金分红"),MIN(E123,M123),0)),"") | O123: =IF(I123="已计入",IF(OR(B123="卖出",B123="现金分红"),MIN(Q122,MAX(0,E123-N123)),0),"") | P123: =IF(I123="已计入",IF(AND(B123="卖出",K123=0),MAX(0,Q122-O123),0),"") | Q123: =IF(AA123="正常",IF(I123="已计入",ROUND(Q122+IF(OR(B123="买入",B123="定投",B123="转换转入"),E123,0)-O123-P123,2),Q122),"") -> 82516.01 | R123: =IF(I123="已计入",ROUND(K123*C123,2),"") | S123: =IF(I123="已计入",ROUND(R123-Q123,2),"") | T123: =IF(I123="已计入",IF(Q123=0,"",S123/Q123),"") | U123: =IF(AA123="正常",U122+IF(AND(I123="已计入",OR(B123="买入",B123="定投",B123="转换转入")),E123,0),"") -> 82516.01 | V123: =IF(AA123="正常",V122+IF(AND(I123="已计入",OR(B123="卖出",B123="现金分红")),E123,0),"") -> 0 | W123: =IF(AA123="正常",W122+IF(I123="已计入",N123,0),"") -> 0 | X123: =IF(AA123="正常",X122+IF(I123="已计入",P123,0),"") -> 0 | Y123: =IF(I123="已计入",ROUND(R123+V123-U123,2),"") | Z123: =IF(AA123="正常",IF(I123="已计入",A123,Z122),"") -> 46247 | AA123: =IF(OR(AA122="错误",AND(I123<>"",I123<>"已排除",I123<>"待确认",I123<>"已计入")),"错误","正常") -> 正常 | AB123: =IF(AA123="正常",IF(I123="已计入",C123,AB122),"") -> 2.7686
E124: =IF(AND(ISNUMBER(C124),ISNUMBER(D124),ISNUMBER(F124)),IF(OR(B124="买入",B124="定投"),ROUND(C124*D124+F124,2),IF(B124="卖出",ROUND(C124*D124-F124,2),IF(B124="红利再投",0,""))),"") | G124: =IF(COUNTA(A124:D124,F124)=0,"",IF(I124="已计入","已录入","待修正")) | H124: =IF(COUNTA(A124:D124,F124)=0,"",IF(B124="红利再投","仅增加份额，不增加现金投入","金额由份额、净值和手续费推算")) | I124: =IF(COUNTA(A124:D124,F124)=0,"",IF(NOT(ISNUMBER(A124)),"缺少有效净值日期",IF(OR(A124<=0,A124<>INT(A124)),"净值日期无效",IF(OR(B124="转换转入",B124="现金分红"),"该类型需实际金额，五项录入不适用",IF(NOT(OR(OR(B124="买入",B124="定投"),B124="卖出",B124="红利再投")),"请选择交易类型",IF(NOT(ISNUMBER(C124)),"缺少成交净值",IF(C124<=0,"成交净值须大于零",IF(NOT(ISNUMBER(D124)),"缺少确认份额",IF(D124<=0,"确认份额须大于零",IF(NOT(ISNUMBER(F124)),"缺少手续费，无费用请填 0",IF(F124<0,"手续费不能为负",IF(AA123="错误","前行待修正",IF(A124<Z123,"日期需按成交顺序递增",IF(AND(B124="红利再投",F124<>0),"红利再投手续费应填 0",IF(AND(B124="红利再投",K123<=0),"红利再投前须有持仓",IF(AND(B124="卖出",D124>K123+0.000001),"卖出份额超过持仓",IF(AND(B124="卖出",F124>=C124*D124),"赎回费不能达到赎回总额",IF(NOT(ISNUMBER(E124)),"自动金额未生成，请检查五项输入",IF(NOT(OR(持仓总览!$C$7="利润优先",持仓总览!$C$7="本金优先")),"请选择卖出分配模式","已计入"))))))))))))))))))) | J124: =IF(AA124="正常",IF(I124="已计入",IF(OR(OR(B124="买入",B124="定投",B124="转换转入"),B124="红利再投"),D124,IF(B124="卖出",-D124,0)),0),"") -> 0 | K124: =IF(AA124="正常",ROUND(K123+J124,6),"") -> 34284.43 | L124: =IF(I124="已计入",ROUND(K123*C124,2),"") | M124: =IF(I124="已计入",IF(B124="卖出",MAX(0,L124-Q123-F124),IF(B124="现金分红",MAX(0,L124+E124-Q123),0)),"") | N124: =IF(I124="已计入",IF(AND(B124="卖出",持仓总览!$C$7="本金优先"),MAX(0,E124-Q123),IF(OR(B124="卖出",B124="现金分红"),MIN(E124,M124),0)),"") | O124: =IF(I124="已计入",IF(OR(B124="卖出",B124="现金分红"),MIN(Q123,MAX(0,E124-N124)),0),"") | P124: =IF(I124="已计入",IF(AND(B124="卖出",K124=0),MAX(0,Q123-O124),0),"") | Q124: =IF(AA124="正常",IF(I124="已计入",ROUND(Q123+IF(OR(B124="买入",B124="定投",B124="转换转入"),E124,0)-O124-P124,2),Q123),"") -> 82516.01 | R124: =IF(I124="已计入",ROUND(K124*C124,2),"") | S124: =IF(I124="已计入",ROUND(R124-Q124,2),"") | T124: =IF(I124="已计入",IF(Q124=0,"",S124/Q124),"") | U124: =IF(AA124="正常",U123+IF(AND(I124="已计入",OR(B124="买入",B124="定投",B124="转换转入")),E124,0),"") -> 82516.01 | V124: =IF(AA124="正常",V123+IF(AND(I124="已计入",OR(B124="卖出",B124="现金分红")),E124,0),"") -> 0 | W124: =IF(AA124="正常",W123+IF(I124="已计入",N124,0),"") -> 0 | X124: =IF(AA124="正常",X123+IF(I124="已计入",P124,0),"") -> 0 | Y124: =IF(I124="已计入",ROUND(R124+V124-U124,2),"") | Z124: =IF(AA124="正常",IF(I124="已计入",A124,Z123),"") -> 46247 | AA124: =IF(OR(AA123="错误",AND(I124<>"",I124<>"已排除",I124<>"待确认",I124<>"已计入")),"错误","正常") -> 正常 | AB124: =IF(AA124="正常",IF(I124="已计入",C124,AB123),"") -> 2.7686
E125: =IF(AND(ISNUMBER(C125),ISNUMBER(D125),ISNUMBER(F125)),IF(OR(B125="买入",B125="定投"),ROUND(C125*D125+F125,2),IF(B125="卖出",ROUND(C125*D125-F125,2),IF(B125="红利再投",0,""))),"") | G125: =IF(COUNTA(A125:D125,F125)=0,"",IF(I125="已计入","已录入","待修正")) | H125: =IF(COUNTA(A125:D125,F125)=0,"",IF(B125="红利再投","仅增加份额，不增加现金投入","金额由份额、净值和手续费推算")) | I125: =IF(COUNTA(A125:D125,F125)=0,"",IF(NOT(ISNUMBER(A125)),"缺少有效净值日期",IF(OR(A125<=0,A125<>INT(A125)),"净值日期无效",IF(OR(B125="转换转入",B125="现金分红"),"该类型需实际金额，五项录入不适用",IF(NOT(OR(OR(B125="买入",B125="定投"),B125="卖出",B125="红利再投")),"请选择交易类型",IF(NOT(ISNUMBER(C125)),"缺少成交净值",IF(C125<=0,"成交净值须大于零",IF(NOT(ISNUMBER(D125)),"缺少确认份额",IF(D125<=0,"确认份额须大于零",IF(NOT(ISNUMBER(F125)),"缺少手续费，无费用请填 0",IF(F125<0,"手续费不能为负",IF(AA124="错误","前行待修正",IF(A125<Z124,"日期需按成交顺序递增",IF(AND(B125="红利再投",F125<>0),"红利再投手续费应填 0",IF(AND(B125="红利再投",K124<=0),"红利再投前须有持仓",IF(AND(B125="卖出",D125>K124+0.000001),"卖出份额超过持仓",IF(AND(B125="卖出",F125>=C125*D125),"赎回费不能达到赎回总额",IF(NOT(ISNUMBER(E125)),"自动金额未生成，请检查五项输入",IF(NOT(OR(持仓总览!$C$7="利润优先",持仓总览!$C$7="本金优先")),"请选择卖出分配模式","已计入"))))))))))))))))))) | J125: =IF(AA125="正常",IF(I125="已计入",IF(OR(OR(B125="买入",B125="定投",B125="转换转入"),B125="红利再投"),D125,IF(B125="卖出",-D125,0)),0),"") -> 0 | K125: =IF(AA125="正常",ROUND(K124+J125,6),"") -> 34284.43 | L125: =IF(I125="已计入",ROUND(K124*C125,2),"") | M125: =IF(I125="已计入",IF(B125="卖出",MAX(0,L125-Q124-F125),IF(B125="现金分红",MAX(0,L125+E125-Q124),0)),"") | N125: =IF(I125="已计入",IF(AND(B125="卖出",持仓总览!$C$7="本金优先"),MAX(0,E125-Q124),IF(OR(B125="卖出",B125="现金分红"),MIN(E125,M125),0)),"") | O125: =IF(I125="已计入",IF(OR(B125="卖出",B125="现金分红"),MIN(Q124,MAX(0,E125-N125)),0),"") | P125: =IF(I125="已计入",IF(AND(B125="卖出",K125=0),MAX(0,Q124-O125),0),"") | Q125: =IF(AA125="正常",IF(I125="已计入",ROUND(Q124+IF(OR(B125="买入",B125="定投",B125="转换转入"),E125,0)-O125-P125,2),Q124),"") -> 82516.01 | R125: =IF(I125="已计入",ROUND(K125*C125,2),"") | S125: =IF(I125="已计入",ROUND(R125-Q125,2),"") | T125: =IF(I125="已计入",IF(Q125=0,"",S125/Q125),"") | U125: =IF(AA125="正常",U124+IF(AND(I125="已计入",OR(B125="买入",B125="定投",B125="转换转入")),E125,0),"") -> 82516.01 | V125: =IF(AA125="正常",V124+IF(AND(I125="已计入",OR(B125="卖出",B125="现金分红")),E125,0),"") -> 0 | W125: =IF(AA125="正常",W124+IF(I125="已计入",N125,0),"") -> 0 | X125: =IF(AA125="正常",X124+IF(I125="已计入",P125,0),"") -> 0 | Y125: =IF(I125="已计入",ROUND(R125+V125-U125,2),"") | Z125: =IF(AA125="正常",IF(I125="已计入",A125,Z124),"") -> 46247 | AA125: =IF(OR(AA124="错误",AND(I125<>"",I125<>"已排除",I125<>"待确认",I125<>"已计入")),"错误","正常") -> 正常 | AB125: =IF(AA125="正常",IF(I125="已计入",C125,AB124),"") -> 2.7686
E126: =IF(AND(ISNUMBER(C126),ISNUMBER(D126),ISNUMBER(F126)),IF(OR(B126="买入",B126="定投"),ROUND(C126*D126+F126,2),IF(B126="卖出",ROUND(C126*D126-F126,2),IF(B126="红利再投",0,""))),"") | G126: =IF(COUNTA(A126:D126,F126)=0,"",IF(I126="已计入","已录入","待修正")) | H126: =IF(COUNTA(A126:D126,F126)=0,"",IF(B126="红利再投","仅增加份额，不增加现金投入","金额由份额、净值和手续费推算")) | I126: =IF(COUNTA(A126:D126,F126)=0,"",IF(NOT(ISNUMBER(A126)),"缺少有效净值日期",IF(OR(A126<=0,A126<>INT(A126)),"净值日期无效",IF(OR(B126="转换转入",B126="现金分红"),"该类型需实际金额，五项录入不适用",IF(NOT(OR(OR(B126="买入",B126="定投"),B126="卖出",B126="红利再投")),"请选择交易类型",IF(NOT(ISNUMBER(C126)),"缺少成交净值",IF(C126<=0,"成交净值须大于零",IF(NOT(ISNUMBER(D126)),"缺少确认份额",IF(D126<=0,"确认份额须大于零",IF(NOT(ISNUMBER(F126)),"缺少手续费，无费用请填 0",IF(F126<0,"手续费不能为负",IF(AA125="错误","前行待修正",IF(A126<Z125,"日期需按成交顺序递增",IF(AND(B126="红利再投",F126<>0),"红利再投手续费应填 0",IF(AND(B126="红利再投",K125<=0),"红利再投前须有持仓",IF(AND(B126="卖出",D126>K125+0.000001),"卖出份额超过持仓",IF(AND(B126="卖出",F126>=C126*D126),"赎回费不能达到赎回总额",IF(NOT(ISNUMBER(E126)),"自动金额未生成，请检查五项输入",IF(NOT(OR(持仓总览!$C$7="利润优先",持仓总览!$C$7="本金优先")),"请选择卖出分配模式","已计入"))))))))))))))))))) | J126: =IF(AA126="正常",IF(I126="已计入",IF(OR(OR(B126="买入",B126="定投",B126="转换转入"),B126="红利再投"),D126,IF(B126="卖出",-D126,0)),0),"") -> 0 | K126: =IF(AA126="正常",ROUND(K125+J126,6),"") -> 34284.43 | L126: =IF(I126="已计入",ROUND(K125*C126,2),"") | M126: =IF(I126="已计入",IF(B126="卖出",MAX(0,L126-Q125-F126),IF(B126="现金分红",MAX(0,L126+E126-Q125),0)),"") | N126: =IF(I126="已计入",IF(AND(B126="卖出",持仓总览!$C$7="本金优先"),MAX(0,E126-Q125),IF(OR(B126="卖出",B126="现金分红"),MIN(E126,M126),0)),"") | O126: =IF(I126="已计入",IF(OR(B126="卖出",B126="现金分红"),MIN(Q125,MAX(0,E126-N126)),0),"") | P126: =IF(I126="已计入",IF(AND(B126="卖出",K126=0),MAX(0,Q125-O126),0),"") | Q126: =IF(AA126="正常",IF(I126="已计入",ROUND(Q125+IF(OR(B126="买入",B126="定投",B126="转换转入"),E126,0)-O126-P126,2),Q125),"") -> 82516.01 | R126: =IF(I126="已计入",ROUND(K126*C126,2),"") | S126: =IF(I126="已计入",ROUND(R126-Q126,2),"") | T126: =IF(I126="已计入",IF(Q126=0,"",S126/Q126),"") | U126: =IF(AA126="正常",U125+IF(AND(I126="已计入",OR(B126="买入",B126="定投",B126="转换转入")),E126,0),"") -> 82516.01 | V126: =IF(AA126="正常",V125+IF(AND(I126="已计入",OR(B126="卖出",B126="现金分红")),E126,0),"") -> 0 | W126: =IF(AA126="正常",W125+IF(I126="已计入",N126,0),"") -> 0 | X126: =IF(AA126="正常",X125+IF(I126="已计入",P126,0),"") -> 0 | Y126: =IF(I126="已计入",ROUND(R126+V126-U126,2),"") | Z126: =IF(AA126="正常",IF(I126="已计入",A126,Z125),"") -> 46247 | AA126: =IF(OR(AA125="错误",AND(I126<>"",I126<>"已排除",I126<>"待确认",I126<>"已计入")),"错误","正常") -> 正常 | AB126: =IF(AA126="正常",IF(I126="已计入",C126,AB125),"") -> 2.7686
E127: =IF(AND(ISNUMBER(C127),ISNUMBER(D127),ISNUMBER(F127)),IF(OR(B127="买入",B127="定投"),ROUND(C127*D127+F127,2),IF(B127="卖出",ROUND(C127*D127-F127,2),IF(B127="红利再投",0,""))),"") | G127: =IF(COUNTA(A127:D127,F127)=0,"",IF(I127="已计入","已录入","待修正")) | H127: =IF(COUNTA(A127:D127,F127)=0,"",IF(B127="红利再投","仅增加份额，不增加现金投入","金额由份额、净值和手续费推算")) | I127: =IF(COUNTA(A127:D127,F127)=0,"",IF(NOT(ISNUMBER(A127)),"缺少有效净值日期",IF(OR(A127<=0,A127<>INT(A127)),"净值日期无效",IF(OR(B127="转换转入",B127="现金分红"),"该类型需实际金额，五项录入不适用",IF(NOT(OR(OR(B127="买入",B127="定投"),B127="卖出",B127="红利再投")),"请选择交易类型",IF(NOT(ISNUMBER(C127)),"缺少成交净值",IF(C127<=0,"成交净值须大于零",IF(NOT(ISNUMBER(D127)),"缺少确认份额",IF(D127<=0,"确认份额须大于零",IF(NOT(ISNUMBER(F127)),"缺少手续费，无费用请填 0",IF(F127<0,"手续费不能为负",IF(AA126="错误","前行待修正",IF(A127<Z126,"日期需按成交顺序递增",IF(AND(B127="红利再投",F127<>0),"红利再投手续费应填 0",IF(AND(B127="红利再投",K126<=0),"红利再投前须有持仓",IF(AND(B127="卖出",D127>K126+0.000001),"卖出份额超过持仓",IF(AND(B127="卖出",F127>=C127*D127),"赎回费不能达到赎回总额",IF(NOT(ISNUMBER(E127)),"自动金额未生成，请检查五项输入",IF(NOT(OR(持仓总览!$C$7="利润优先",持仓总览!$C$7="本金优先")),"请选择卖出分配模式","已计入"))))))))))))))))))) | J127: =IF(AA127="正常",IF(I127="已计入",IF(OR(OR(B127="买入",B127="定投",B127="转换转入"),B127="红利再投"),D127,IF(B127="卖出",-D127,0)),0),"") -> 0 | K127: =IF(AA127="正常",ROUND(K126+J127,6),"") -> 34284.43 | L127: =IF(I127="已计入",ROUND(K126*C127,2),"") | M127: =IF(I127="已计入",IF(B127="卖出",MAX(0,L127-Q126-F127),IF(B127="现金分红",MAX(0,L127+E127-Q126),0)),"") | N127: =IF(I127="已计入",IF(AND(B127="卖出",持仓总览!$C$7="本金优先"),MAX(0,E127-Q126),IF(OR(B127="卖出",B127="现金分红"),MIN(E127,M127),0)),"") | O127: =IF(I127="已计入",IF(OR(B127="卖出",B127="现金分红"),MIN(Q126,MAX(0,E127-N127)),0),"") | P127: =IF(I127="已计入",IF(AND(B127="卖出",K127=0),MAX(0,Q126-O127),0),"") | Q127: =IF(AA127="正常",IF(I127="已计入",ROUND(Q126+IF(OR(B127="买入",B127="定投",B127="转换转入"),E127,0)-O127-P127,2),Q126),"") -> 82516.01 | R127: =IF(I127="已计入",ROUND(K127*C127,2),"") | S127: =IF(I127="已计入",ROUND(R127-Q127,2),"") | T127: =IF(I127="已计入",IF(Q127=0,"",S127/Q127),"") | U127: =IF(AA127="正常",U126+IF(AND(I127="已计入",OR(B127="买入",B127="定投",B127="转换转入")),E127,0),"") -> 82516.01 | V127: =IF(AA127="正常",V126+IF(AND(I127="已计入",OR(B127="卖出",B127="现金分红")),E127,0),"") -> 0 | W127: =IF(AA127="正常",W126+IF(I127="已计入",N127,0),"") -> 0 | X127: =IF(AA127="正常",X126+IF(I127="已计入",P127,0),"") -> 0 | Y127: =IF(I127="已计入",ROUND(R127+V127-U127,2),"") | Z127: =IF(AA127="正常",IF(I127="已计入",A127,Z126),"") -> 46247 | AA127: =IF(OR(AA126="错误",AND(I127<>"",I127<>"已排除",I127<>"待确认",I127<>"已计入")),"错误","正常") -> 正常 | AB127: =IF(AA127="正常",IF(I127="已计入",C127,AB126),"") -> 2.7686
E128: =IF(AND(ISNUMBER(C128),ISNUMBER(D128),ISNUMBER(F128)),IF(OR(B128="买入",B128="定投"),ROUND(C128*D128+F128,2),IF(B128="卖出",ROUND(C128*D128-F128,2),IF(B128="红利再投",0,""))),"") | G128: =IF(COUNTA(A128:D128,F128)=0,"",IF(I128="已计入","已录入","待修正")) | H128: =IF(COUNTA(A128:D128,F128)=0,"",IF(B128="红利再投","仅增加份额，不增加现金投入","金额由份额、净值和手续费推算")) | I128: =IF(COUNTA(A128:D128,F128)=0,"",IF(NOT(ISNUMBER(A128)),"缺少有效净值日期",IF(OR(A128<=0,A128<>INT(A128)),"净值日期无效",IF(OR(B128="转换转入",B128="现金分红"),"该类型需实际金额，五项录入不适用",IF(NOT(OR(OR(B128="买入",B128="定投"),B128="卖出",B128="红利再投")),"请选择交易类型",IF(NOT(ISNUMBER(C128)),"缺少成交净值",IF(C128<=0,"成交净值须大于零",IF(NOT(ISNUMBER(D128)),"缺少确认份额",IF(D128<=0,"确认份额须大于零",IF(NOT(ISNUMBER(F128)),"缺少手续费，无费用请填 0",IF(F128<0,"手续费不能为负",IF(AA127="错误","前行待修正",IF(A128<Z127,"日期需按成交顺序递增",IF(AND(B128="红利再投",F128<>0),"红利再投手续费应填 0",IF(AND(B128="红利再投",K127<=0),"红利再投前须有持仓",IF(AND(B128="卖出",D128>K127+0.000001),"卖出份额超过持仓",IF(AND(B128="卖出",F128>=C128*D128),"赎回费不能达到赎回总额",IF(NOT(ISNUMBER(E128)),"自动金额未生成，请检查五项输入",IF(NOT(OR(持仓总览!$C$7="利润优先",持仓总览!$C$7="本金优先")),"请选择卖出分配模式","已计入"))))))))))))))))))) | J128: =IF(AA128="正常",IF(I128="已计入",IF(OR(OR(B128="买入",B128="定投",B128="转换转入"),B128="红利再投"),D128,IF(B128="卖出",-D128,0)),0),"") -> 0 | K128: =IF(AA128="正常",ROUND(K127+J128,6),"") -> 34284.43 | L128: =IF(I128="已计入",ROUND(K127*C128,2),"") | M128: =IF(I128="已计入",IF(B128="卖出",MAX(0,L128-Q127-F128),IF(B128="现金分红",MAX(0,L128+E128-Q127),0)),"") | N128: =IF(I128="已计入",IF(AND(B128="卖出",持仓总览!$C$7="本金优先"),MAX(0,E128-Q127),IF(OR(B128="卖出",B128="现金分红"),MIN(E128,M128),0)),"") | O128: =IF(I128="已计入",IF(OR(B128="卖出",B128="现金分红"),MIN(Q127,MAX(0,E128-N128)),0),"") | P128: =IF(I128="已计入",IF(AND(B128="卖出",K128=0),MAX(0,Q127-O128),0),"") | Q128: =IF(AA128="正常",IF(I128="已计入",ROUND(Q127+IF(OR(B128="买入",B128="定投",B128="转换转入"),E128,0)-O128-P128,2),Q127),"") -> 82516.01 | R128: =IF(I128="已计入",ROUND(K128*C128,2),"") | S128: =IF(I128="已计入",ROUND(R128-Q128,2),"") | T128: =IF(I128="已计入",IF(Q128=0,"",S128/Q128),"") | U128: =IF(AA128="正常",U127+IF(AND(I128="已计入",OR(B128="买入",B128="定投",B128="转换转入")),E128,0),"") -> 82516.01 | V128: =IF(AA128="正常",V127+IF(AND(I128="已计入",OR(B128="卖出",B128="现金分红")),E128,0),"") -> 0 | W128: =IF(AA128="正常",W127+IF(I128="已计入",N128,0),"") -> 0 | X128: =IF(AA128="正常",X127+IF(I128="已计入",P128,0),"") -> 0 | Y128: =IF(I128="已计入",ROUND(R128+V128-U128,2),"") | Z128: =IF(AA128="正常",IF(I128="已计入",A128,Z127),"") -> 46247 | AA128: =IF(OR(AA127="错误",AND(I128<>"",I128<>"已排除",I128<>"待确认",I128<>"已计入")),"错误","正常") -> 正常 | AB128: =IF(AA128="正常",IF(I128="已计入",C128,AB127),"") -> 2.7686
... E135: =IF(AND(ISNUMBER(C135),ISNUMBER(D135),ISNUMBER(F135)),IF(OR(B135="买入",B135="定投"),ROUND(C135*D135+F135,2),IF(B135="卖出",ROUND(C135*D135-F135,2),IF(B135="红利再投",0,""))),"") | G135: =IF(COUNTA(A135:D135,F135)=0,"",IF(I135="已计入","已录入","待修正")) | H135: =IF(COUNTA(A135:D135,F135)=0,"",IF(B135="红利再投","仅增加份额，不增加现金投入","金额由份额、净值和手续费推算")) | I135: =IF(COUNTA(A135:D135,F135)=0,"",IF(NOT(ISNUMBER(A135)),"缺少有效净值日期",IF(OR(A135<=0,A135<>INT(A135)),"净值日期无效",IF(OR(B135="转换转入",B135="现金分红"),"该类型需实际金额，五项录入不适用",IF(NOT(OR(OR(B135="买入",B135="定投"),B135="卖出",B135="红利再投")),"请选择交易类型",IF(NOT(ISNUMBER(C135)),"缺少成交净值",IF(C135<=0,"成交净值须大于零",IF(NOT(ISNUMBER(D135)),"缺少确认份额",IF(D135<=0,"确认份额须大于零",IF(NOT(ISNUMBER(F135)),"缺少手续费，无费用请填 0",IF(F135<0,"手续费不能为负",IF(AA134="错误","前行待修正",IF(A135<Z134,"日期需按成交顺序递增",IF(AND(B135="红利再投",F135<>0),"红利再投手续费应填 0",IF(AND(B135="红利再投",K134<=0),"红利再投前须有持仓",IF(AND(B135="卖出",D135>K134+0.000001),"卖出份额超过持仓",IF(AND(B135="卖出",F135>=C135*D135),"赎回费不能达到赎回总额",IF(NOT(ISNUMBER(E135)),"自动金额未生成，请检查五项输入",IF(NOT(OR(持仓总览!$C$7="利润优先",持仓总览!$C$7="本金优先")),"请选择卖出分配模式","已计入"))))))))))))))))))) | J135: =IF(AA135="正常",IF(I135="已计入",IF(OR(OR(B135="买入",B135="定投",B135="转换转入"),B135="红利再投"),D135,IF(B135="卖出",-D135,0)),0),"") -> 0 | K135: =IF(AA135="正常",ROUND(K134+J135,6),"") -> 34284.43 | L135: =IF(I135="已计入",ROUND(K134*C135,2),"") | M135: =IF(I135="已计入",IF(B135="卖出",MAX(0,L135-Q134-F135),IF(B135="现金分红",MAX(0,L135+E135-Q134),0)),"") | N135: =IF(I135="已计入",IF(AND(B135="卖出",持仓总览!$C$7="本金优先"),MAX(0,E135-Q134),IF(OR(B135="卖出",B135="现金分红"),MIN(E135,M135),0)),"") | O135: =IF(I135="已计入",IF(OR(B135="卖出",B135="现金分红"),MIN(Q134,MAX(0,E135-N135)),0),"") | P135: =IF(I135="已计入",IF(AND(B135="卖出",K135=0),MAX(0,Q134-O135),0),"") | Q135: =IF(AA135="正常",IF(I135="已计入",ROUND(Q134+IF(OR(B135="买入",B135="定投",B135="转换转入"),E135,0)-O135-P135,2),Q134),"") -> 82516.01 | R135: =IF(I135="已计入",ROUND(K135*C135,2),"") | S135: =IF(I135="已计入",ROUND(R135-Q135,2),"") | T135: =IF(I135="已计入",IF(Q135=0,"",S135/Q135),"") | U135: =IF(AA135="正常",U134+IF(AND(I135="已计入",OR(B135="买入",B135="定投",B135="转换转入")),E135,0),"") -> 82516.01 | V135: =IF(AA135="正常",V134+IF(AND(I135="已计入",OR(B135="卖出",B135="现金分红")),E135,0),"") -> 0 | W135: =IF(AA135="正常",W134+IF(I135="已计入",N135,0),"") -> 0 | X135: =IF(AA135="正常",X134+IF(I135="已计入",P135,0),"") -> 0 | Y135: =IF(I135="已计入",ROUND(R135+V135-U135,2),"") | Z135: =IF(AA135="正常",IF(I135="已计入",A135,Z134),"") -> 46247 | AA135: =IF(OR(AA134="错误",AND(I135<>"",I135<>"已排除",I135<>"待确认",I135<>"已计入")),"错误","正常") -> 正常 | AB135: =IF(AA135="正常",IF(I135="已计入",C135,AB134),"") -> 2.7686
E136: =IF(AND(ISNUMBER(C136),ISNUMBER(D136),ISNUMBER(F136)),IF(OR(B136="买入",B136="定投"),ROUND(C136*D136+F136,2),IF(B136="卖出",ROUND(C136*D136-F136,2),IF(B136="红利再投",0,""))),"") | G136: =IF(COUNTA(A136:D136,F136)=0,"",IF(I136="已计入","已录入","待修正")) | H136: =IF(COUNTA(A136:D136,F136)=0,"",IF(B136="红利再投","仅增加份额，不增加现金投入","金额由份额、净值和手续费推算")) | I136: =IF(COUNTA(A136:D136,F136)=0,"",IF(NOT(ISNUMBER(A136)),"缺少有效净值日期",IF(OR(A136<=0,A136<>INT(A136)),"净值日期无效",IF(OR(B136="转换转入",B136="现金分红"),"该类型需实际金额，五项录入不适用",IF(NOT(OR(OR(B136="买入",B136="定投"),B136="卖出",B136="红利再投")),"请选择交易类型",IF(NOT(ISNUMBER(C136)),"缺少成交净值",IF(C136<=0,"成交净值须大于零",IF(NOT(ISNUMBER(D136)),"缺少确认份额",IF(D136<=0,"确认份额须大于零",IF(NOT(ISNUMBER(F136)),"缺少手续费，无费用请填 0",IF(F136<0,"手续费不能为负",IF(AA135="错误","前行待修正",IF(A136<Z135,"日期需按成交顺序递增",IF(AND(B136="红利再投",F136<>0),"红利再投手续费应填 0",IF(AND(B136="红利再投",K135<=0),"红利再投前须有持仓",IF(AND(B136="卖出",D136>K135+0.000001),"卖出份额超过持仓",IF(AND(B136="卖出",F136>=C136*D136),"赎回费不能达到赎回总额",IF(NOT(ISNUMBER(E136)),"自动金额未生成，请检查五项输入",IF(NOT(OR(持仓总览!$C$7="利润优先",持仓总览!$C$7="本金优先")),"请选择卖出分配模式","已计入"))))))))))))))))))) | J136: =IF(AA136="正常",IF(I136="已计入",IF(OR(OR(B136="买入",B136="定投",B136="转换转入"),B136="红利再投"),D136,IF(B136="卖出",-D136,0)),0),"") -> 0 | K136: =IF(AA136="正常",ROUND(K135+J136,6),"") -> 34284.43 | L136: =IF(I136="已计入",ROUND(K135*C136,2),"") | M136: =IF(I136="已计入",IF(B136="卖出",MAX(0,L136-Q135-F136),IF(B136="现金分红",MAX(0,L136+E136-Q135),0)),"") | N136: =IF(I136="已计入",IF(AND(B136="卖出",持仓总览!$C$7="本金优先"),MAX(0,E136-Q135),IF(OR(B136="卖出",B136="现金分红"),MIN(E136,M136),0)),"") | O136: =IF(I136="已计入",IF(OR(B136="卖出",B136="现金分红"),MIN(Q135,MAX(0,E136-N136)),0),"") | P136: =IF(I136="已计入",IF(AND(B136="卖出",K136=0),MAX(0,Q135-O136),0),"") | Q136: =IF(AA136="正常",IF(I136="已计入",ROUND(Q135+IF(OR(B136="买入",B136="定投",B136="转换转入"),E136,0)-O136-P136,2),Q135),"") -> 82516.01 | R136: =IF(I136="已计入",ROUND(K136*C136,2),"") | S136: =IF(I136="已计入",ROUND(R136-Q136,2),"") | T136: =IF(I136="已计入",IF(Q136=0,"",S136/Q136),"") | U136: =IF(AA136="正常",U135+IF(AND(I136="已计入",OR(B136="买入",B136="定投",B136="转换转入")),E136,0),"") -> 82516.01 | V136: =IF(AA136="正常",V135+IF(AND(I136="已计入",OR(B136="卖出",B136="现金分红")),E136,0),"") -> 0 | W136: =IF(AA136="正常",W135+IF(I136="已计入",N136,0),"") -> 0 | X136: =IF(AA136="正常",X135+IF(I136="已计入",P136,0),"") -> 0 | Y136: =IF(I136="已计入",ROUND(R136+V136-U136,2),"") | Z136: =IF(AA136="正常",IF(I136="已计入",A136,Z135),"") -> 46247 | AA136: =IF(OR($AA$116="错误",COUNTIF($G$117:G136,"待修正")>0),"错误","正常") -> 正常 | AB136: =IF(AA136="正常",IF(I136="已计入",C136,AB135),"") -> 2.7686
E137: =IF(AND(ISNUMBER(C137),ISNUMBER(D137),ISNUMBER(F137)),IF(OR(B137="买入",B137="定投"),ROUND(C137*D137+F137,2),IF(B137="卖出",ROUND(C137*D137-F137,2),IF(B137="红利再投",0,""))),"") | G137: =IF(COUNTA(A137:D137,F137)=0,"",IF(I137="已计入","已录入","待修正")) | H137: =IF(COUNTA(A137:D137,F137)=0,"",IF(B137="红利再投","仅增加份额，不增加现金投入","金额由份额、净值和手续费推算")) | I137: =IF(COUNTA(A137:D137,F137)=0,"",IF(NOT(ISNUMBER(A137)),"缺少有效净值日期",IF(OR(A137<=0,A137<>INT(A137)),"净值日期无效",IF(OR(B137="转换转入",B137="现金分红"),"该类型需实际金额，五项录入不适用",IF(NOT(OR(OR(B137="买入",B137="定投"),B137="卖出",B137="红利再投")),"请选择交易类型",IF(NOT(ISNUMBER(C137)),"缺少成交净值",IF(C137<=0,"成交净值须大于零",IF(NOT(ISNUMBER(D137)),"缺少确认份额",IF(D137<=0,"确认份额须大于零",IF(NOT(ISNUMBER(F137)),"缺少手续费，无费用请填 0",IF(F137<0,"手续费不能为负",IF(AA136="错误","前行待修正",IF(A137<Z136,"日期需按成交顺序递增",IF(AND(B137="红利再投",F137<>0),"红利再投手续费应填 0",IF(AND(B137="红利再投",K136<=0),"红利再投前须有持仓",IF(AND(B137="卖出",D137>K136+0.000001),"卖出份额超过持仓",IF(AND(B137="卖出",F137>=C137*D137),"赎回费不能达到赎回总额",IF(NOT(ISNUMBER(E137)),"自动金额未生成，请检查五项输入",IF(NOT(OR(持仓总览!$C$7="利润优先",持仓总览!$C$7="本金优先")),"请选择卖出分配模式","已计入"))))))))))))))))))) | J137: =IF(AA137="正常",IF(I137="已计入",IF(OR(OR(B137="买入",B137="定投",B137="转换转入"),B137="红利再投"),D137,IF(B137="卖出",-D137,0)),0),"") -> 0 | K137: =IF(AA137="正常",ROUND(K136+J137,6),"") -> 34284.43 | L137: =IF(I137="已计入",ROUND(K136*C137,2),"") | M137: =IF(I137="已计入",IF(B137="卖出",MAX(0,L137-Q136-F137),IF(B137="现金分红",MAX(0,L137+E137-Q136),0)),"") | N137: =IF(I137="已计入",IF(AND(B137="卖出",持仓总览!$C$7="本金优先"),MAX(0,E137-Q136),IF(OR(B137="卖出",B137="现金分红"),MIN(E137,M137),0)),"") | O137: =IF(I137="已计入",IF(OR(B137="卖出",B137="现金分红"),MIN(Q136,MAX(0,E137-N137)),0),"") | P137: =IF(I137="已计入",IF(AND(B137="卖出",K137=0),MAX(0,Q136-O137),0),"") | Q137: =IF(AA137="正常",IF(I137="已计入",ROUND(Q136+IF(OR(B137="买入",B137="定投",B137="转换转入"),E137,0)-O137-P137,2),Q136),"") -> 82516.01 | R137: =IF(I137="已计入",ROUND(K137*C137,2),"") | S137: =IF(I137="已计入",ROUND(R137-Q137,2),"") | T137: =IF(I137="已计入",IF(Q137=0,"",S137/Q137),"") | U137: =IF(AA137="正常",U136+IF(AND(I137="已计入",OR(B137="买入",B137="定投",B137="转换转入")),E137,0),"") -> 82516.01 | V137: =IF(AA137="正常",V136+IF(AND(I137="已计入",OR(B137="卖出",B137="现金分红")),E137,0),"") -> 0 | W137: =IF(AA137="正常",W136+IF(I137="已计入",N137,0),"") -> 0 | X137: =IF(AA137="正常",X136+IF(I137="已计入",P137,0),"") -> 0 | Y137: =IF(I137="已计入",ROUND(R137+V137-U137,2),"") | Z137: =IF(AA137="正常",IF(I137="已计入",A137,Z136),"") -> 46247 | AA137: =IF(OR($AA$116="错误",COUNTIF($G$117:G137,"待修正")>0),"错误","正常") -> 正常 | AB137: =IF(AA137="正常",IF(I137="已计入",C137,AB136),"") -> 2.7686
E138: =IF(AND(ISNUMBER(C138),ISNUMBER(D138),ISNUMBER(F138)),IF(OR(B138="买入",B138="定投"),ROUND(C138*D138+F138,2),IF(B138="卖出",ROUND(C138*D138-F138,2),IF(B138="红利再投",0,""))),"") | G138: =IF(COUNTA(A138:D138,F138)=0,"",IF(I138="已计入","已录入","待修正")) | H138: =IF(COUNTA(A138:D138,F138)=0,"",IF(B138="红利再投","仅增加份额，不增加现金投入","金额由份额、净值和手续费推算")) | I138: =IF(COUNTA(A138:D138,F138)=0,"",IF(NOT(ISNUMBER(A138)),"缺少有效净值日期",IF(OR(A138<=0,A138<>INT(A138)),"净值日期无效",IF(OR(B138="转换转入",B138="现金分红"),"该类型需实际金额，五项录入不适用",IF(NOT(OR(OR(B138="买入",B138="定投"),B138="卖出",B138="红利再投")),"请选择交易类型",IF(NOT(ISNUMBER(C138)),"缺少成交净值",IF(C138<=0,"成交净值须大于零",IF(NOT(ISNUMBER(D138)),"缺少确认份额",IF(D138<=0,"确认份额须大于零",IF(NOT(ISNUMBER(F138)),"缺少手续费，无费用请填 0",IF(F138<0,"手续费不能为负",IF(AA137="错误","前行待修正",IF(A138<Z137,"日期需按成交顺序递增",IF(AND(B138="红利再投",F138<>0),"红利再投手续费应填 0",IF(AND(B138="红利再投",K137<=0),"红利再投前须有持仓",IF(AND(B138="卖出",D138>K137+0.000001),"卖出份额超过持仓",IF(AND(B138="卖出",F138>=C138*D138),"赎回费不能达到赎回总额",IF(NOT(ISNUMBER(E138)),"自动金额未生成，请检查五项输入",IF(NOT(OR(持仓总览!$C$7="利润优先",持仓总览!$C$7="本金优先")),"请选择卖出分配模式","已计入"))))))))))))))))))) | J138: =IF(AA138="正常",IF(I138="已计入",IF(OR(OR(B138="买入",B138="定投",B138="转换转入"),B138="红利再投"),D138,IF(B138="卖出",-D138,0)),0),"") -> 0 | K138: =IF(AA138="正常",ROUND(K137+J138,6),"") -> 34284.43 | L138: =IF(I138="已计入",ROUND(K137*C138,2),"") | M138: =IF(I138="已计入",IF(B138="卖出",MAX(0,L138-Q137-F138),IF(B138="现金分红",MAX(0,L138+E138-Q137),0)),"") | N138: =IF(I138="已计入",IF(AND(B138="卖出",持仓总览!$C$7="本金优先"),MAX(0,E138-Q137),IF(OR(B138="卖出",B138="现金分红"),MIN(E138,M138),0)),"") | O138: =IF(I138="已计入",IF(OR(B138="卖出",B138="现金分红"),MIN(Q137,MAX(0,E138-N138)),0),"") | P138: =IF(I138="已计入",IF(AND(B138="卖出",K138=0),MAX(0,Q137-O138),0),"") | Q138: =IF(AA138="正常",IF(I138="已计入",ROUND(Q137+IF(OR(B138="买入",B138="定投",B138="转换转入"),E138,0)-O138-P138,2),Q137),"") -> 82516.01 | R138: =IF(I138="已计入",ROUND(K138*C138,2),"") | S138: =IF(I138="已计入",ROUND(R138-Q138,2),"") | T138: =IF(I138="已计入",IF(Q138=0,"",S138/Q138),"") | U138: =IF(AA138="正常",U137+IF(AND(I138="已计入",OR(B138="买入",B138="定投",B138="转换转入")),E138,0),"") -> 82516.01 | V138: =IF(AA138="正常",V137+IF(AND(I138="已计入",OR(B138="卖出",B138="现金分红")),E138,0),"") -> 0 | W138: =IF(AA138="正常",W137+IF(I138="已计入",N138,0),"") -> 0 | X138: =IF(AA138="正常",X137+IF(I138="已计入",P138,0),"") -> 0 | Y138: =IF(I138="已计入",ROUND(R138+V138-U138,2),"") | Z138: =IF(AA138="正常",IF(I138="已计入",A138,Z137),"") -> 46247 | AA138: =IF(OR($AA$116="错误",COUNTIF($G$117:G138,"待修正")>0),"错误","正常") -> 正常 | AB138: =IF(AA138="正常",IF(I138="已计入",C138,AB137),"") -> 2.7686
E139: =IF(AND(ISNUMBER(C139),ISNUMBER(D139),ISNUMBER(F139)),IF(OR(B139="买入",B139="定投"),ROUND(C139*D139+F139,2),IF(B139="卖出",ROUND(C139*D139-F139,2),IF(B139="红利再投",0,""))),"") | G139: =IF(COUNTA(A139:D139,F139)=0,"",IF(I139="已计入","已录入","待修正")) | H139: =IF(COUNTA(A139:D139,F139)=0,"",IF(B139="红利再投","仅增加份额，不增加现金投入","金额由份额、净值和手续费推算")) | I139: =IF(COUNTA(A139:D139,F139)=0,"",IF(NOT(ISNUMBER(A139)),"缺少有效净值日期",IF(OR(A139<=0,A139<>INT(A139)),"净值日期无效",IF(OR(B139="转换转入",B139="现金分红"),"该类型需实际金额，五项录入不适用",IF(NOT(OR(OR(B139="买入",B139="定投"),B139="卖出",B139="红利再投")),"请选择交易类型",IF(NOT(ISNUMBER(C139)),"缺少成交净值",IF(C139<=0,"成交净值须大于零",IF(NOT(ISNUMBER(D139)),"缺少确认份额",IF(D139<=0,"确认份额须大于零",IF(NOT(ISNUMBER(F139)),"缺少手续费，无费用请填 0",IF(F139<0,"手续费不能为负",IF(AA138="错误","前行待修正",IF(A139<Z138,"日期需按成交顺序递增",IF(AND(B139="红利再投",F139<>0),"红利再投手续费应填 0",IF(AND(B139="红利再投",K138<=0),"红利再投前须有持仓",IF(AND(B139="卖出",D139>K138+0.000001),"卖出份额超过持仓",IF(AND(B139="卖出",F139>=C139*D139),"赎回费不能达到赎回总额",IF(NOT(ISNUMBER(E139)),"自动金额未生成，请检查五项输入",IF(NOT(OR(持仓总览!$C$7="利润优先",持仓总览!$C$7="本金优先")),"请选择卖出分配模式","已计入"))))))))))))))))))) | J139: =IF(AA139="正常",IF(I139="已计入",IF(OR(OR(B139="买入",B139="定投",B139="转换转入"),B139="红利再投"),D139,IF(B139="卖出",-D139,0)),0),"") -> 0 | K139: =IF(AA139="正常",ROUND(K138+J139,6),"") -> 34284.43 | L139: =IF(I139="已计入",ROUND(K138*C139,2),"") | M139: =IF(I139="已计入",IF(B139="卖出",MAX(0,L139-Q138-F139),IF(B139="现金分红",MAX(0,L139+E139-Q138),0)),"") | N139: =IF(I139="已计入",IF(AND(B139="卖出",持仓总览!$C$7="本金优先"),MAX(0,E139-Q138),IF(OR(B139="卖出",B139="现金分红"),MIN(E139,M139),0)),"") | O139: =IF(I139="已计入",IF(OR(B139="卖出",B139="现金分红"),MIN(Q138,MAX(0,E139-N139)),0),"") | P139: =IF(I139="已计入",IF(AND(B139="卖出",K139=0),MAX(0,Q138-O139),0),"") | Q139: =IF(AA139="正常",IF(I139="已计入",ROUND(Q138+IF(OR(B139="买入",B139="定投",B139="转换转入"),E139,0)-O139-P139,2),Q138),"") -> 82516.01 | R139: =IF(I139="已计入",ROUND(K139*C139,2),"") | S139: =IF(I139="已计入",ROUND(R139-Q139,2),"") | T139: =IF(I139="已计入",IF(Q139=0,"",S139/Q139),"") | U139: =IF(AA139="正常",U138+IF(AND(I139="已计入",OR(B139="买入",B139="定投",B139="转换转入")),E139,0),"") -> 82516.01 | V139: =IF(AA139="正常",V138+IF(AND(I139="已计入",OR(B139="卖出",B139="现金分红")),E139,0),"") -> 0 | W139: =IF(AA139="正常",W138+IF(I139="已计入",N139,0),"") -> 0 | X139: =IF(AA139="正常",X138+IF(I139="已计入",P139,0),"") -> 0 | Y139: =IF(I139="已计入",ROUND(R139+V139-U139,2),"") | Z139: =IF(AA139="正常",IF(I139="已计入",A139,Z138),"") -> 46247 | AA139: =IF(OR($AA$116="错误",COUNTIF($G$117:G139,"待修正")>0),"错误","正常") -> 正常 | AB139: =IF(AA139="正常",IF(I139="已计入",C139,AB138),"") -> 2.7686
E140: =IF(AND(ISNUMBER(C140),ISNUMBER(D140),ISNUMBER(F140)),IF(OR(B140="买入",B140="定投"),ROUND(C140*D140+F140,2),IF(B140="卖出",ROUND(C140*D140-F140,2),IF(B140="红利再投",0,""))),"") | G140: =IF(COUNTA(A140:D140,F140)=0,"",IF(I140="已计入","已录入","待修正")) | H140: =IF(COUNTA(A140:D140,F140)=0,"",IF(B140="红利再投","仅增加份额，不增加现金投入","金额由份额、净值和手续费推算")) | I140: =IF(COUNTA(A140:D140,F140)=0,"",IF(NOT(ISNUMBER(A140)),"缺少有效净值日期",IF(OR(A140<=0,A140<>INT(A140)),"净值日期无效",IF(OR(B140="转换转入",B140="现金分红"),"该类型需实际金额，五项录入不适用",IF(NOT(OR(OR(B140="买入",B140="定投"),B140="卖出",B140="红利再投")),"请选择交易类型",IF(NOT(ISNUMBER(C140)),"缺少成交净值",IF(C140<=0,"成交净值须大于零",IF(NOT(ISNUMBER(D140)),"缺少确认份额",IF(D140<=0,"确认份额须大于零",IF(NOT(ISNUMBER(F140)),"缺少手续费，无费用请填 0",IF(F140<0,"手续费不能为负",IF(AA139="错误","前行待修正",IF(A140<Z139,"日期需按成交顺序递增",IF(AND(B140="红利再投",F140<>0),"红利再投手续费应填 0",IF(AND(B140="红利再投",K139<=0),"红利再投前须有持仓",IF(AND(B140="卖出",D140>K139+0.000001),"卖出份额超过持仓",IF(AND(B140="卖出",F140>=C140*D140),"赎回费不能达到赎回总额",IF(NOT(ISNUMBER(E140)),"自动金额未生成，请检查五项输入",IF(NOT(OR(持仓总览!$C$7="利润优先",持仓总览!$C$7="本金优先")),"请选择卖出分配模式","已计入"))))))))))))))))))) | J140: =IF(AA140="正常",IF(I140="已计入",IF(OR(OR(B140="买入",B140="定投",B140="转换转入"),B140="红利再投"),D140,IF(B140="卖出",-D140,0)),0),"") -> 0 | K140: =IF(AA140="正常",ROUND(K139+J140,6),"") -> 34284.43 | L140: =IF(I140="已计入",ROUND(K139*C140,2),"") | M140: =IF(I140="已计入",IF(B140="卖出",MAX(0,L140-Q139-F140),IF(B140="现金分红",MAX(0,L140+E140-Q139),0)),"") | N140: =IF(I140="已计入",IF(AND(B140="卖出",持仓总览!$C$7="本金优先"),MAX(0,E140-Q139),IF(OR(B140="卖出",B140="现金分红"),MIN(E140,M140),0)),"") | O140: =IF(I140="已计入",IF(OR(B140="卖出",B140="现金分红"),MIN(Q139,MAX(0,E140-N140)),0),"") | P140: =IF(I140="已计入",IF(AND(B140="卖出",K140=0),MAX(0,Q139-O140),0),"") | Q140: =IF(AA140="正常",IF(I140="已计入",ROUND(Q139+IF(OR(B140="买入",B140="定投",B140="转换转入"),E140,0)-O140-P140,2),Q139),"") -> 82516.01 | R140: =IF(I140="已计入",ROUND(K140*C140,2),"") | S140: =IF(I140="已计入",ROUND(R140-Q140,2),"") | T140: =IF(I140="已计入",IF(Q140=0,"",S140/Q140),"") | U140: =IF(AA140="正常",U139+IF(AND(I140="已计入",OR(B140="买入",B140="定投",B140="转换转入")),E140,0),"") -> 82516.01 | V140: =IF(AA140="正常",V139+IF(AND(I140="已计入",OR(B140="卖出",B140="现金分红")),E140,0),"") -> 0 | W140: =IF(AA140="正常",W139+IF(I140="已计入",N140,0),"") -> 0 | X140: =IF(AA140="正常",X139+IF(I140="已计入",P140,0),"") -> 0 | Y140: =IF(I140="已计入",ROUND(R140+V140-U140,2),"") | Z140: =IF(AA140="正常",IF(I140="已计入",A140,Z139),"") -> 46247 | AA140: =IF(OR($AA$116="错误",COUNTIF($G$117:G140,"待修正")>0),"错误","正常") -> 正常 | AB140: =IF(AA140="正常",IF(I140="已计入",C140,AB139),"") -> 2.7686
E141: =IF(AND(ISNUMBER(C141),ISNUMBER(D141),ISNUMBER(F141)),IF(OR(B141="买入",B141="定投"),ROUND(C141*D141+F141,2),IF(B141="卖出",ROUND(C141*D141-F141,2),IF(B141="红利再投",0,""))),"") | G141: =IF(COUNTA(A141:D141,F141)=0,"",IF(I141="已计入","已录入","待修正")) | H141: =IF(COUNTA(A141:D141,F141)=0,"",IF(B141="红利再投","仅增加份额，不增加现金投入","金额由份额、净值和手续费推算")) | I141: =IF(COUNTA(A141:D141,F141)=0,"",IF(NOT(ISNUMBER(A141)),"缺少有效净值日期",IF(OR(A141<=0,A141<>INT(A141)),"净值日期无效",IF(OR(B141="转换转入",B141="现金分红"),"该类型需实际金额，五项录入不适用",IF(NOT(OR(OR(B141="买入",B141="定投"),B141="卖出",B141="红利再投")),"请选择交易类型",IF(NOT(ISNUMBER(C141)),"缺少成交净值",IF(C141<=0,"成交净值须大于零",IF(NOT(ISNUMBER(D141)),"缺少确认份额",IF(D141<=0,"确认份额须大于零",IF(NOT(ISNUMBER(F141)),"缺少手续费，无费用请填 0",IF(F141<0,"手续费不能为负",IF(AA140="错误","前行待修正",IF(A141<Z140,"日期需按成交顺序递增",IF(AND(B141="红利再投",F141<>0),"红利再投手续费应填 0",IF(AND(B141="红利再投",K140<=0),"红利再投前须有持仓",IF(AND(B141="卖出",D141>K140+0.000001),"卖出份额超过持仓",IF(AND(B141="卖出",F141>=C141*D141),"赎回费不能达到赎回总额",IF(NOT(ISNUMBER(E141)),"自动金额未生成，请检查五项输入",IF(NOT(OR(持仓总览!$C$7="利润优先",持仓总览!$C$7="本金优先")),"请选择卖出分配模式","已计入"))))))))))))))))))) | J141: =IF(AA141="正常",IF(I141="已计入",IF(OR(OR(B141="买入",B141="定投",B141="转换转入"),B141="红利再投"),D141,IF(B141="卖出",-D141,0)),0),"") -> 0 | K141: =IF(AA141="正常",ROUND(K140+J141,6),"") -> 34284.43 | L141: =IF(I141="已计入",ROUND(K140*C141,2),"") | M141: =IF(I141="已计入",IF(B141="卖出",MAX(0,L141-Q140-F141),IF(B141="现金分红",MAX(0,L141+E141-Q140),0)),"") | N141: =IF(I141="已计入",IF(AND(B141="卖出",持仓总览!$C$7="本金优先"),MAX(0,E141-Q140),IF(OR(B141="卖出",B141="现金分红"),MIN(E141,M141),0)),"") | O141: =IF(I141="已计入",IF(OR(B141="卖出",B141="现金分红"),MIN(Q140,MAX(0,E141-N141)),0),"") | P141: =IF(I141="已计入",IF(AND(B141="卖出",K141=0),MAX(0,Q140-O141),0),"") | Q141: =IF(AA141="正常",IF(I141="已计入",ROUND(Q140+IF(OR(B141="买入",B141="定投",B141="转换转入"),E141,0)-O141-P141,2),Q140),"") -> 82516.01 | R141: =IF(I141="已计入",ROUND(K141*C141,2),"") | S141: =IF(I141="已计入",ROUND(R141-Q141,2),"") | T141: =IF(I141="已计入",IF(Q141=0,"",S141/Q141),"") | U141: =IF(AA141="正常",U140+IF(AND(I141="已计入",OR(B141="买入",B141="定投",B141="转换转入")),E141,0),"") -> 82516.01 | V141: =IF(AA141="正常",V140+IF(AND(I141="已计入",OR(B141="卖出",B141="现金分红")),E141,0),"") -> 0 | W141: =IF(AA141="正常",W140+IF(I141="已计入",N141,0),"") -> 0 | X141: =IF(AA141="正常",X140+IF(I141="已计入",P141,0),"") -> 0 | Y141: =IF(I141="已计入",ROUND(R141+V141-U141,2),"") | Z141: =IF(AA141="正常",IF(I141="已计入",A141,Z140),"") -> 46247 | AA141: =IF(OR($AA$116="错误",COUNTIF($G$117:G141,"待修正")>0),"错误","正常") -> 正常 | AB141: =IF(AA141="正常",IF(I141="已计入",C141,AB140),"") -> 2.7686
E142: =IF(AND(ISNUMBER(C142),ISNUMBER(D142),ISNUMBER(F142)),IF(OR(B142="买入",B142="定投"),ROUND(C142*D142+F142,2),IF(B142="卖出",ROUND(C142*D142-F142,2),IF(B142="红利再投",0,""))),"") | G142: =IF(COUNTA(A142:D142,F142)=0,"",IF(I142="已计入","已录入","待修正")) | H142: =IF(COUNTA(A142:D142,F142)=0,"",IF(B142="红利再投","仅增加份额，不增加现金投入","金额由份额、净值和手续费推算")) | I142: =IF(COUNTA(A142:D142,F142)=0,"",IF(NOT(ISNUMBER(A142)),"缺少有效净值日期",IF(OR(A142<=0,A142<>INT(A142)),"净值日期无效",IF(OR(B142="转换转入",B142="现金分红"),"该类型需实际金额，五项录入不适用",IF(NOT(OR(OR(B142="买入",B142="定投"),B142="卖出",B142="红利再投")),"请选择交易类型",IF(NOT(ISNUMBER(C142)),"缺少成交净值",IF(C142<=0,"成交净值须大于零",IF(NOT(ISNUMBER(D142)),"缺少确认份额",IF(D142<=0,"确认份额须大于零",IF(NOT(ISNUMBER(F142)),"缺少手续费，无费用请填 0",IF(F142<0,"手续费不能为负",IF(AA141="错误","前行待修正",IF(A142<Z141,"日期需按成交顺序递增",IF(AND(B142="红利再投",F142<>0),"红利再投手续费应填 0",IF(AND(B142="红利再投",K141<=0),"红利再投前须有持仓",IF(AND(B142="卖出",D142>K141+0.000001),"卖出份额超过持仓",IF(AND(B142="卖出",F142>=C142*D142),"赎回费不能达到赎回总额",IF(NOT(ISNUMBER(E142)),"自动金额未生成，请检查五项输入",IF(NOT(OR(持仓总览!$C$7="利润优先",持仓总览!$C$7="本金优先")),"请选择卖出分配模式","已计入"))))))))))))))))))) | J142: =IF(AA142="正常",IF(I142="已计入",IF(OR(OR(B142="买入",B142="定投",B142="转换转入"),B142="红利再投"),D142,IF(B142="卖出",-D142,0)),0),"") -> 0 | K142: =IF(AA142="正常",ROUND(K141+J142,6),"") -> 34284.43 | L142: =IF(I142="已计入",ROUND(K141*C142,2),"") | M142: =IF(I142="已计入",IF(B142="卖出",MAX(0,L142-Q141-F142),IF(B142="现金分红",MAX(0,L142+E142-Q141),0)),"") | N142: =IF(I142="已计入",IF(AND(B142="卖出",持仓总览!$C$7="本金优先"),MAX(0,E142-Q141),IF(OR(B142="卖出",B142="现金分红"),MIN(E142,M142),0)),"") | O142: =IF(I142="已计入",IF(OR(B142="卖出",B142="现金分红"),MIN(Q141,MAX(0,E142-N142)),0),"") | P142: =IF(I142="已计入",IF(AND(B142="卖出",K142=0),MAX(0,Q141-O142),0),"") | Q142: =IF(AA142="正常",IF(I142="已计入",ROUND(Q141+IF(OR(B142="买入",B142="定投",B142="转换转入"),E142,0)-O142-P142,2),Q141),"") -> 82516.01 | R142: =IF(I142="已计入",ROUND(K142*C142,2),"") | S142: =IF(I142="已计入",ROUND(R142-Q142,2),"") | T142: =IF(I142="已计入",IF(Q142=0,"",S142/Q142),"") | U142: =IF(AA142="正常",U141+IF(AND(I142="已计入",OR(B142="买入",B142="定投",B142="转换转入")),E142,0),"") -> 82516.01 | V142: =IF(AA142="正常",V141+IF(AND(I142="已计入",OR(B142="卖出",B142="现金分红")),E142,0),"") -> 0 | W142: =IF(AA142="正常",W141+IF(I142="已计入",N142,0),"") -> 0 | X142: =IF(AA142="正常",X141+IF(I142="已计入",P142,0),"") -> 0 | Y142: =IF(I142="已计入",ROUND(R142+V142-U142,2),"") | Z142: =IF(AA142="正常",IF(I142="已计入",A142,Z141),"") -> 46247 | AA142: =IF(OR($AA$116="错误",COUNTIF($G$117:G142,"待修正")>0),"错误","正常") -> 正常 | AB142: =IF(AA142="正常",IF(I142="已计入",C142,AB141),"") -> 2.7686
E143: =IF(AND(ISNUMBER(C143),ISNUMBER(D143),ISNUMBER(F143)),IF(OR(B143="买入",B143="定投"),ROUND(C143*D143+F143,2),IF(B143="卖出",ROUND(C143*D143-F143,2),IF(B143="红利再投",0,""))),"") | G143: =IF(COUNTA(A143:D143,F143)=0,"",IF(I143="已计入","已录入","待修正")) | H143: =IF(COUNTA(A143:D143,F143)=0,"",IF(B143="红利再投","仅增加份额，不增加现金投入","金额由份额、净值和手续费推算")) | I143: =IF(COUNTA(A143:D143,F143)=0,"",IF(NOT(ISNUMBER(A143)),"缺少有效净值日期",IF(OR(A143<=0,A143<>INT(A143)),"净值日期无效",IF(OR(B143="转换转入",B143="现金分红"),"该类型需实际金额，五项录入不适用",IF(NOT(OR(OR(B143="买入",B143="定投"),B143="卖出",B143="红利再投")),"请选择交易类型",IF(NOT(ISNUMBER(C143)),"缺少成交净值",IF(C143<=0,"成交净值须大于零",IF(NOT(ISNUMBER(D143)),"缺少确认份额",IF(D143<=0,"确认份额须大于零",IF(NOT(ISNUMBER(F143)),"缺少手续费，无费用请填 0",IF(F143<0,"手续费不能为负",IF(AA142="错误","前行待修正",IF(A143<Z142,"日期需按成交顺序递增",IF(AND(B143="红利再投",F143<>0),"红利再投手续费应填 0",IF(AND(B143="红利再投",K142<=0),"红利再投前须有持仓",IF(AND(B143="卖出",D143>K142+0.000001),"卖出份额超过持仓",IF(AND(B143="卖出",F143>=C143*D143),"赎回费不能达到赎回总额",IF(NOT(ISNUMBER(E143)),"自动金额未生成，请检查五项输入",IF(NOT(OR(持仓总览!$C$7="利润优先",持仓总览!$C$7="本金优先")),"请选择卖出分配模式","已计入"))))))))))))))))))) | J143: =IF(AA143="正常",IF(I143="已计入",IF(OR(OR(B143="买入",B143="定投",B143="转换转入"),B143="红利再投"),D143,IF(B143="卖出",-D143,0)),0),"") -> 0 | K143: =IF(AA143="正常",ROUND(K142+J143,6),"") -> 34284.43 | L143: =IF(I143="已计入",ROUND(K142*C143,2),"") | M143: =IF(I143="已计入",IF(B143="卖出",MAX(0,L143-Q142-F143),IF(B143="现金分红",MAX(0,L143+E143-Q142),0)),"") | N143: =IF(I143="已计入",IF(AND(B143="卖出",持仓总览!$C$7="本金优先"),MAX(0,E143-Q142),IF(OR(B143="卖出",B143="现金分红"),MIN(E143,M143),0)),"") | O143: =IF(I143="已计入",IF(OR(B143="卖出",B143="现金分红"),MIN(Q142,MAX(0,E143-N143)),0),"") | P143: =IF(I143="已计入",IF(AND(B143="卖出",K143=0),MAX(0,Q142-O143),0),"") | Q143: =IF(AA143="正常",IF(I143="已计入",ROUND(Q142+IF(OR(B143="买入",B143="定投",B143="转换转入"),E143,0)-O143-P143,2),Q142),"") -> 82516.01 | R143: =IF(I143="已计入",ROUND(K143*C143,2),"") | S143: =IF(I143="已计入",ROUND(R143-Q143,2),"") | T143: =IF(I143="已计入",IF(Q143=0,"",S143/Q143),"") | U143: =IF(AA143="正常",U142+IF(AND(I143="已计入",OR(B143="买入",B143="定投",B143="转换转入")),E143,0),"") -> 82516.01 | V143: =IF(AA143="正常",V142+IF(AND(I143="已计入",OR(B143="卖出",B143="现金分红")),E143,0),"") -> 0 | W143: =IF(AA143="正常",W142+IF(I143="已计入",N143,0),"") -> 0 | X143: =IF(AA143="正常",X142+IF(I143="已计入",P143,0),"") -> 0 | Y143: =IF(I143="已计入",ROUND(R143+V143-U143,2),"") | Z143: =IF(AA143="正常",IF(I143="已计入",A143,Z142),"") -> 46247 | AA143: =IF(OR($AA$116="错误",COUNTIF($G$117:G143,"待修正")>0),"错误","正常") -> 正常 | AB143: =IF(AA143="正常",IF(I143="已计入",C143,AB142),"") -> 2.7686
E144: =IF(AND(ISNUMBER(C144),ISNUMBER(D144),ISNUMBER(F144)),IF(OR(B144="买入",B144="定投"),ROUND(C144*D144+F144,2),IF(B144="卖出",ROUND(C144*D144-F144,2),IF(B144="红利再投",0,""))),"") | G144: =IF(COUNTA(A144:D144,F144)=0,"",IF(I144="已计入","已录入","待修正")) | H144: =IF(COUNTA(A144:D144,F144)=0,"",IF(B144="红利再投","仅增加份额，不增加现金投入","金额由份额、净值和手续费推算")) | I144: =IF(COUNTA(A144:D144,F144)=0,"",IF(NOT(ISNUMBER(A144)),"缺少有效净值日期",IF(OR(A144<=0,A144<>INT(A144)),"净值日期无效",IF(OR(B144="转换转入",B144="现金分红"),"该类型需实际金额，五项录入不适用",IF(NOT(OR(OR(B144="买入",B144="定投"),B144="卖出",B144="红利再投")),"请选择交易类型",IF(NOT(ISNUMBER(C144)),"缺少成交净值",IF(C144<=0,"成交净值须大于零",IF(NOT(ISNUMBER(D144)),"缺少确认份额",IF(D144<=0,"确认份额须大于零",IF(NOT(ISNUMBER(F144)),"缺少手续费，无费用请填 0",IF(F144<0,"手续费不能为负",IF(AA143="错误","前行待修正",IF(A144<Z143,"日期需按成交顺序递增",IF(AND(B144="红利再投",F144<>0),"红利再投手续费应填 0",IF(AND(B144="红利再投",K143<=0),"红利再投前须有持仓",IF(AND(B144="卖出",D144>K143+0.000001),"卖出份额超过持仓",IF(AND(B144="卖出",F144>=C144*D144),"赎回费不能达到赎回总额",IF(NOT(ISNUMBER(E144)),"自动金额未生成，请检查五项输入",IF(NOT(OR(持仓总览!$C$7="利润优先",持仓总览!$C$7="本金优先")),"请选择卖出分配模式","已计入"))))))))))))))))))) | J144: =IF(AA144="正常",IF(I144="已计入",IF(OR(OR(B144="买入",B144="定投",B144="转换转入"),B144="红利再投"),D144,IF(B144="卖出",-D144,0)),0),"") -> 0 | K144: =IF(AA144="正常",ROUND(K143+J144,6),"") -> 34284.43 | L144: =IF(I144="已计入",ROUND(K143*C144,2),"") | M144: =IF(I144="已计入",IF(B144="卖出",MAX(0,L144-Q143-F144),IF(B144="现金分红",MAX(0,L144+E144-Q143),0)),"") | N144: =IF(I144="已计入",IF(AND(B144="卖出",持仓总览!$C$7="本金优先"),MAX(0,E144-Q143),IF(OR(B144="卖出",B144="现金分红"),MIN(E144,M144),0)),"") | O144: =IF(I144="已计入",IF(OR(B144="卖出",B144="现金分红"),MIN(Q143,MAX(0,E144-N144)),0),"") | P144: =IF(I144="已计入",IF(AND(B144="卖出",K144=0),MAX(0,Q143-O144),0),"") | Q144: =IF(AA144="正常",IF(I144="已计入",ROUND(Q143+IF(OR(B144="买入",B144="定投",B144="转换转入"),E144,0)-O144-P144,2),Q143),"") -> 82516.01 | R144: =IF(I144="已计入",ROUND(K144*C144,2),"") | S144: =IF(I144="已计入",ROUND(R144-Q144,2),"") | T144: =IF(I144="已计入",IF(Q144=0,"",S144/Q144),"") | U144: =IF(AA144="正常",U143+IF(AND(I144="已计入",OR(B144="买入",B144="定投",B144="转换转入")),E144,0),"") -> 82516.01 | V144: =IF(AA144="正常",V143+IF(AND(I144="已计入",OR(B144="卖出",B144="现金分红")),E144,0),"") -> 0 | W144: =IF(AA144="正常",W143+IF(I144="已计入",N144,0),"") -> 0 | X144: =IF(AA144="正常",X143+IF(I144="已计入",P144,0),"") -> 0 | Y144: =IF(I144="已计入",ROUND(R144+V144-U144,2),"") | Z144: =IF(AA144="正常",IF(I144="已计入",A144,Z143),"") -> 46247 | AA144: =IF(OR($AA$116="错误",COUNTIF($G$117:G144,"待修正")>0),"错误","正常") -> 正常 | AB144: =IF(AA144="正常",IF(I144="已计入",C144,AB143),"") -> 2.7686
E145: =IF(AND(ISNUMBER(C145),ISNUMBER(D145),ISNUMBER(F145)),IF(OR(B145="买入",B145="定投"),ROUND(C145*D145+F145,2),IF(B145="卖出",ROUND(C145*D145-F145,2),IF(B145="红利再投",0,""))),"") | G145: =IF(COUNTA(A145:D145,F145)=0,"",IF(I145="已计入","已录入","待修正")) | H145: =IF(COUNTA(A145:D145,F145)=0,"",IF(B145="红利再投","仅增加份额，不增加现金投入","金额由份额、净值和手续费推算")) | I145: =IF(COUNTA(A145:D145,F145)=0,"",IF(NOT(ISNUMBER(A145)),"缺少有效净值日期",IF(OR(A145<=0,A145<>INT(A145)),"净值日期无效",IF(OR(B145="转换转入",B145="现金分红"),"该类型需实际金额，五项录入不适用",IF(NOT(OR(OR(B145="买入",B145="定投"),B145="卖出",B145="红利再投")),"请选择交易类型",IF(NOT(ISNUMBER(C145)),"缺少成交净值",IF(C145<=0,"成交净值须大于零",IF(NOT(ISNUMBER(D145)),"缺少确认份额",IF(D145<=0,"确认份额须大于零",IF(NOT(ISNUMBER(F145)),"缺少手续费，无费用请填 0",IF(F145<0,"手续费不能为负",IF(AA144="错误","前行待修正",IF(A145<Z144,"日期需按成交顺序递增",IF(AND(B145="红利再投",F145<>0),"红利再投手续费应填 0",IF(AND(B145="红利再投",K144<=0),"红利再投前须有持仓",IF(AND(B145="卖出",D145>K144+0.000001),"卖出份额超过持仓",IF(AND(B145="卖出",F145>=C145*D145),"赎回费不能达到赎回总额",IF(NOT(ISNUMBER(E145)),"自动金额未生成，请检查五项输入",IF(NOT(OR(持仓总览!$C$7="利润优先",持仓总览!$C$7="本金优先")),"请选择卖出分配模式","已计入"))))))))))))))))))) | J145: =IF(AA145="正常",IF(I145="已计入",IF(OR(OR(B145="买入",B145="定投",B145="转换转入"),B145="红利再投"),D145,IF(B145="卖出",-D145,0)),0),"") -> 0 | K145: =IF(AA145="正常",ROUND(K144+J145,6),"") -> 34284.43 | L145: =IF(I145="已计入",ROUND(K144*C145,2),"") | M145: =IF(I145="已计入",IF(B145="卖出",MAX(0,L145-Q144-F145),IF(B145="现金分红",MAX(0,L145+E145-Q144),0)),"") | N145: =IF(I145="已计入",IF(AND(B145="卖出",持仓总览!$C$7="本金优先"),MAX(0,E145-Q144),IF(OR(B145="卖出",B145="现金分红"),MIN(E145,M145),0)),"") | O145: =IF(I145="已计入",IF(OR(B145="卖出",B145="现金分红"),MIN(Q144,MAX(0,E145-N145)),0),"") | P145: =IF(I145="已计入",IF(AND(B145="卖出",K145=0),MAX(0,Q144-O145),0),"") | Q145: =IF(AA145="正常",IF(I145="已计入",ROUND(Q144+IF(OR(B145="买入",B145="定投",B145="转换转入"),E145,0)-O145-P145,2),Q144),"") -> 82516.01 | R145: =IF(I145="已计入",ROUND(K145*C145,2),"") | S145: =IF(I145="已计入",ROUND(R145-Q145,2),"") | T145: =IF(I145="已计入",IF(Q145=0,"",S145/Q145),"") | U145: =IF(AA145="正常",U144+IF(AND(I145="已计入",OR(B145="买入",B145="定投",B145="转换转入")),E145,0),"") -> 82516.01 | V145: =IF(AA145="正常",V144+IF(AND(I145="已计入",OR(B145="卖出",B145="现金分红")),E145,0),"") -> 0 | W145: =IF(AA145="正常",W144+IF(I145="已计入",N145,0),"") -> 0 | X145: =IF(AA145="正常",X144+IF(I145="已计入",P145,0),"") -> 0 | Y145: =IF(I145="已计入",ROUND(R145+V145-U145,2),"") | Z145: =IF(AA145="正常",IF(I145="已计入",A145,Z144),"") -> 46247 | AA145: =IF(OR($AA$116="错误",COUNTIF($G$117:G145,"待修正")>0),"错误","正常") -> 正常 | AB145: =IF(AA145="正常",IF(I145="已计入",C145,AB144),"") -> 2.7686
E146: =IF(AND(ISNUMBER(C146),ISNUMBER(D146),ISNUMBER(F146)),IF(OR(B146="买入",B146="定投"),ROUND(C146*D146+F146,2),IF(B146="卖出",ROUND(C146*D146-F146,2),IF(B146="红利再投",0,""))),"") | G146: =IF(COUNTA(A146:D146,F146)=0,"",IF(I146="已计入","已录入","待修正")) | H146: =IF(COUNTA(A146:D146,F146)=0,"",IF(B146="红利再投","仅增加份额，不增加现金投入","金额由份额、净值和手续费推算")) | I146: =IF(COUNTA(A146:D146,F146)=0,"",IF(NOT(ISNUMBER(A146)),"缺少有效净值日期",IF(OR(A146<=0,A146<>INT(A146)),"净值日期无效",IF(OR(B146="转换转入",B146="现金分红"),"该类型需实际金额，五项录入不适用",IF(NOT(OR(OR(B146="买入",B146="定投"),B146="卖出",B146="红利再投")),"请选择交易类型",IF(NOT(ISNUMBER(C146)),"缺少成交净值",IF(C146<=0,"成交净值须大于零",IF(NOT(ISNUMBER(D146)),"缺少确认份额",IF(D146<=0,"确认份额须大于零",IF(NOT(ISNUMBER(F146)),"缺少手续费，无费用请填 0",IF(F146<0,"手续费不能为负",IF(AA145="错误","前行待修正",IF(A146<Z145,"日期需按成交顺序递增",IF(AND(B146="红利再投",F146<>0),"红利再投手续费应填 0",IF(AND(B146="红利再投",K145<=0),"红利再投前须有持仓",IF(AND(B146="卖出",D146>K145+0.000001),"卖出份额超过持仓",IF(AND(B146="卖出",F146>=C146*D146),"赎回费不能达到赎回总额",IF(NOT(ISNUMBER(E146)),"自动金额未生成，请检查五项输入",IF(NOT(OR(持仓总览!$C$7="利润优先",持仓总览!$C$7="本金优先")),"请选择卖出分配模式","已计入"))))))))))))))))))) | J146: =IF(AA146="正常",IF(I146="已计入",IF(OR(OR(B146="买入",B146="定投",B146="转换转入"),B146="红利再投"),D146,IF(B146="卖出",-D146,0)),0),"") -> 0 | K146: =IF(AA146="正常",ROUND(K145+J146,6),"") -> 34284.43 | L146: =IF(I146="已计入",ROUND(K145*C146,2),"") | M146: =IF(I146="已计入",IF(B146="卖出",MAX(0,L146-Q145-F146),IF(B146="现金分红",MAX(0,L146+E146-Q145),0)),"") | N146: =IF(I146="已计入",IF(AND(B146="卖出",持仓总览!$C$7="本金优先"),MAX(0,E146-Q145),IF(OR(B146="卖出",B146="现金分红"),MIN(E146,M146),0)),"") | O146: =IF(I146="已计入",IF(OR(B146="卖出",B146="现金分红"),MIN(Q145,MAX(0,E146-N146)),0),"") | P146: =IF(I146="已计入",IF(AND(B146="卖出",K146=0),MAX(0,Q145-O146),0),"") | Q146: =IF(AA146="正常",IF(I146="已计入",ROUND(Q145+IF(OR(B146="买入",B146="定投",B146="转换转入"),E146,0)-O146-P146,2),Q145),"") -> 82516.01 | R146: =IF(I146="已计入",ROUND(K146*C146,2),"") | S146: =IF(I146="已计入",ROUND(R146-Q146,2),"") | T146: =IF(I146="已计入",IF(Q146=0,"",S146/Q146),"") | U146: =IF(AA146="正常",U145+IF(AND(I146="已计入",OR(B146="买入",B146="定投",B146="转换转入")),E146,0),"") -> 82516.01 | V146: =IF(AA146="正常",V145+IF(AND(I146="已计入",OR(B146="卖出",B146="现金分红")),E146,0),"") -> 0 | W146: =IF(AA146="正常",W145+IF(I146="已计入",N146,0),"") -> 0 | X146: =IF(AA146="正常",X145+IF(I146="已计入",P146,0),"") -> 0 | Y146: =IF(I146="已计入",ROUND(R146+V146-U146,2),"") | Z146: =IF(AA146="正常",IF(I146="已计入",A146,Z145),"") -> 46247 | AA146: =IF(OR($AA$116="错误",COUNTIF($G$117:G146,"待修正")>0),"错误","正常") -> 正常 | AB146: =IF(AA146="正常",IF(I146="已计入",C146,AB145),"") -> 2.7686
E147: =IF(AND(ISNUMBER(C147),ISNUMBER(D147),ISNUMBER(F147)),IF(OR(B147="买入",B147="定投"),ROUND(C147*D147+F147,2),IF(B147="卖出",ROUND(C147*D147-F147,2),IF(B147="红利再投",0,""))),"") | G147: =IF(COUNTA(A147:D147,F147)=0,"",IF(I147="已计入","已录入","待修正")) | H147: =IF(COUNTA(A147:D147,F147)=0,"",IF(B147="红利再投","仅增加份额，不增加现金投入","金额由份额、净值和手续费推算")) | I147: =IF(COUNTA(A147:D147,F147)=0,"",IF(NOT(ISNUMBER(A147)),"缺少有效净值日期",IF(OR(A147<=0,A147<>INT(A147)),"净值日期无效",IF(OR(B147="转换转入",B147="现金分红"),"该类型需实际金额，五项录入不适用",IF(NOT(OR(OR(B147="买入",B147="定投"),B147="卖出",B147="红利再投")),"请选择交易类型",IF(NOT(ISNUMBER(C147)),"缺少成交净值",IF(C147<=0,"成交净值须大于零",IF(NOT(ISNUMBER(D147)),"缺少确认份额",IF(D147<=0,"确认份额须大于零",IF(NOT(ISNUMBER(F147)),"缺少手续费，无费用请填 0",IF(F147<0,"手续费不能为负",IF(AA146="错误","前行待修正",IF(A147<Z146,"日期需按成交顺序递增",IF(AND(B147="红利再投",F147<>0),"红利再投手续费应填 0",IF(AND(B147="红利再投",K146<=0),"红利再投前须有持仓",IF(AND(B147="卖出",D147>K146+0.000001),"卖出份额超过持仓",IF(AND(B147="卖出",F147>=C147*D147),"赎回费不能达到赎回总额",IF(NOT(ISNUMBER(E147)),"自动金额未生成，请检查五项输入",IF(NOT(OR(持仓总览!$C$7="利润优先",持仓总览!$C$7="本金优先")),"请选择卖出分配模式","已计入"))))))))))))))))))) | J147: =IF(AA147="正常",IF(I147="已计入",IF(OR(OR(B147="买入",B147="定投",B147="转换转入"),B147="红利再投"),D147,IF(B147="卖出",-D147,0)),0),"") -> 0 | K147: =IF(AA147="正常",ROUND(K146+J147,6),"") -> 34284.43 | L147: =IF(I147="已计入",ROUND(K146*C147,2),"") | M147: =IF(I147="已计入",IF(B147="卖出",MAX(0,L147-Q146-F147),IF(B147="现金分红",MAX(0,L147+E147-Q146),0)),"") | N147: =IF(I147="已计入",IF(AND(B147="卖出",持仓总览!$C$7="本金优先"),MAX(0,E147-Q146),IF(OR(B147="卖出",B147="现金分红"),MIN(E147,M147),0)),"") | O147: =IF(I147="已计入",IF(OR(B147="卖出",B147="现金分红"),MIN(Q146,MAX(0,E147-N147)),0),"") | P147: =IF(I147="已计入",IF(AND(B147="卖出",K147=0),MAX(0,Q146-O147),0),"") | Q147: =IF(AA147="正常",IF(I147="已计入",ROUND(Q146+IF(OR(B147="买入",B147="定投",B147="转换转入"),E147,0)-O147-P147,2),Q146),"") -> 82516.01 | R147: =IF(I147="已计入",ROUND(K147*C147,2),"") | S147: =IF(I147="已计入",ROUND(R147-Q147,2),"") | T147: =IF(I147="已计入",IF(Q147=0,"",S147/Q147),"") | U147: =IF(AA147="正常",U146+IF(AND(I147="已计入",OR(B147="买入",B147="定投",B147="转换转入")),E147,0),"") -> 82516.01 | V147: =IF(AA147="正常",V146+IF(AND(I147="已计入",OR(B147="卖出",B147="现金分红")),E147,0),"") -> 0 | W147: =IF(AA147="正常",W146+IF(I147="已计入",N147,0),"") -> 0 | X147: =IF(AA147="正常",X146+IF(I147="已计入",P147,0),"") -> 0 | Y147: =IF(I147="已计入",ROUND(R147+V147-U147,2),"") | Z147: =IF(AA147="正常",IF(I147="已计入",A147,Z146),"") -> 46247 | AA147: =IF(OR($AA$116="错误",COUNTIF($G$117:G147,"待修正")>0),"错误","正常") -> 正常 | AB147: =IF(AA147="正常",IF(I147="已计入",C147,AB146),"") -> 2.7686
... E506: =IF(AND(ISNUMBER(C506),ISNUMBER(D506),ISNUMBER(F506)),IF(OR(B506="买入",B506="定投"),ROUND(C506*D506+F506,2),IF(B506="卖出",ROUND(C506*D506-F506,2),IF(B506="红利再投",0,""))),"") | G506: =IF(COUNTA(A506:D506,F506)=0,"",IF(I506="已计入","已录入","待修正")) | H506: =IF(COUNTA(A506:D506,F506)=0,"",IF(B506="红利再投","仅增加份额，不增加现金投入","金额由份额、净值和手续费推算")) | I506: =IF(COUNTA(A506:D506,F506)=0,"",IF(NOT(ISNUMBER(A506)),"缺少有效净值日期",IF(OR(A506<=0,A506<>INT(A506)),"净值日期无效",IF(OR(B506="转换转入",B506="现金分红"),"该类型需实际金额，五项录入不适用",IF(NOT(OR(OR(B506="买入",B506="定投"),B506="卖出",B506="红利再投")),"请选择交易类型",IF(NOT(ISNUMBER(C506)),"缺少成交净值",IF(C506<=0,"成交净值须大于零",IF(NOT(ISNUMBER(D506)),"缺少确认份额",IF(D506<=0,"确认份额须大于零",IF(NOT(ISNUMBER(F506)),"缺少手续费，无费用请填 0",IF(F506<0,"手续费不能为负",IF(AA505="错误","前行待修正",IF(A506<Z505,"日期需按成交顺序递增",IF(AND(B506="红利再投",F506<>0),"红利再投手续费应填 0",IF(AND(B506="红利再投",K505<=0),"红利再投前须有持仓",IF(AND(B506="卖出",D506>K505+0.000001),"卖出份额超过持仓",IF(AND(B506="卖出",F506>=C506*D506),"赎回费不能达到赎回总额",IF(NOT(ISNUMBER(E506)),"自动金额未生成，请检查五项输入",IF(NOT(OR(持仓总览!$C$7="利润优先",持仓总览!$C$7="本金优先")),"请选择卖出分配模式","已计入"))))))))))))))))))) | J506: =IF(AA506="正常",IF(I506="已计入",IF(OR(OR(B506="买入",B506="定投",B506="转换转入"),B506="红利再投"),D506,IF(B506="卖出",-D506,0)),0),"") -> 0 | K506: =IF(AA506="正常",ROUND(K505+J506,6),"") -> 34284.43 | L506: =IF(I506="已计入",ROUND(K505*C506,2),"") | M506: =IF(I506="已计入",IF(B506="卖出",MAX(0,L506-Q505-F506),IF(B506="现金分红",MAX(0,L506+E506-Q505),0)),"") | N506: =IF(I506="已计入",IF(AND(B506="卖出",持仓总览!$C$7="本金优先"),MAX(0,E506-Q505),IF(OR(B506="卖出",B506="现金分红"),MIN(E506,M506),0)),"") | O506: =IF(I506="已计入",IF(OR(B506="卖出",B506="现金分红"),MIN(Q505,MAX(0,E506-N506)),0),"") | P506: =IF(I506="已计入",IF(AND(B506="卖出",K506=0),MAX(0,Q505-O506),0),"") | Q506: =IF(AA506="正常",IF(I506="已计入",ROUND(Q505+IF(OR(B506="买入",B506="定投",B506="转换转入"),E506,0)-O506-P506,2),Q505),"") -> 82516.01 | R506: =IF(I506="已计入",ROUND(K506*C506,2),"") | S506: =IF(I506="已计入",ROUND(R506-Q506,2),"") | T506: =IF(I506="已计入",IF(Q506=0,"",S506/Q506),"") | U506: =IF(AA506="正常",U505+IF(AND(I506="已计入",OR(B506="买入",B506="定投",B506="转换转入")),E506,0),"") -> 82516.01 | V506: =IF(AA506="正常",V505+IF(AND(I506="已计入",OR(B506="卖出",B506="现金分红")),E506,0),"") -> 0 | W506: =IF(AA506="正常",W505+IF(I506="已计入",N506,0),"") -> 0 | X506: =IF(AA506="正常",X505+IF(I506="已计入",P506,0),"") -> 0 | Y506: =IF(I506="已计入",ROUND(R506+V506-U506,2),"") | Z506: =IF(AA506="正常",IF(I506="已计入",A506,Z505),"") -> 46247 | AA506: =IF(OR($AA$116="错误",COUNTIF($G$117:G506,"待修正")>0),"错误","正常") -> 正常 | AB506: =IF(AA506="正常",IF(I506="已计入",C506,AB505),"") -> 2.7686
